Workbook

Sheet Дашборд
A1: BADK LIVE — РЕЖИМНА БАЛІСТИЧНА МОДЕЛЬ
A2: Цільова дата | B2: ='Розрахунок'!B2 -> 46307 | D2: День | E2: ='Розрахунок'!B3 -> Понеділок | G2: Версія | H2: ='Налаштування'!G2 -> v2.1-shrink | I2: Цільова ніч | J2: =CHOOSE(WEEKDAY(B2-1,2),"ПН","ВТ","СР","ЧТ","ПТ","СБ","НД")&"→"&CHOOSE(WEEKDAY(B2,2),"ПН","ВТ","СР","ЧТ","ПТ","СБ","НД") -> НД→ПН | K2: Дата після 00:00 | L2: =B2 -> 46307 | M2: Фаза | N2: ='Контроль моделі'!B28 -> PREVIEW | O2: Audit cutoff | P2: ='Розрахунок'!K2 -> 46297 | Q2: ='Контроль моделі'!B31 -> STALE_HISTORY
A4: Місто | B4: R56 | C4: R90 | D4: R180 | E4: R365 | F4: Історична база | G4: Домінантний день режиму | H4: Сила домінанти | I4: Зсув режиму | J4: Домінантний день = цільовому? | K4: Оперативний % | L4: Остання атака | M4: Support R56 • R365 | N4: 95% CI R365 | O4: A-only R365 | P4: Evidence
A5: ='Налаштування'!R39 -> Київ | B5: =IF(IFERROR(VLOOKUP($A5,'Налаштування'!$F$39:$K$52,6,FALSE),"ONBOARDING")="ACTIVE",'Розрахунок'!B5,"") -> 0 | C5: =IF(IFERROR(VLOOKUP($A5,'Налаштування'!$F$39:$K$52,6,FALSE),"ONBOARDING")="ACTIVE",'Розрахунок'!C5,"") -> 0 | D5: =IF(IFERROR(VLOOKUP($A5,'Налаштування'!$F$39:$K$52,6,FALSE),"ONBOARDING")="ACTIVE",'Розрахунок'!D5,"") -> 0.08 | E5: =IF(IFERROR(VLOOKUP($A5,'Налаштування'!$F$39:$K$52,6,FALSE),"ONBOARDING")="ACTIVE",'Розрахунок'!E5,"") -> 0.038461538 | F5: =IF(IFERROR(VLOOKUP($A5,'Налаштування'!$F$39:$K$52,6,FALSE),"ONBOARDING")="ACTIVE",'Розрахунок'!F5,"") -> 0.11679186 | G5: =IF(IFERROR(VLOOKUP($A5,'Налаштування'!$F$39:$K$52,6,FALSE),"ONBOARDING")="ACTIVE",'Розрахунок'!G5,"BACKFILL 365") -> Четвер | H5: =IF(IFERROR(VLOOKUP($A5,'Налаштування'!$F$39:$K$52,6,FALSE),"ONBOARDING")="ACTIVE",'Розрахунок'!H5,"") -> 0.33333333 | I5: =IF(IFERROR(VLOOKUP($A5,'Налаштування'!$F$39:$K$52,6,FALSE),"ONBOARDING")="ACTIVE",'Розрахунок'!J5,"—") -> — | J5: =IF(IFERROR(VLOOKUP($A5,'Налаштування'!$F$39:$K$52,6,FALSE),"ONBOARDING")="ACTIVE",'Розрахунок'!K5,"—") -> Ні | K5: {=IF(IFERROR(VLOOKUP($A5,'Налаштування'!$F$39:$K$52,6,FALSE),"ONBOARDING")="ACTIVE",INDEX('Оперативна оцінка'!$B$24:$N$24,1,MATCH($A5,'Оперативна оцінка'!$B$4:$N$4,0)),"")} | L5: =IFERROR(__xludf.DUMMYFUNCTION("IF(IFERROR(VLOOKUP($A5,'Налаштування'!$F$39:$K$52,6,FALSE),""ONBOARDING"")<>""ACTIVE"",""BACKFILL"",IFERROR(MAX(FILTER(DATEVALUE('Реєстр'!$D$2:$D$5000),'Реєстр'!$B$2:$B$5000=$A5,'Реєстр'!$C$2:$C$5000=""Балістика / швидкісні ракети"",REGEXMATCH('Реєстр'!$A"&"C$2:$AC$5000,""^Включено""))),""—""))"),46305.0) -> 46305 | M5: =IF(IFERROR(VLOOKUP($A5,'Налаштування'!$F$39:$K$52,6,FALSE),"ONBOARDING")="ACTIVE",'Розрахунок'!O5,"") -> 0/8 • 2/52 | N5: =IF(IFERROR(VLOOKUP($A5,'Налаштування'!$F$39:$K$52,6,FALSE),"ONBOARDING")="ACTIVE",TEXT('Розрахунок'!Q5,"0.0%")&"–"&TEXT('Розрахунок'!R5,"0.0%"),"") -> 1,1%–13,0% | O5: =IF(IFERROR(VLOOKUP($A5,'Налаштування'!$F$39:$K$52,6,FALSE),"ONBOARDING")="ACTIVE",'Розрахунок'!S5,"") -> 0.038461538 | P5: =IFERROR("2src "&TEXT(COUNTIFS('Реєстр'!$B$2:$B$5000,$A5,'Реєстр'!$C$2:$C$5000,"Балістика / швидкісні ракети",'Реєстр'!$AC$2:$AC$5000,"Включено*",'Реєстр'!$AR$2:$AR$5000,"MODEL-365",'Реєстр'!$O$2:$O$5000,"<>")/COUNTIFS('Реєстр'!$B$2:$B$5000,$A5,'Реєстр'!$C$2:$C$5000,"Балістика / швидкісні ракети",'Реєстр'!$AC$2:$AC$5000,"Включено*",'Реєстр'!$AR$2:$AR$5000,"MODEL-365"),"0%")&" • B "&TEXT(COUNTIFS('Реєстр'!$B$2:$B$5000,$A5,'Реєстр'!$C$2:$C$5000,"Балістика / швидкісні ракети",'Реєстр'!$AC$2:$AC$5000,"Включено*",'Реєстр'!$AR$2:$AR$5000,"MODEL-365",'Реєстр'!$L$2:$L$5000,"B*")/COUNTIFS('Реєстр'!$B$2:$B$5000,$A5,'Реєстр'!$C$2:$C$5000,"Балістика / швидкісні ракети",'Реєстр'!$AC$2:$AC$5000,"Включено*",'Реєстр'!$AR$2:$AR$5000,"MODEL-365"),"0%"),"—") -> 2src 100% • B 4%
A6: ='Налаштування'!R40 -> Дніпро | B6: =IF(IFERROR(VLOOKUP($A6,'Налаштування'!$F$39:$K$52,6,FALSE),"ONBOARDING")="ACTIVE",'Розрахунок'!B6,"") -> 0 | C6: =IF(IFERROR(VLOOKUP($A6,'Налаштування'!$F$39:$K$52,6,FALSE),"ONBOARDING")="ACTIVE",'Розрахунок'!C6,"") -> 0 | D6: =IF(IFERROR(VLOOKUP($A6,'Налаштування'!$F$39:$K$52,6,FALSE),"ONBOARDING")="ACTIVE",'Розрахунок'!D6,"") -> 0.08 | E6: =IF(IFERROR(VLOOKUP($A6,'Налаштування'!$F$39:$K$52,6,FALSE),"ONBOARDING")="ACTIVE",'Розрахунок'!E6,"") -> 0.076923077 | F6: =IF(IFERROR(VLOOKUP($A6,'Налаштування'!$F$39:$K$52,6,FALSE),"ONBOARDING")="ACTIVE",'Розрахунок'!F6,"") -> 0.049345885 | G6: =IF(IFERROR(VLOOKUP($A6,'Налаштування'!$F$39:$K$52,6,FALSE),"ONBOARDING")="ACTIVE",'Розрахунок'!G6,"BACKFILL 365") -> Вівторок/Середа/Субота • по 1 (нічия) | H6: =IF(IFERROR(VLOOKUP($A6,'Налаштування'!$F$39:$K$52,6,FALSE),"ONBOARDING")="ACTIVE",'Розрахунок'!H6,"") -> 0 | I6: =IF(IFERROR(VLOOKUP($A6,'Налаштування'!$F$39:$K$52,6,FALSE),"ONBOARDING")="ACTIVE",'Розрахунок'!J6,"—") -> — | J6: =IF(IFERROR(VLOOKUP($A6,'Налаштування'!$F$39:$K$52,6,FALSE),"ONBOARDING")="ACTIVE",'Розрахунок'!K6,"—") -> — | K6: {=IF(IFERROR(VLOOKUP($A6,'Налаштування'!$F$39:$K$52,6,FALSE),"ONBOARDING")="ACTIVE",INDEX('Оперативна оцінка'!$B$24:$N$24,1,MATCH($A6,'Оперативна оцінка'!$B$4:$N$4,0)),"")} | L6: =IFERROR(__xludf.DUMMYFUNCTION("IF(IFERROR(VLOOKUP($A6,'Налаштування'!$F$39:$K$52,6,FALSE),""ONBOARDING"")<>""ACTIVE"",""BACKFILL"",IFERROR(MAX(FILTER(DATEVALUE('Реєстр'!$D$2:$D$5000),'Реєстр'!$B$2:$B$5000=$A6,'Реєстр'!$C$2:$C$5000=""Балістика / швидкісні ракети"",REGEXMATCH('Реєстр'!$A"&"C$2:$AC$5000,""^Включено""))),""—""))"),46302.0) -> 46302 | M6: =IF(IFERROR(VLOOKUP($A6,'Налаштування'!$F$39:$K$52,6,FALSE),"ONBOARDING")="ACTIVE",'Розрахунок'!O6,"") -> 0/8 • 4/52 | N6: =IF(IFERROR(VLOOKUP($A6,'Налаштування'!$F$39:$K$52,6,FALSE),"ONBOARDING")="ACTIVE",TEXT('Розрахунок'!Q6,"0.0%")&"–"&TEXT('Розрахунок'!R6,"0.0%"),"") -> 3,0%–18,2% | O6: =IF(IFERROR(VLOOKUP($A6,'Налаштування'!$F$39:$K$52,6,FALSE),"ONBOARDING")="ACTIVE",'Розрахунок'!S6,"") -> 0.038461538 | P6: =IFERROR("2src "&TEXT(COUNTIFS('Реєстр'!$B$2:$B$5000,$A6,'Реєстр'!$C$2:$C$5000,"Балістика / швидкісні ракети",'Реєстр'!$AC$2:$AC$5000,"Включено*",'Реєстр'!$AR$2:$AR$5000,"MODEL-365",'Реєстр'!$O$2:$O$5000,"<>")/COUNTIFS('Реєстр'!$B$2:$B$5000,$A6,'Реєстр'!$C$2:$C$5000,"Балістика / швидкісні ракети",'Реєстр'!$AC$2:$AC$5000,"Включено*",'Реєстр'!$AR$2:$AR$5000,"MODEL-365"),"0%")&" • B "&TEXT(COUNTIFS('Реєстр'!$B$2:$B$5000,$A6,'Реєстр'!$C$2:$C$5000,"Балістика / швидкісні ракети",'Реєстр'!$AC$2:$AC$5000,"Включено*",'Реєстр'!$AR$2:$AR$5000,"MODEL-365",'Реєстр'!$L$2:$L$5000,"B*")/COUNTIFS('Реєстр'!$B$2:$B$5000,$A6,'Реєстр'!$C$2:$C$5000,"Балістика / швидкісні ракети",'Реєстр'!$AC$2:$AC$5000,"Включено*",'Реєстр'!$AR$2:$AR$5000,"MODEL-365"),"0%"),"—") -> 2src 100% • B 27%
A7: ='Налаштування'!R41 -> Житомир | B7: =IF(IFERROR(VLOOKUP($A7,'Налаштування'!$F$39:$K$52,6,FALSE),"ONBOARDING")="ACTIVE",'Розрахунок'!B7,"") -> 0 | C7: =IF(IFERROR(VLOOKUP($A7,'Налаштування'!$F$39:$K$52,6,FALSE),"ONBOARDING")="ACTIVE",'Розрахунок'!C7,"") -> 0 | D7: =IF(IFERROR(VLOOKUP($A7,'Налаштування'!$F$39:$K$52,6,FALSE),"ONBOARDING")="ACTIVE",'Розрахунок'!D7,"") -> 0 | E7: =IF(IFERROR(VLOOKUP($A7,'Налаштування'!$F$39:$K$52,6,FALSE),"ONBOARDING")="ACTIVE",'Розрахунок'!E7,"") -> 0 | F7: =IF(IFERROR(VLOOKUP($A7,'Налаштування'!$F$39:$K$52,6,FALSE),"ONBOARDING")="ACTIVE",'Розрахунок'!F7,"") -> 0.00029077646 | G7: =IF(IFERROR(VLOOKUP($A7,'Налаштування'!$F$39:$K$52,6,FALSE),"ONBOARDING")="ACTIVE",'Розрахунок'!G7,"BACKFILL 365") -> Немає | H7: =IF(IFERROR(VLOOKUP($A7,'Налаштування'!$F$39:$K$52,6,FALSE),"ONBOARDING")="ACTIVE",'Розрахунок'!H7,"") -> 0 | I7: =IF(IFERROR(VLOOKUP($A7,'Налаштування'!$F$39:$K$52,6,FALSE),"ONBOARDING")="ACTIVE",'Розрахунок'!J7,"—") -> — | J7: =IF(IFERROR(VLOOKUP($A7,'Налаштування'!$F$39:$K$52,6,FALSE),"ONBOARDING")="ACTIVE",'Розрахунок'!K7,"—") -> — | K7: {=IF(IFERROR(VLOOKUP($A7,'Налаштування'!$F$39:$K$52,6,FALSE),"ONBOARDING")="ACTIVE",INDEX('Оперативна оцінка'!$B$24:$N$24,1,MATCH($A7,'Оперативна оцінка'!$B$4:$N$4,0)),"")} | L7: =IFERROR(__xludf.DUMMYFUNCTION("IF(IFERROR(VLOOKUP($A7,'Налаштування'!$F$39:$K$52,6,FALSE),""ONBOARDING"")<>""ACTIVE"",""BACKFILL"",IFERROR(MAX(FILTER(DATEVALUE('Реєстр'!$D$2:$D$5000),'Реєстр'!$B$2:$B$5000=$A7,'Реєстр'!$C$2:$C$5000=""Балістика / швидкісні ракети"",REGEXMATCH('Реєстр'!$A"&"C$2:$AC$5000,""^Включено""))),""—""))"),45963.0) -> 45963 | M7: =IF(IFERROR(VLOOKUP($A7,'Налаштування'!$F$39:$K$52,6,FALSE),"ONBOARDING")="ACTIVE",'Розрахунок'!O7,"") -> 0/8 • 0/52 | N7: =IF(IFERROR(VLOOKUP($A7,'Налаштування'!$F$39:$K$52,6,FALSE),"ONBOARDING")="ACTIVE",TEXT('Розрахунок'!Q7,"0.0%")&"–"&TEXT('Розрахунок'!R7,"0.0%"),"") -> 0,0%–6,9% | O7: =IF(IFERROR(VLOOKUP($A7,'Налаштування'!$F$39:$K$52,6,FALSE),"ONBOARDING")="ACTIVE",'Розрахунок'!S7,"") -> 0 | P7: =IFERROR("2src "&TEXT(COUNTIFS('Реєстр'!$B$2:$B$5000,$A7,'Реєстр'!$C$2:$C$5000,"Балістика / швидкісні ракети",'Реєстр'!$AC$2:$AC$5000,"Включено*",'Реєстр'!$AR$2:$AR$5000,"MODEL-365",'Реєстр'!$O$2:$O$5000,"<>")/COUNTIFS('Реєстр'!$B$2:$B$5000,$A7,'Реєстр'!$C$2:$C$5000,"Балістика / швидкісні ракети",'Реєстр'!$AC$2:$AC$5000,"Включено*",'Реєстр'!$AR$2:$AR$5000,"MODEL-365"),"0%")&" • B "&TEXT(COUNTIFS('Реєстр'!$B$2:$B$5000,$A7,'Реєстр'!$C$2:$C$5000,"Балістика / швидкісні ракети",'Реєстр'!$AC$2:$AC$5000,"Включено*",'Реєстр'!$AR$2:$AR$5000,"MODEL-365",'Реєстр'!$L$2:$L$5000,"B*")/COUNTIFS('Реєстр'!$B$2:$B$5000,$A7,'Реєстр'!$C$2:$C$5000,"Балістика / швидкісні ракети",'Реєстр'!$AC$2:$AC$5000,"Включено*",'Реєстр'!$AR$2:$AR$5000,"MODEL-365"),"0%"),"—") -> 2src 100% • B 0%
A8: ='Налаштування'!R42 -> Запоріжжя | B8: =IF(IFERROR(VLOOKUP($A8,'Налаштування'!$F$39:$K$52,6,FALSE),"ONBOARDING")="ACTIVE",'Розрахунок'!B8,"") -> 0 | C8: =IF(IFERROR(VLOOKUP($A8,'Налаштування'!$F$39:$K$52,6,FALSE),"ONBOARDING")="ACTIVE",'Розрахунок'!C8,"") -> 0 | D8: =IF(IFERROR(VLOOKUP($A8,'Налаштування'!$F$39:$K$52,6,FALSE),"ONBOARDING")="ACTIVE",'Розрахунок'!D8,"") -> 0 | E8: =IF(IFERROR(VLOOKUP($A8,'Налаштування'!$F$39:$K$52,6,FALSE),"ONBOARDING")="ACTIVE",'Розрахунок'!E8,"") -> 0 | F8: =IF(IFERROR(VLOOKUP($A8,'Налаштування'!$F$39:$K$52,6,FALSE),"ONBOARDING")="ACTIVE",'Розрахунок'!F8,"") -> 0.026823138 | G8: =IF(IFERROR(VLOOKUP($A8,'Налаштування'!$F$39:$K$52,6,FALSE),"ONBOARDING")="ACTIVE",'Розрахунок'!G8,"BACKFILL 365") -> Середа/Четвер • по 2 (нічия) | H8: =IF(IFERROR(VLOOKUP($A8,'Налаштування'!$F$39:$K$52,6,FALSE),"ONBOARDING")="ACTIVE",'Розрахунок'!H8,"") -> 0 | I8: =IF(IFERROR(VLOOKUP($A8,'Налаштування'!$F$39:$K$52,6,FALSE),"ONBOARDING")="ACTIVE",'Розрахунок'!J8,"—") -> — | J8: =IF(IFERROR(VLOOKUP($A8,'Налаштування'!$F$39:$K$52,6,FALSE),"ONBOARDING")="ACTIVE",'Розрахунок'!K8,"—") -> — | K8: {=IF(IFERROR(VLOOKUP($A8,'Налаштування'!$F$39:$K$52,6,FALSE),"ONBOARDING")="ACTIVE",INDEX('Оперативна оцінка'!$B$24:$N$24,1,MATCH($A8,'Оперативна оцінка'!$B$4:$N$4,0)),"")} | L8: =IFERROR(__xludf.DUMMYFUNCTION("IF(IFERROR(VLOOKUP($A8,'Налаштування'!$F$39:$K$52,6,FALSE),""ONBOARDING"")<>""ACTIVE"",""BACKFILL"",IFERROR(MAX(FILTER(DATEVALUE('Реєстр'!$D$2:$D$5000),'Реєстр'!$B$2:$B$5000=$A8,'Реєстр'!$C$2:$C$5000=""Балістика / швидкісні ракети"",REGEXMATCH('Реєстр'!$A"&"C$2:$AC$5000,""^Включено""))),""—""))"),46302.0) -> 46302 | M8: =IF(IFERROR(VLOOKUP($A8,'Налаштування'!$F$39:$K$52,6,FALSE),"ONBOARDING")="ACTIVE",'Розрахунок'!O8,"") -> 0/8 • 0/52 | N8: =IF(IFERROR(VLOOKUP($A8,'Налаштування'!$F$39:$K$52,6,FALSE),"ONBOARDING")="ACTIVE",TEXT('Розрахунок'!Q8,"0.0%")&"–"&TEXT('Розрахунок'!R8,"0.0%"),"") -> 0,0%–6,9% | O8: =IF(IFERROR(VLOOKUP($A8,'Налаштування'!$F$39:$K$52,6,FALSE),"ONBOARDING")="ACTIVE",'Розрахунок'!S8,"") -> 0 | P8: =IFERROR("2src "&TEXT(COUNTIFS('Реєстр'!$B$2:$B$5000,$A8,'Реєстр'!$C$2:$C$5000,"Балістика / швидкісні ракети",'Реєстр'!$AC$2:$AC$5000,"Включено*",'Реєстр'!$AR$2:$AR$5000,"MODEL-365",'Реєстр'!$O$2:$O$5000,"<>")/COUNTIFS('Реєстр'!$B$2:$B$5000,$A8,'Реєстр'!$C$2:$C$5000,"Балістика / швидкісні ракети",'Реєстр'!$AC$2:$AC$5000,"Включено*",'Реєстр'!$AR$2:$AR$5000,"MODEL-365"),"0%")&" • B "&TEXT(COUNTIFS('Реєстр'!$B$2:$B$5000,$A8,'Реєстр'!$C$2:$C$5000,"Балістика / швидкісні ракети",'Реєстр'!$AC$2:$AC$5000,"Включено*",'Реєстр'!$AR$2:$AR$5000,"MODEL-365",'Реєстр'!$L$2:$L$5000,"B*")/COUNTIFS('Реєстр'!$B$2:$B$5000,$A8,'Реєстр'!$C$2:$C$5000,"Балістика / швидкісні ракети",'Реєстр'!$AC$2:$AC$5000,"Включено*",'Реєстр'!$AR$2:$AR$5000,"MODEL-365"),"0%"),"—") -> 2src 100% • B 46%
A9: ='Налаштування'!R43 -> Миколаїв | B9: =IF(IFERROR(VLOOKUP($A9,'Налаштування'!$F$39:$K$52,6,FALSE),"ONBOARDING")="ACTIVE",'Розрахунок'!B9,"") -> 0 | C9: =IF(IFERROR(VLOOKUP($A9,'Налаштування'!$F$39:$K$52,6,FALSE),"ONBOARDING")="ACTIVE",'Розрахунок'!C9,"") -> 0 | D9: =IF(IFERROR(VLOOKUP($A9,'Налаштування'!$F$39:$K$52,6,FALSE),"ONBOARDING")="ACTIVE",'Розрахунок'!D9,"") -> 0 | E9: =IF(IFERROR(VLOOKUP($A9,'Налаштування'!$F$39:$K$52,6,FALSE),"ONBOARDING")="ACTIVE",'Розрахунок'!E9,"") -> 0 | F9: =IF(IFERROR(VLOOKUP($A9,'Налаштування'!$F$39:$K$52,6,FALSE),"ONBOARDING")="ACTIVE",'Розрахунок'!F9,"") -> 0.0089819532 | G9: =IF(IFERROR(VLOOKUP($A9,'Налаштування'!$F$39:$K$52,6,FALSE),"ONBOARDING")="ACTIVE",'Розрахунок'!G9,"BACKFILL 365") -> Середа/П’ятниця • по 1 (нічия) | H9: =IF(IFERROR(VLOOKUP($A9,'Налаштування'!$F$39:$K$52,6,FALSE),"ONBOARDING")="ACTIVE",'Розрахунок'!H9,"") -> 0 | I9: =IF(IFERROR(VLOOKUP($A9,'Налаштування'!$F$39:$K$52,6,FALSE),"ONBOARDING")="ACTIVE",'Розрахунок'!J9,"—") -> — | J9: =IF(IFERROR(VLOOKUP($A9,'Налаштування'!$F$39:$K$52,6,FALSE),"ONBOARDING")="ACTIVE",'Розрахунок'!K9,"—") -> — | K9: {=IF(IFERROR(VLOOKUP($A9,'Налаштування'!$F$39:$K$52,6,FALSE),"ONBOARDING")="ACTIVE",INDEX('Оперативна оцінка'!$B$24:$N$24,1,MATCH($A9,'Оперативна оцінка'!$B$4:$N$4,0)),"")} | L9: =IFERROR(__xludf.DUMMYFUNCTION("IF(IFERROR(VLOOKUP($A9,'Налаштування'!$F$39:$K$52,6,FALSE),""ONBOARDING"")<>""ACTIVE"",""BACKFILL"",IFERROR(MAX(FILTER(DATEVALUE('Реєстр'!$D$2:$D$5000),'Реєстр'!$B$2:$B$5000=$A9,'Реєстр'!$C$2:$C$5000=""Балістика / швидкісні ракети"",REGEXMATCH('Реєстр'!$A"&"C$2:$AC$5000,""^Включено""))),""—""))"),46297.0) -> 46297 | M9: =IF(IFERROR(VLOOKUP($A9,'Налаштування'!$F$39:$K$52,6,FALSE),"ONBOARDING")="ACTIVE",'Розрахунок'!O9,"") -> 0/8 • 0/52 | N9: =IF(IFERROR(VLOOKUP($A9,'Налаштування'!$F$39:$K$52,6,FALSE),"ONBOARDING")="ACTIVE",TEXT('Розрахунок'!Q9,"0.0%")&"–"&TEXT('Розрахунок'!R9,"0.0%"),"") -> 0,0%–6,9% | O9: =IF(IFERROR(VLOOKUP($A9,'Налаштування'!$F$39:$K$52,6,FALSE),"ONBOARDING")="ACTIVE",'Розрахунок'!S9,"") -> 0 | P9: =IFERROR("2src "&TEXT(COUNTIFS('Реєстр'!$B$2:$B$5000,$A9,'Реєстр'!$C$2:$C$5000,"Балістика / швидкісні ракети",'Реєстр'!$AC$2:$AC$5000,"Включено*",'Реєстр'!$AR$2:$AR$5000,"MODEL-365",'Реєстр'!$O$2:$O$5000,"<>")/COUNTIFS('Реєстр'!$B$2:$B$5000,$A9,'Реєстр'!$C$2:$C$5000,"Балістика / швидкісні ракети",'Реєстр'!$AC$2:$AC$5000,"Включено*",'Реєстр'!$AR$2:$AR$5000,"MODEL-365"),"0%")&" • B "&TEXT(COUNTIFS('Реєстр'!$B$2:$B$5000,$A9,'Реєстр'!$C$2:$C$5000,"Балістика / швидкісні ракети",'Реєстр'!$AC$2:$AC$5000,"Включено*",'Реєстр'!$AR$2:$AR$5000,"MODEL-365",'Реєстр'!$L$2:$L$5000,"B*")/COUNTIFS('Реєстр'!$B$2:$B$5000,$A9,'Реєстр'!$C$2:$C$5000,"Балістика / швидкісні ракети",'Реєстр'!$AC$2:$AC$5000,"Включено*",'Реєстр'!$AR$2:$AR$5000,"MODEL-365"),"0%"),"—") -> 2src 100% • B 40%
A10: ='Налаштування'!R44 -> Одеса | B10: =IF(IFERROR(VLOOKUP($A10,'Налаштування'!$F$39:$K$52,6,FALSE),"ONBOARDING")="ACTIVE",'Розрахунок'!B10,"") -> 0 | C10: =IF(IFERROR(VLOOKUP($A10,'Налаштування'!$F$39:$K$52,6,FALSE),"ONBOARDING")="ACTIVE",'Розрахунок'!C10,"") -> 0 | D10: =IF(IFERROR(VLOOKUP($A10,'Налаштування'!$F$39:$K$52,6,FALSE),"ONBOARDING")="ACTIVE",'Розрахунок'!D10,"") -> 0.04 | E10: =IF(IFERROR(VLOOKUP($A10,'Налаштування'!$F$39:$K$52,6,FALSE),"ONBOARDING")="ACTIVE",'Розрахунок'!E10,"") -> 0.076923077 | F10: =IF(IFERROR(VLOOKUP($A10,'Налаштування'!$F$39:$K$52,6,FALSE),"ONBOARDING")="ACTIVE",'Розрахунок'!F10,"") -> 0.061666566 | G10: =IF(IFERROR(VLOOKUP($A10,'Налаштування'!$F$39:$K$52,6,FALSE),"ONBOARDING")="ACTIVE",'Розрахунок'!G10,"BACKFILL 365") -> Вівторок/Середа/Четвер • по 1 (нічия) | H10: =IF(IFERROR(VLOOKUP($A10,'Налаштування'!$F$39:$K$52,6,FALSE),"ONBOARDING")="ACTIVE",'Розрахунок'!H10,"") -> 0 | I10: =IF(IFERROR(VLOOKUP($A10,'Налаштування'!$F$39:$K$52,6,FALSE),"ONBOARDING")="ACTIVE",'Розрахунок'!J10,"—") -> — | J10: =IF(IFERROR(VLOOKUP($A10,'Налаштування'!$F$39:$K$52,6,FALSE),"ONBOARDING")="ACTIVE",'Розрахунок'!K10,"—") -> — | K10: {=IF(IFERROR(VLOOKUP($A10,'Налаштування'!$F$39:$K$52,6,FALSE),"ONBOARDING")="ACTIVE",INDEX('Оперативна оцінка'!$B$24:$N$24,1,MATCH($A10,'Оперативна оцінка'!$B$4:$N$4,0)),"")} | L10: =IFERROR(__xludf.DUMMYFUNCTION("IF(IFERROR(VLOOKUP($A10,'Налаштування'!$F$39:$K$52,6,FALSE),""ONBOARDING"")<>""ACTIVE"",""BACKFILL"",IFERROR(MAX(FILTER(DATEVALUE('Реєстр'!$D$2:$D$5000),'Реєстр'!$B$2:$B$5000=$A10,'Реєстр'!$C$2:$C$5000=""Балістика / швидкісні ракети"",REGEXMATCH('Реєстр'!"&"$AC$2:$AC$5000,""^Включено""))),""—""))"),46289.0) -> 46289 | M10: =IF(IFERROR(VLOOKUP($A10,'Налаштування'!$F$39:$K$52,6,FALSE),"ONBOARDING")="ACTIVE",'Розрахунок'!O10,"") -> 0/8 • 4/52 | N10: =IF(IFERROR(VLOOKUP($A10,'Налаштування'!$F$39:$K$52,6,FALSE),"ONBOARDING")="ACTIVE",TEXT('Розрахунок'!Q10,"0.0%")&"–"&TEXT('Розрахунок'!R10,"0.0%"),"") -> 3,0%–18,2% | O10: =IF(IFERROR(VLOOKUP($A10,'Налаштування'!$F$39:$K$52,6,FALSE),"ONBOARDING")="ACTIVE",'Розрахунок'!S10,"") -> 0.076923077 | P10: =IFERROR("2src "&TEXT(COUNTIFS('Реєстр'!$B$2:$B$5000,$A10,'Реєстр'!$C$2:$C$5000,"Балістика / швидкісні ракети",'Реєстр'!$AC$2:$AC$5000,"Включено*",'Реєстр'!$AR$2:$AR$5000,"MODEL-365",'Реєстр'!$O$2:$O$5000,"<>")/COUNTIFS('Реєстр'!$B$2:$B$5000,$A10,'Реєстр'!$C$2:$C$5000,"Балістика / швидкісні ракети",'Реєстр'!$AC$2:$AC$5000,"Включено*",'Реєстр'!$AR$2:$AR$5000,"MODEL-365"),"0%")&" • B "&TEXT(COUNTIFS('Реєстр'!$B$2:$B$5000,$A10,'Реєстр'!$C$2:$C$5000,"Балістика / швидкісні ракети",'Реєстр'!$AC$2:$AC$5000,"Включено*",'Реєстр'!$AR$2:$AR$5000,"MODEL-365",'Реєстр'!$L$2:$L$5000,"B*")/COUNTIFS('Реєстр'!$B$2:$B$5000,$A10,'Реєстр'!$C$2:$C$5000,"Балістика / швидкісні ракети",'Реєстр'!$AC$2:$AC$5000,"Включено*",'Реєстр'!$AR$2:$AR$5000,"MODEL-365"),"0%"),"—") -> 2src 100% • B 12%
A11: ='Налаштування'!R45 -> Харків | B11: =IF(IFERROR(VLOOKUP($A11,'Налаштування'!$F$39:$K$52,6,FALSE),"ONBOARDING")="ACTIVE",'Розрахунок'!B11,"") -> 0 | C11: =IF(IFERROR(VLOOKUP($A11,'Налаштування'!$F$39:$K$52,6,FALSE),"ONBOARDING")="ACTIVE",'Розрахунок'!C11,"") -> 0 | D11: =IF(IFERROR(VLOOKUP($A11,'Налаштування'!$F$39:$K$52,6,FALSE),"ONBOARDING")="ACTIVE",'Розрахунок'!D11,"") -> 0.12 | E11: =IF(IFERROR(VLOOKUP($A11,'Налаштування'!$F$39:$K$52,6,FALSE),"ONBOARDING")="ACTIVE",'Розрахунок'!E11,"") -> 0.057692308 | F11: =IF(IFERROR(VLOOKUP($A11,'Налаштування'!$F$39:$K$52,6,FALSE),"ONBOARDING")="ACTIVE",'Розрахунок'!F11,"") -> 0.042414339 | G11: =IF(IFERROR(VLOOKUP($A11,'Налаштування'!$F$39:$K$52,6,FALSE),"ONBOARDING")="ACTIVE",'Розрахунок'!G11,"BACKFILL 365") -> Немає | H11: =IF(IFERROR(VLOOKUP($A11,'Налаштування'!$F$39:$K$52,6,FALSE),"ONBOARDING")="ACTIVE",'Розрахунок'!H11,"") -> 0 | I11: =IF(IFERROR(VLOOKUP($A11,'Налаштування'!$F$39:$K$52,6,FALSE),"ONBOARDING")="ACTIVE",'Розрахунок'!J11,"—") -> — | J11: =IF(IFERROR(VLOOKUP($A11,'Налаштування'!$F$39:$K$52,6,FALSE),"ONBOARDING")="ACTIVE",'Розрахунок'!K11,"—") -> — | K11: {=IF(IFERROR(VLOOKUP($A11,'Налаштування'!$F$39:$K$52,6,FALSE),"ONBOARDING")="ACTIVE",INDEX('Оперативна оцінка'!$B$24:$N$24,1,MATCH($A11,'Оперативна оцінка'!$B$4:$N$4,0)),"")} | L11: =IFERROR(__xludf.DUMMYFUNCTION("IF(IFERROR(VLOOKUP($A11,'Налаштування'!$F$39:$K$52,6,FALSE),""ONBOARDING"")<>""ACTIVE"",""BACKFILL"",IFERROR(MAX(FILTER(DATEVALUE('Реєстр'!$D$2:$D$5000),'Реєстр'!$B$2:$B$5000=$A11,'Реєстр'!$C$2:$C$5000=""Балістика / швидкісні ракети"",REGEXMATCH('Реєстр'!"&"$AC$2:$AC$5000,""^Включено""))),""—""))"),46211.0) -> 46211 | M11: =IF(IFERROR(VLOOKUP($A11,'Налаштування'!$F$39:$K$52,6,FALSE),"ONBOARDING")="ACTIVE",'Розрахунок'!O11,"") -> 0/8 • 3/52 | N11: =IF(IFERROR(VLOOKUP($A11,'Налаштування'!$F$39:$K$52,6,FALSE),"ONBOARDING")="ACTIVE",TEXT('Розрахунок'!Q11,"0.0%")&"–"&TEXT('Розрахунок'!R11,"0.0%"),"") -> 2,0%–15,6% | O11: =IF(IFERROR(VLOOKUP($A11,'Налаштування'!$F$39:$K$52,6,FALSE),"ONBOARDING")="ACTIVE",'Розрахунок'!S11,"") -> 0.038461538 | P11: =IFERROR("2src "&TEXT(COUNTIFS('Реєстр'!$B$2:$B$5000,$A11,'Реєстр'!$C$2:$C$5000,"Балістика / швидкісні ракети",'Реєстр'!$AC$2:$AC$5000,"Включено*",'Реєстр'!$AR$2:$AR$5000,"MODEL-365",'Реєстр'!$O$2:$O$5000,"<>")/COUNTIFS('Реєстр'!$B$2:$B$5000,$A11,'Реєстр'!$C$2:$C$5000,"Балістика / швидкісні ракети",'Реєстр'!$AC$2:$AC$5000,"Включено*",'Реєстр'!$AR$2:$AR$5000,"MODEL-365"),"0%")&" • B "&TEXT(COUNTIFS('Реєстр'!$B$2:$B$5000,$A11,'Реєстр'!$C$2:$C$5000,"Балістика / швидкісні ракети",'Реєстр'!$AC$2:$AC$5000,"Включено*",'Реєстр'!$AR$2:$AR$5000,"MODEL-365",'Реєстр'!$L$2:$L$5000,"B*")/COUNTIFS('Реєстр'!$B$2:$B$5000,$A11,'Реєстр'!$C$2:$C$5000,"Балістика / швидкісні ракети",'Реєстр'!$AC$2:$AC$5000,"Включено*",'Реєстр'!$AR$2:$AR$5000,"MODEL-365"),"0%"),"—") -> 2src 100% • B 25%
A12: ='Налаштування'!R46 -> Херсон | B12: =IF(IFERROR(VLOOKUP($A12,'Налаштування'!$F$39:$K$52,6,FALSE),"ONBOARDING")="ACTIVE",'Розрахунок'!B12,"") -> 0 | C12: =IF(IFERROR(VLOOKUP($A12,'Налаштування'!$F$39:$K$52,6,FALSE),"ONBOARDING")="ACTIVE",'Розрахунок'!C12,"") -> 0 | D12: =IF(IFERROR(VLOOKUP($A12,'Налаштування'!$F$39:$K$52,6,FALSE),"ONBOARDING")="ACTIVE",'Розрахунок'!D12,"") -> 0 | E12: =IF(IFERROR(VLOOKUP($A12,'Налаштування'!$F$39:$K$52,6,FALSE),"ONBOARDING")="ACTIVE",'Розрахунок'!E12,"") -> 0 | F12: =IF(IFERROR(VLOOKUP($A12,'Налаштування'!$F$39:$K$52,6,FALSE),"ONBOARDING")="ACTIVE",'Розрахунок'!F12,"") -> 0 | G12: =IF(IFERROR(VLOOKUP($A12,'Налаштування'!$F$39:$K$52,6,FALSE),"ONBOARDING")="ACTIVE",'Розрахунок'!G12,"BACKFILL 365") -> Немає | H12: =IF(IFERROR(VLOOKUP($A12,'Налаштування'!$F$39:$K$52,6,FALSE),"ONBOARDING")="ACTIVE",'Розрахунок'!H12,"") -> 0 | I12: =IF(IFERROR(VLOOKUP($A12,'Налаштування'!$F$39:$K$52,6,FALSE),"ONBOARDING")="ACTIVE",'Розрахунок'!J12,"—") -> — | J12: =IF(IFERROR(VLOOKUP($A12,'Налаштування'!$F$39:$K$52,6,FALSE),"ONBOARDING")="ACTIVE",'Розрахунок'!K12,"—") -> — | K12: {=IF(IFERROR(VLOOKUP($A12,'Налаштування'!$F$39:$K$52,6,FALSE),"ONBOARDING")="ACTIVE",INDEX('Оперативна оцінка'!$B$24:$N$24,1,MATCH($A12,'Оперативна оцінка'!$B$4:$N$4,0)),"")} | L12: =IFERROR(__xludf.DUMMYFUNCTION("IF(IFERROR(VLOOKUP($A12,'Налаштування'!$F$39:$K$52,6,FALSE),""ONBOARDING"")<>""ACTIVE"",""BACKFILL"",IFERROR(MAX(FILTER(DATEVALUE('Реєстр'!$D$2:$D$5000),'Реєстр'!$B$2:$B$5000=$A12,'Реєстр'!$C$2:$C$5000=""Балістика / швидкісні ракети"",REGEXMATCH('Реєстр'!"&"$AC$2:$AC$5000,""^Включено""))),""—""))"),45597.0) -> 45597 | M12: =IF(IFERROR(VLOOKUP($A12,'Налаштування'!$F$39:$K$52,6,FALSE),"ONBOARDING")="ACTIVE",'Розрахунок'!O12,"") -> 0/8 • 0/52 | N12: =IF(IFERROR(VLOOKUP($A12,'Налаштування'!$F$39:$K$52,6,FALSE),"ONBOARDING")="ACTIVE",TEXT('Розрахунок'!Q12,"0.0%")&"–"&TEXT('Розрахунок'!R12,"0.0%"),"") -> 0,0%–6,9% | O12: =IF(IFERROR(VLOOKUP($A12,'Налаштування'!$F$39:$K$52,6,FALSE),"ONBOARDING")="ACTIVE",'Розрахунок'!S12,"") -> 0 | P12: =IFERROR("2src "&TEXT(COUNTIFS('Реєстр'!$B$2:$B$5000,$A12,'Реєстр'!$C$2:$C$5000,"Балістика / швидкісні ракети",'Реєстр'!$AC$2:$AC$5000,"Включено*",'Реєстр'!$AR$2:$AR$5000,"MODEL-365",'Реєстр'!$O$2:$O$5000,"<>")/COUNTIFS('Реєстр'!$B$2:$B$5000,$A12,'Реєстр'!$C$2:$C$5000,"Балістика / швидкісні ракети",'Реєстр'!$AC$2:$AC$5000,"Включено*",'Реєстр'!$AR$2:$AR$5000,"MODEL-365"),"0%")&" • B "&TEXT(COUNTIFS('Реєстр'!$B$2:$B$5000,$A12,'Реєстр'!$C$2:$C$5000,"Балістика / швидкісні ракети",'Реєстр'!$AC$2:$AC$5000,"Включено*",'Реєстр'!$AR$2:$AR$5000,"MODEL-365",'Реєстр'!$L$2:$L$5000,"B*")/COUNTIFS('Реєстр'!$B$2:$B$5000,$A12,'Реєстр'!$C$2:$C$5000,"Балістика / швидкісні ракети",'Реєстр'!$AC$2:$AC$5000,"Включено*",'Реєстр'!$AR$2:$AR$5000,"MODEL-365"),"0%"),"—") -> —
A13: ='Налаштування'!R47 -> Чернігів | B13: =IF(IFERROR(VLOOKUP($A13,'Налаштування'!$F$39:$K$52,6,FALSE),"ONBOARDING")="ACTIVE",'Розрахунок'!B13,"") -> 0 | C13: =IF(IFERROR(VLOOKUP($A13,'Налаштування'!$F$39:$K$52,6,FALSE),"ONBOARDING")="ACTIVE",'Розрахунок'!C13,"") -> 0 | D13: =IF(IFERROR(VLOOKUP($A13,'Налаштування'!$F$39:$K$52,6,FALSE),"ONBOARDING")="ACTIVE",'Розрахунок'!D13,"") -> 0 | E13: =IF(IFERROR(VLOOKUP($A13,'Налаштування'!$F$39:$K$52,6,FALSE),"ONBOARDING")="ACTIVE",'Розрахунок'!E13,"") -> 0.019230769 | F13: =IF(IFERROR(VLOOKUP($A13,'Налаштування'!$F$39:$K$52,6,FALSE),"ONBOARDING")="ACTIVE",'Розрахунок'!F13,"") -> 0.004818431 | G13: =IF(IFERROR(VLOOKUP($A13,'Налаштування'!$F$39:$K$52,6,FALSE),"ONBOARDING")="ACTIVE",'Розрахунок'!G13,"BACKFILL 365") -> Немає | H13: =IF(IFERROR(VLOOKUP($A13,'Налаштування'!$F$39:$K$52,6,FALSE),"ONBOARDING")="ACTIVE",'Розрахунок'!H13,"") -> 0 | I13: =IF(IFERROR(VLOOKUP($A13,'Налаштування'!$F$39:$K$52,6,FALSE),"ONBOARDING")="ACTIVE",'Розрахунок'!J13,"—") -> — | J13: =IF(IFERROR(VLOOKUP($A13,'Налаштування'!$F$39:$K$52,6,FALSE),"ONBOARDING")="ACTIVE",'Розрахунок'!K13,"—") -> — | K13: {=IF(IFERROR(VLOOKUP($A13,'Налаштування'!$F$39:$K$52,6,FALSE),"ONBOARDING")="ACTIVE",INDEX('Оперативна оцінка'!$B$24:$N$24,1,MATCH($A13,'Оперативна оцінка'!$B$4:$N$4,0)),"")} | L13: =IFERROR(__xludf.DUMMYFUNCTION("IFERROR(MAX(FILTER(DATEVALUE('Реєстр'!$D$2:$D$5000),'Реєстр'!$B$2:$B$5000=$A13,'Реєстр'!$C$2:$C$5000=""Балістика / швидкісні ракети"",REGEXMATCH('Реєстр'!$AC$2:$AC$5000,""^Включено""))),""—"")"),46114.0) -> 46114 | M13: =IF(IFERROR(VLOOKUP($A13,'Налаштування'!$F$39:$K$52,6,FALSE),"ONBOARDING")="ACTIVE",'Розрахунок'!O13,"") -> 0/8 • 1/52 | N13: =IF(IFERROR(VLOOKUP($A13,'Налаштування'!$F$39:$K$52,6,FALSE),"ONBOARDING")="ACTIVE",TEXT('Розрахунок'!Q13,"0.0%")&"–"&TEXT('Розрахунок'!R13,"0.0%"),"") -> 0,3%–10,1% | O13: =IF(IFERROR(VLOOKUP($A13,'Налаштування'!$F$39:$K$52,6,FALSE),"ONBOARDING")="ACTIVE",'Розрахунок'!S13,"") -> 0.019230769 | P13: =IFERROR("2src "&TEXT(COUNTIFS('Реєстр'!$B$2:$B$5000,$A13,'Реєстр'!$C$2:$C$5000,"Балістика / швидкісні ракети",'Реєстр'!$AC$2:$AC$5000,"Включено*",'Реєстр'!$AR$2:$AR$5000,"MODEL-365",'Реєстр'!$O$2:$O$5000,"<>")/COUNTIFS('Реєстр'!$B$2:$B$5000,$A13,'Реєстр'!$C$2:$C$5000,"Балістика / швидкісні ракети",'Реєстр'!$AC$2:$AC$5000,"Включено*",'Реєстр'!$AR$2:$AR$5000,"MODEL-365"),"0%")&" • B "&TEXT(COUNTIFS('Реєстр'!$B$2:$B$5000,$A13,'Реєстр'!$C$2:$C$5000,"Балістика / швидкісні ракети",'Реєстр'!$AC$2:$AC$5000,"Включено*",'Реєстр'!$AR$2:$AR$5000,"MODEL-365",'Реєстр'!$L$2:$L$5000,"B*")/COUNTIFS('Реєстр'!$B$2:$B$5000,$A13,'Реєстр'!$C$2:$C$5000,"Балістика / швидкісні ракети",'Реєстр'!$AC$2:$AC$5000,"Включено*",'Реєстр'!$AR$2:$AR$5000,"MODEL-365"),"0%"),"—") -> 2src 100% • B 0%
A14: ='Налаштування'!R48 -> Кривий Ріг | B14: =IF(IFERROR(VLOOKUP($A14,'Налаштування'!$F$39:$K$52,6,FALSE),"ONBOARDING")="ACTIVE",'Розрахунок'!B14,"") -> 0 | C14: =IF(IFERROR(VLOOKUP($A14,'Налаштування'!$F$39:$K$52,6,FALSE),"ONBOARDING")="ACTIVE",'Розрахунок'!C14,"") -> 0 | D14: =IF(IFERROR(VLOOKUP($A14,'Налаштування'!$F$39:$K$52,6,FALSE),"ONBOARDING")="ACTIVE",'Розрахунок'!D14,"") -> 0 | E14: =IF(IFERROR(VLOOKUP($A14,'Налаштування'!$F$39:$K$52,6,FALSE),"ONBOARDING")="ACTIVE",'Розрахунок'!E14,"") -> 0.019230769 | F14: =IF(IFERROR(VLOOKUP($A14,'Налаштування'!$F$39:$K$52,6,FALSE),"ONBOARDING")="ACTIVE",'Розрахунок'!F14,"") -> 0.025545057 | G14: =IF(IFERROR(VLOOKUP($A14,'Налаштування'!$F$39:$K$52,6,FALSE),"ONBOARDING")="ACTIVE",'Розрахунок'!G14,"BACKFILL 365") -> Немає | H14: =IF(IFERROR(VLOOKUP($A14,'Налаштування'!$F$39:$K$52,6,FALSE),"ONBOARDING")="ACTIVE",'Розрахунок'!H14,"") -> 0 | I14: =IF(IFERROR(VLOOKUP($A14,'Налаштування'!$F$39:$K$52,6,FALSE),"ONBOARDING")="ACTIVE",'Розрахунок'!J14,"—") -> — | J14: =IF(IFERROR(VLOOKUP($A14,'Налаштування'!$F$39:$K$52,6,FALSE),"ONBOARDING")="ACTIVE",'Розрахунок'!K14,"—") -> — | K14: {=IF(IFERROR(VLOOKUP($A14,'Налаштування'!$F$39:$K$52,6,FALSE),"ONBOARDING")="ACTIVE",INDEX('Оперативна оцінка'!$B$24:$N$24,1,MATCH($A14,'Оперативна оцінка'!$B$4:$N$4,0)),"")} | L14: =IFERROR(__xludf.DUMMYFUNCTION("IFERROR(MAX(FILTER(DATEVALUE('Реєстр'!$D$2:$D$5000),'Реєстр'!$B$2:$B$5000=$A14,'Реєстр'!$C$2:$C$5000=""Балістика / швидкісні ракети"",REGEXMATCH('Реєстр'!$AC$2:$AC$5000,""^Включено""))),""—"")"),46287.0) -> 46287 | M14: =IF(IFERROR(VLOOKUP($A14,'Налаштування'!$F$39:$K$52,6,FALSE),"ONBOARDING")="ACTIVE",'Розрахунок'!O14,"") -> 0/8 • 1/52 | N14: =IF(IFERROR(VLOOKUP($A14,'Налаштування'!$F$39:$K$52,6,FALSE),"ONBOARDING")="ACTIVE",TEXT('Розрахунок'!Q14,"0.0%")&"–"&TEXT('Розрахунок'!R14,"0.0%"),"") -> 0,3%–10,1% | O14: =IF(IFERROR(VLOOKUP($A14,'Налаштування'!$F$39:$K$52,6,FALSE),"ONBOARDING")="ACTIVE",'Розрахунок'!S14,"") -> 0.019230769 | P14: =IFERROR(__xludf.DUMMYFUNCTION("IF(IFERROR(VLOOKUP($A14,'Налаштування'!$F$39:$K$52,6,FALSE),""ONBOARDING"")=""ACTIVE"",IF(COUNTIFS('Реєстр'!$B$2:$B$5000,$A14,'Реєстр'!$C$2:$C$5000,""Балістика / швидкісні ракети"",'Реєстр'!$AC$2:$AC$5000,""Включено*"",'Реєстр'!$AR$2:$AR$5000,""MODEL-365"&""")=0,""0 positives • 365D covered"",""2src ""&TEXT(COUNTIFS('Реєстр'!$B$2:$B$5000,$A14,'Реєстр'!$C$2:$C$5000,""Балістика / швидкісні ракети"",'Реєстр'!$AC$2:$AC$5000,""Включено*"",'Реєстр'!$AR$2:$AR$5000,""MODEL-365"",'Реєстр'!$O$2:$O$5000,""<>"")/COUNTI"&"FS('Реєстр'!$B$2:$B$5000,$A14,'Реєстр'!$C$2:$C$5000,""Балістика / швидкісні ракети"",'Реєстр'!$AC$2:$AC$5000,""Включено*"",'Реєстр'!$AR$2:$AR$5000,""MODEL-365""),""0%"")),""audit ""&IFERROR(ROWS(UNIQUE(FILTER('Аудит покриття'!$A$2:$A$6905,'Аудит покриття'"&"!$B$2:$B$6905=$A14,'Аудит покриття'!$C$2:$C$6905=""VERIFIED""))),0)&""/365 • scoring OFF"")"),"2src 100%") -> 2src 100%
A15: ='Налаштування'!R49 -> Павлоград | B15: =IF(IFERROR(VLOOKUP($A15,'Налаштування'!$F$39:$K$52,6,FALSE),"ONBOARDING")="ACTIVE",'Розрахунок'!B15,"") -> 0 | C15: =IF(IFERROR(VLOOKUP($A15,'Налаштування'!$F$39:$K$52,6,FALSE),"ONBOARDING")="ACTIVE",'Розрахунок'!C15,"") -> 0 | D15: =IF(IFERROR(VLOOKUP($A15,'Налаштування'!$F$39:$K$52,6,FALSE),"ONBOARDING")="ACTIVE",'Розрахунок'!D15,"") -> 0 | E15: =IF(IFERROR(VLOOKUP($A15,'Налаштування'!$F$39:$K$52,6,FALSE),"ONBOARDING")="ACTIVE",'Розрахунок'!E15,"") -> 0 | F15: =IF(IFERROR(VLOOKUP($A15,'Налаштування'!$F$39:$K$52,6,FALSE),"ONBOARDING")="ACTIVE",'Розрахунок'!F15,"") -> 0.0038013929 | G15: =IF(IFERROR(VLOOKUP($A15,'Налаштування'!$F$39:$K$52,6,FALSE),"ONBOARDING")="ACTIVE",'Розрахунок'!G15,"BACKFILL 365") -> Немає | H15: =IF(IFERROR(VLOOKUP($A15,'Налаштування'!$F$39:$K$52,6,FALSE),"ONBOARDING")="ACTIVE",'Розрахунок'!H15,"") -> 0 | I15: =IF(IFERROR(VLOOKUP($A15,'Налаштування'!$F$39:$K$52,6,FALSE),"ONBOARDING")="ACTIVE",'Розрахунок'!J15,"—") -> — | J15: =IF(IFERROR(VLOOKUP($A15,'Налаштування'!$F$39:$K$52,6,FALSE),"ONBOARDING")="ACTIVE",'Розрахунок'!K15,"—") -> — | K15: {=IF(IFERROR(VLOOKUP($A15,'Налаштування'!$F$39:$K$52,6,FALSE),"ONBOARDING")="ACTIVE",INDEX('Оперативна оцінка'!$B$24:$N$24,1,MATCH($A15,'Оперативна оцінка'!$B$4:$N$4,0)),"")} | L15: =IFERROR(__xludf.DUMMYFUNCTION("IFERROR(MAX(FILTER(DATEVALUE('Реєстр'!$D$2:$D$5000),'Реєстр'!$B$2:$B$5000=$A15,'Реєстр'!$C$2:$C$5000=""Балістика / швидкісні ракети"",REGEXMATCH('Реєстр'!$AC$2:$AC$5000,""^Включено""))),""—"")"),46287.0) -> 46287 | M15: =IF(IFERROR(VLOOKUP($A15,'Налаштування'!$F$39:$K$52,6,FALSE),"ONBOARDING")="ACTIVE",'Розрахунок'!O15,"") -> 0/8 • 0/52 | N15: =IF(IFERROR(VLOOKUP($A15,'Налаштування'!$F$39:$K$52,6,FALSE),"ONBOARDING")="ACTIVE",TEXT('Розрахунок'!Q15,"0.0%")&"–"&TEXT('Розрахунок'!R15,"0.0%"),"") -> 0,0%–6,9% | O15: =IF(IFERROR(VLOOKUP($A15,'Налаштування'!$F$39:$K$52,6,FALSE),"ONBOARDING")="ACTIVE",'Розрахунок'!S15,"") -> 0 | P15: =IFERROR(__xludf.DUMMYFUNCTION("IF(IFERROR(VLOOKUP($A15,'Налаштування'!$F$39:$K$52,6,FALSE),""ONBOARDING"")=""ACTIVE"",IF(COUNTIFS('Реєстр'!$B$2:$B$5000,$A15,'Реєстр'!$C$2:$C$5000,""Балістика / швидкісні ракети"",'Реєстр'!$AC$2:$AC$5000,""Включено*"",'Реєстр'!$AR$2:$AR$5000,""MODEL-365"&""")=0,""0 positives • 365D covered"",""2src ""&TEXT(COUNTIFS('Реєстр'!$B$2:$B$5000,$A15,'Реєстр'!$C$2:$C$5000,""Балістика / швидкісні ракети"",'Реєстр'!$AC$2:$AC$5000,""Включено*"",'Реєстр'!$AR$2:$AR$5000,""MODEL-365"",'Реєстр'!$O$2:$O$5000,""<>"")/COUNTI"&"FS('Реєстр'!$B$2:$B$5000,$A15,'Реєстр'!$C$2:$C$5000,""Балістика / швидкісні ракети"",'Реєстр'!$AC$2:$AC$5000,""Включено*"",'Реєстр'!$AR$2:$AR$5000,""MODEL-365""),""0%"")),""audit ""&IFERROR(ROWS(UNIQUE(FILTER('Аудит покриття'!$A$2:$A$6905,'Аудит покриття'"&"!$B$2:$B$6905=$A15,'Аудит покриття'!$C$2:$C$6905=""VERIFIED""))),0)&""/365 • scoring OFF"")"),"2src 100%") -> 2src 100%
A16: ='Налаштування'!R50 -> Полтава | B16: =IF(IFERROR(VLOOKUP($A16,'Налаштування'!$F$39:$K$52,6,FALSE),"ONBOARDING")="ACTIVE",'Розрахунок'!B16,"") -> 0 | C16: =IF(IFERROR(VLOOKUP($A16,'Налаштування'!$F$39:$K$52,6,FALSE),"ONBOARDING")="ACTIVE",'Розрахунок'!C16,"") -> 0 | D16: =IF(IFERROR(VLOOKUP($A16,'Налаштування'!$F$39:$K$52,6,FALSE),"ONBOARDING")="ACTIVE",'Розрахунок'!D16,"") -> 0 | E16: =IF(IFERROR(VLOOKUP($A16,'Налаштування'!$F$39:$K$52,6,FALSE),"ONBOARDING")="ACTIVE",'Розрахунок'!E16,"") -> 0 | F16: =IF(IFERROR(VLOOKUP($A16,'Налаштування'!$F$39:$K$52,6,FALSE),"ONBOARDING")="ACTIVE",'Розрахунок'!F16,"") -> 0.0091047491 | G16: =IF(IFERROR(VLOOKUP($A16,'Налаштування'!$F$39:$K$52,6,FALSE),"ONBOARDING")="ACTIVE",'Розрахунок'!G16,"BACKFILL 365") -> Немає | H16: =IF(IFERROR(VLOOKUP($A16,'Налаштування'!$F$39:$K$52,6,FALSE),"ONBOARDING")="ACTIVE",'Розрахунок'!H16,"") -> 0 | I16: =IF(IFERROR(VLOOKUP($A16,'Налаштування'!$F$39:$K$52,6,FALSE),"ONBOARDING")="ACTIVE",'Розрахунок'!J16,"—") -> — | J16: =IF(IFERROR(VLOOKUP($A16,'Налаштування'!$F$39:$K$52,6,FALSE),"ONBOARDING")="ACTIVE",'Розрахунок'!K16,"—") -> — | K16: {=IF(IFERROR(VLOOKUP($A16,'Налаштування'!$F$39:$K$52,6,FALSE),"ONBOARDING")="ACTIVE",INDEX('Оперативна оцінка'!$B$24:$N$24,1,MATCH($A16,'Оперативна оцінка'!$B$4:$N$4,0)),"")} | L16: =IFERROR(__xludf.DUMMYFUNCTION("IFERROR(MAX(FILTER(DATEVALUE('Реєстр'!$D$2:$D$5000),'Реєстр'!$B$2:$B$5000=$A16,'Реєстр'!$C$2:$C$5000=""Балістика / швидкісні ракети"",REGEXMATCH('Реєстр'!$AC$2:$AC$5000,""^Включено""))),""—"")"),46204.0) -> 46204 | M16: =IF(IFERROR(VLOOKUP($A16,'Налаштування'!$F$39:$K$52,6,FALSE),"ONBOARDING")="ACTIVE",'Розрахунок'!O16,"") -> 0/6 • 0/50 | N16: =IF(IFERROR(VLOOKUP($A16,'Налаштування'!$F$39:$K$52,6,FALSE),"ONBOARDING")="ACTIVE",TEXT('Розрахунок'!Q16,"0.0%")&"–"&TEXT('Розрахунок'!R16,"0.0%"),"") -> 0,0%–7,1% | O16: =IF(IFERROR(VLOOKUP($A16,'Налаштування'!$F$39:$K$52,6,FALSE),"ONBOARDING")="ACTIVE",'Розрахунок'!S16,"") -> 0 | P16: =IFERROR(__xludf.DUMMYFUNCTION("IF(IFERROR(VLOOKUP($A16,'Налаштування'!$F$39:$K$52,6,FALSE),""ONBOARDING"")=""ACTIVE"",IF(COUNTIFS('Реєстр'!$B$2:$B$5000,$A16,'Реєстр'!$C$2:$C$5000,""Балістика / швидкісні ракети"",'Реєстр'!$AC$2:$AC$5000,""Включено*"",'Реєстр'!$AR$2:$AR$5000,""MODEL-365"&""")=0,""0 positives • 365D covered"",""2src ""&TEXT(COUNTIFS('Реєстр'!$B$2:$B$5000,$A16,'Реєстр'!$C$2:$C$5000,""Балістика / швидкісні ракети"",'Реєстр'!$AC$2:$AC$5000,""Включено*"",'Реєстр'!$AR$2:$AR$5000,""MODEL-365"",'Реєстр'!$O$2:$O$5000,""<>"")/COUNTI"&"FS('Реєстр'!$B$2:$B$5000,$A16,'Реєстр'!$C$2:$C$5000,""Балістика / швидкісні ракети"",'Реєстр'!$AC$2:$AC$5000,""Включено*"",'Реєстр'!$AR$2:$AR$5000,""MODEL-365""),""0%"")),""audit ""&IFERROR(ROWS(UNIQUE(FILTER('Аудит покриття'!$A$2:$A$6905,'Аудит покриття'"&"!$B$2:$B$6905=$A16,'Аудит покриття'!$C$2:$C$6905=""VERIFIED""))),0)&""/365 • scoring OFF"")"),"2src 100%") -> 2src 100%
A17: ='Налаштування'!R51 -> Суми | B17: =IF(IFERROR(VLOOKUP($A17,'Налаштування'!$F$39:$K$52,6,FALSE),"ONBOARDING")="ACTIVE",'Розрахунок'!B17,"") -> 0 | C17: =IF(IFERROR(VLOOKUP($A17,'Налаштування'!$F$39:$K$52,6,FALSE),"ONBOARDING")="ACTIVE",'Розрахунок'!C17,"") -> 0 | D17: =IF(IFERROR(VLOOKUP($A17,'Налаштування'!$F$39:$K$52,6,FALSE),"ONBOARDING")="ACTIVE",'Розрахунок'!D17,"") -> 0 | E17: =IF(IFERROR(VLOOKUP($A17,'Налаштування'!$F$39:$K$52,6,FALSE),"ONBOARDING")="ACTIVE",'Розрахунок'!E17,"") -> 0 | F17: =IF(IFERROR(VLOOKUP($A17,'Налаштування'!$F$39:$K$52,6,FALSE),"ONBOARDING")="ACTIVE",'Розрахунок'!F17,"") -> 0.000358165 | G17: ='Розрахунок'!G17 -> Немає | H17: =IF(IFERROR(VLOOKUP($A17,'Налаштування'!$F$39:$K$52,6,FALSE),"ONBOARDING")="ACTIVE",'Розрахунок'!H17,"") -> 0 | I17: =IF(IFERROR(VLOOKUP($A17,'Налаштування'!$F$39:$K$52,6,FALSE),"ONBOARDING")="ACTIVE",'Розрахунок'!J17,"—") -> — | J17: =IF(IFERROR(VLOOKUP($A17,'Налаштування'!$F$39:$K$52,6,FALSE),"ONBOARDING")="ACTIVE",'Розрахунок'!K17,"—") -> — | K17: {=IF(IFERROR(VLOOKUP($A17,'Налаштування'!$F$39:$K$52,6,FALSE),"ONBOARDING")="ACTIVE",INDEX('Оперативна оцінка'!$B$24:$N$24,1,MATCH($A17,'Оперативна оцінка'!$B$4:$N$4,0)),"")} | L17: =IFERROR(__xludf.DUMMYFUNCTION("IFERROR(MAX(FILTER(DATEVALUE('Реєстр'!$D$2:$D$5000),'Реєстр'!$B$2:$B$5000=$A17,'Реєстр'!$C$2:$C$5000=""Балістика / швидкісні ракети"",REGEXMATCH('Реєстр'!$AC$2:$AC$5000,""^Включено""))),""—"")"),45975.0) -> 45975 | M17: =IF(IFERROR(VLOOKUP($A17,'Налаштування'!$F$39:$K$52,6,FALSE),"ONBOARDING")="ACTIVE",'Розрахунок'!O17,"") -> 0/8 • 0/52 | N17: =IF(IFERROR(VLOOKUP($A17,'Налаштування'!$F$39:$K$52,6,FALSE),"ONBOARDING")="ACTIVE",TEXT('Розрахунок'!Q17,"0.0%")&"–"&TEXT('Розрахунок'!R17,"0.0%"),"") -> 0,0%–6,9% | O17: =IF(IFERROR(VLOOKUP($A17,'Налаштування'!$F$39:$K$52,6,FALSE),"ONBOARDING")="ACTIVE",'Розрахунок'!S17,"") -> 0 | P17: =IFERROR(__xludf.DUMMYFUNCTION("IF(IFERROR(VLOOKUP($A17,'Налаштування'!$F$39:$K$52,6,FALSE),""ONBOARDING"")=""ACTIVE"",IF(COUNTIFS('Реєстр'!$B$2:$B$5000,$A17,'Реєстр'!$C$2:$C$5000,""Балістика / швидкісні ракети"",'Реєстр'!$AC$2:$AC$5000,""Включено*"",'Реєстр'!$AR$2:$AR$5000,""MODEL-365"&""")=0,""0 positives • 365D covered"",""2src ""&TEXT(COUNTIFS('Реєстр'!$B$2:$B$5000,$A17,'Реєстр'!$C$2:$C$5000,""Балістика / швидкісні ракети"",'Реєстр'!$AC$2:$AC$5000,""Включено*"",'Реєстр'!$AR$2:$AR$5000,""MODEL-365"",'Реєстр'!$O$2:$O$5000,""<>"")/COUNTI"&"FS('Реєстр'!$B$2:$B$5000,$A17,'Реєстр'!$C$2:$C$5000,""Балістика / швидкісні ракети"",'Реєстр'!$AC$2:$AC$5000,""Включено*"",'Реєстр'!$AR$2:$AR$5000,""MODEL-365""),""0%"")),""audit ""&IFERROR(ROWS(UNIQUE(FILTER('Аудит покриття'!$A$2:$A$6905,'Аудит покриття'"&"!$B$2:$B$6905=$A17,'Аудит покриття'!$C$2:$C$6905=""VERIFIED""))),0)&""/365 • scoring OFF"")"),"2src 100%") -> 2src 100%
A18: ='Налаштування'!R52 -> Кременчук | B18: =IF(IFERROR(VLOOKUP($A18,'Налаштування'!$F$39:$K$52,6,FALSE),"ONBOARDING")="ACTIVE",'Розрахунок'!B18,"") -> 0 | C18: =IF(IFERROR(VLOOKUP($A18,'Налаштування'!$F$39:$K$52,6,FALSE),"ONBOARDING")="ACTIVE",'Розрахунок'!C18,"") -> 0 | D18: =IF(IFERROR(VLOOKUP($A18,'Налаштування'!$F$39:$K$52,6,FALSE),"ONBOARDING")="ACTIVE",'Розрахунок'!D18,"") -> 0 | E18: =IF(IFERROR(VLOOKUP($A18,'Налаштування'!$F$39:$K$52,6,FALSE),"ONBOARDING")="ACTIVE",'Розрахунок'!E18,"") -> 0 | F18: =IF(IFERROR(VLOOKUP($A18,'Налаштування'!$F$39:$K$52,6,FALSE),"ONBOARDING")="ACTIVE",'Розрахунок'!F18,"") -> 0.014910861 | G18: ='Розрахунок'!G18 -> Немає | H18: =IF(IFERROR(VLOOKUP($A18,'Налаштування'!$F$39:$K$52,6,FALSE),"ONBOARDING")="ACTIVE",'Розрахунок'!H18,"") -> 0 | I18: =IF(IFERROR(VLOOKUP($A18,'Налаштування'!$F$39:$K$52,6,FALSE),"ONBOARDING")="ACTIVE",'Розрахунок'!J18,"—") -> — | J18: =IF(IFERROR(VLOOKUP($A18,'Налаштування'!$F$39:$K$52,6,FALSE),"ONBOARDING")="ACTIVE",'Розрахунок'!K18,"—") -> — | K18: {=IF(IFERROR(VLOOKUP($A18,'Налаштування'!$F$39:$K$52,6,FALSE),"ONBOARDING")="ACTIVE",INDEX('Оперативна оцінка'!$B$24:$O$24,1,MATCH($A18,'Оперативна оцінка'!$B$4:$O$4,0)),"")} | L18: =IFERROR(__xludf.DUMMYFUNCTION("IFERROR(MAX(FILTER(DATEVALUE('Реєстр'!$D$2:$D$5000),'Реєстр'!$B$2:$B$5000=$A18,'Реєстр'!$C$2:$C$5000=""Балістика / швидкісні ракети"",REGEXMATCH('Реєстр'!$AC$2:$AC$5000,""^Включено""))),""—"")"),46302.0) -> 46302 | M18: =IF(IFERROR(VLOOKUP($A18,'Налаштування'!$F$39:$K$52,6,FALSE),"ONBOARDING")="ACTIVE",'Розрахунок'!O18,"") -> 0/6 • 0/50 | N18: =IF(IFERROR(VLOOKUP($A18,'Налаштування'!$F$39:$K$52,6,FALSE),"ONBOARDING")="ACTIVE",TEXT('Розрахунок'!Q18,"0.0%")&"–"&TEXT('Розрахунок'!R18,"0.0%"),"") -> 0,0%–7,1% | O18: =IF(IFERROR(VLOOKUP($A18,'Налаштування'!$F$39:$K$52,6,FALSE),"ONBOARDING")="ACTIVE",'Розрахунок'!S18,"") -> 0 | P18: =IFERROR(__xludf.DUMMYFUNCTION("IF(IFERROR(VLOOKUP($A18,'Налаштування'!$F$39:$K$52,6,FALSE),""ONBOARDING"")=""ACTIVE"",IF(COUNTIFS('Реєстр'!$B$2:$B$5000,$A18,'Реєстр'!$C$2:$C$5000,""Балістика / швидкісні ракети"",'Реєстр'!$AC$2:$AC$5000,""Включено*"",'Реєстр'!$AR$2:$AR$5000,""MODEL-365"&""")=0,""0 positives • 365D covered"",""2src ""&TEXT(COUNTIFS('Реєстр'!$B$2:$B$5000,$A18,'Реєстр'!$C$2:$C$5000,""Балістика / швидкісні ракети"",'Реєстр'!$AC$2:$AC$5000,""Включено*"",'Реєстр'!$AR$2:$AR$5000,""MODEL-365"",'Реєстр'!$O$2:$O$5000,""<>"")/COUNTI"&"FS('Реєстр'!$B$2:$B$5000,$A18,'Реєстр'!$C$2:$C$5000,""Балістика / швидкісні ракети"",'Реєстр'!$AC$2:$AC$5000,""Включено*"",'Реєстр'!$AR$2:$AR$5000,""MODEL-365""),""0%"")),""audit ""&IFERROR(ROWS(UNIQUE(FILTER('Аудит покриття'!$A$2:$A$6905,'Аудит покриття'"&"!$B$2:$B$6905=$A18,'Аудит покриття'!$C$2:$C$6905=""VERIFIED""))),0)&""/365 • scoring OFF"")"),"2src 100%") -> 2src 100%
A19: Метод | B19: R56/R90/R180/R365 — raw same-weekday rates. Smoothed base = 50% all-day decay + 50% weekday decay, half-life 90 днів. Домінантний день лишається окремим режимним сигналом.
A20: Режим | B20: Домінантний день режиму — це найчастіший день балістичних attack-days за останні 56 днів. Він не замінює день, для якого зараз рахується %. Цільовий % завжди рахується для дня після 00:00 у поточній ночі.
A21: Невизначеність | B21: 95% CI показує статистичну невизначеність R365 для цільового дня тижня. Support = кількість attack-days / covered occurrences. Це не інтервал для оперативного прогнозу.
A22: Evidence | B22: Model-selection evidence: 4 core cities on historical walk-forward. Expanded ACTIVE cities inherit the frozen v2.1-shrink specification but are not treated as independently validated until prospective backtest accumulates.
A23: Walk-forward | B23: Model selection заморожена на історичній валідації 4 core-моделей: 50/50 shrink + HL90. Суми та Кременчук мають повний 365D calendar + 365D walk-forward/backcast і входять як ACTIVE_EXTENDED після проходження onboarding gate; prospective якість оцінюється новими VALID_PRE_EVENT ночами.
A24: Global cycle | B24: Weekly anchor поки лишається контекстом: 01.08–24.09 pooled attack-rate 12,5% в anchor-дні проти 10,1% в інші дні (RR 1,24x), з різним напрямом по містах. Автоматичної поправки до % немає.
A25: Версія | B25: v2.1-shrink: historical base = 50% weekday decay HL90 + 50% all-day decay HL90. Оперативний % лишається окремим шаром і не підміняється статистичною базою.
A27: MODEL STATUS
A28: Layer | B28: Version | C28: State | D28: Live nights | E28: Gate | F28: Evidence
A29: Historical base | B29: ='Контроль моделі'!B160 -> v2.1-shrink | C29: ='Контроль моделі'!C160 -> VALIDATED / FROZEN | D29: ='Контроль моделі'!D160 -> 1 | E29: ='Контроль моделі'!E160 -> ≥30 new resolved nights before any re-fit | F29: WF90D + 60/30 holdout; 50/50 frozen
A30: Operational layer | B30: ='Контроль моделі'!B161 -> ops-v0 | C30: ='Контроль моделі'!C161 -> COLLECTING DATA | D30: ='Контроль моделі'!D161 -> 1 | E30: ='Контроль моделі'!E161 -> ≥30 resolved OPS_FINAL nights + ≥80% complete factor rows | F30: ='Контроль моделі'!F161 -> factor completeness: 91%
A31: Live backtest | B31: ='Контроль моделі'!B162 -> immutable snapshots | C31: ='Контроль моделі'!C162 -> ACTIVE | D31: ='Контроль моделі'!D162 -> 1 | E31: ='Контроль моделі'!E162 -> VALID_PRE_EVENT only | F31: ='Контроль моделі'!F162 -> LATE_DIAGNOSTIC та LEGACY ніколи не входять у score.
A33: DAILY CYCLE
A34: Крок | B34: Дата | C34: Статус / результат | D34: Міста | E34: Наступна дія | F34: Примітка
A35: Останній аудит | B35: ='Розрахунок'!K2 -> 46297 | C35: =IFERROR(__xludf.DUMMYFUNCTION("""Балістика: ""&SUMPRODUCT(('Аудит покриття'!$A$2:$A$7600='Розрахунок'!K2)*('Аудит покриття'!$C$2:$C$7600=""VERIFIED"")*N(REGEXMATCH('Аудит покриття'!$B$2:$B$7600,""^(""&TEXTJOIN(""|"",TRUE,FILTER('Налаштування'!$F$39:$F$100,'Налаштування'!$K$39:$K$100="""&"ACTIVE""))&"")$""))*'Аудит покриття'!$D$2:$D$7600)&"" attack-days / ""&SUMPRODUCT(('Аудит покриття'!$A$2:$A$7600='Розрахунок'!K2)*('Аудит покриття'!$C$2:$C$7600=""VERIFIED"")*N(REGEXMATCH('Аудит покриття'!$B$2:$B$7600,""^(""&TEXTJOIN(""|"",TRUE,FILTER('На"&"лаштування'!$F$39:$F$100,'Налаштування'!$K$39:$K$100=""ACTIVE""))&"")$"")))&"" audit-verified models"""),"Балістика: 1 attack-days / 14 audit-verified models") -> Балістика: 1 attack-days / 14 audit-verified models | D35: =IFERROR(__xludf.DUMMYFUNCTION("TEXTJOIN("", "",TRUE,FILTER('Аудит покриття'!$B$2:$B$7600,'Аудит покриття'!$A$2:$A$7600='Розрахунок'!K2,'Аудит покриття'!$C$2:$C$7600=""VERIFIED"",REGEXMATCH('Аудит покриття'!$B$2:$B$7600,""^(""&TEXTJOIN(""|"",TRUE,FILTER('Налаштування'!$F$39:$F$100,'Нала"&"штування'!$K$39:$K$100=""ACTIVE""))&"")$"")))"),"Київ, Дніпро, Житомир, Запоріжжя, Миколаїв, Одеса, Харків, Херсон, Чернігів, Кривий Ріг, Павлоград, Полтава, Суми, Кременчук") -> Київ, Дніпро, Житомир, Запоріжжя, Миколаїв, Одеса, Харків, Херсон, Чернігів, Кривий Ріг, Павлоград, Полтава, Суми, Кременчук | E35: Закрито | F35: Audit-required і scoreable розділені. Суми завершили 365D backfill та ACTIVE; Житомир має live-audit start 29.09.
A36: Наступний STAT_20 | B36: ='Розрахунок'!B2 -> 46307 | C36: =IF(MOD(NOW(),1)<TIME(20,0,0),"сьогодні о 20:00","готовий / вже настав") -> сьогодні о 20:00 | D36: =COUNTIF('Налаштування'!K39:K100,"ACTIVE")&" ACTIVE scoreable" -> 14 ACTIVE scoreable | E36: Зафіксувати pre-event snapshot | F36: Цільова дата після 00:00.
A37: Цільова ніч | B37: ='Розрахунок'!B2 -> 46307 | C37: =CHOOSE(WEEKDAY('Розрахунок'!B2-1,2),"ПН","ВТ","СР","ЧТ","ПТ","СБ","НД")&"→"&CHOOSE(WEEKDAY('Розрахунок'!B2,2),"ПН","ВТ","СР","ЧТ","ПТ","СБ","НД") -> НД→ПН | D37: =COUNTA('Налаштування'!F39:F100)&" моделей ("&COUNTIF('Налаштування'!K39:K100,"ACTIVE")&" scoreable)" -> 14 моделей (14 scoreable) | E37: Після STAT_20 — OPS_FINAL | F37: Для цієї дати historical base буде оновлена автоматично.
A38: Наступний аудит | B38: ='Розрахунок'!K2+1 -> 46298 | C38: =IF('Розрахунок'!K2+1=TODAY(),"AUDIT_TODAY",IF('Розрахунок'!K2+1<TODAY(),"PENDING","FUTURE")) -> PENDING | D38: =COUNTA('Налаштування'!F39:F100)&" registered / live-audit models" -> 14 registered / live-audit models | E38: Після завершення ночі | F38: Cutoff рухається тільки після VERIFIED audit.
D39: =COUNTIF('Налаштування'!K39:K100,"ACTIVE")&" ACTIVE + "&COUNTIF('Налаштування'!K39:K100,"ONBOARDING")&" onboarding" -> 14 ACTIVE + 0 onboarding

Sheet Оперативна оцінка
A1: BADK LIVE — ОПЕРАТИВНА ОЦІНКА
A2: Цільова дата | B2: ='Розрахунок'!B2 -> 46307 | D2: День | E2: ='Розрахунок'!B3 -> Понеділок
A4: Фактор | B4: ='Налаштування'!R39 -> Київ | C4: ='Налаштування'!R40 -> Дніпро | D4: ='Налаштування'!R41 -> Житомир | E4: ='Налаштування'!R42 -> Запоріжжя | F4: ='Налаштування'!R43 -> Миколаїв | G4: ='Налаштування'!R44 -> Одеса | H4: ='Налаштування'!R45 -> Харків | I4: ='Налаштування'!R46 -> Херсон | J4: ='Налаштування'!R47 -> Чернігів | K4: ='Налаштування'!R48 -> Кривий Ріг | L4: ='Налаштування'!R49 -> Павлоград | M4: ='Налаштування'!R50 -> Полтава | N4: ='Налаштування'!R51 -> Суми | O4: ='Налаштування'!R52 -> Кременчук | P4: Примітка
A5: Smoothed base 50/50 (авто) | B5: {=IF(IFERROR(VLOOKUP(B$4,'Налаштування'!$F$39:$K$100,6,FALSE),"ONBOARDING")="ACTIVE",INDEX('Розрахунок'!$F$5:$F$17,MATCH(B$4,'Розрахунок'!$A$5:$A$17,0)),"")} -> 0.11679186 | C5: {=IF(IFERROR(VLOOKUP(C$4,'Налаштування'!$F$39:$K$100,6,FALSE),"ONBOARDING")="ACTIVE",INDEX('Розрахунок'!$F$5:$F$17,MATCH(C$4,'Розрахунок'!$A$5:$A$17,0)),"")} -> 0.049345885 | D5: {=IF(IFERROR(VLOOKUP(D$4,'Налаштування'!$F$39:$K$100,6,FALSE),"ONBOARDING")="ACTIVE",INDEX('Розрахунок'!$F$5:$F$17,MATCH(D$4,'Розрахунок'!$A$5:$A$17,0)),"")} -> 0.00029077646 | E5: {=IF(IFERROR(VLOOKUP(E$4,'Налаштування'!$F$39:$K$100,6,FALSE),"ONBOARDING")="ACTIVE",INDEX('Розрахунок'!$F$5:$F$17,MATCH(E$4,'Розрахунок'!$A$5:$A$17,0)),"")} -> 0.026823138 | F5: {=IF(IFERROR(VLOOKUP(F$4,'Налаштування'!$F$39:$K$100,6,FALSE),"ONBOARDING")="ACTIVE",INDEX('Розрахунок'!$F$5:$F$17,MATCH(F$4,'Розрахунок'!$A$5:$A$17,0)),"")} -> 0.0089819532 | G5: {=IF(IFERROR(VLOOKUP(G$4,'Налаштування'!$F$39:$K$100,6,FALSE),"ONBOARDING")="ACTIVE",INDEX('Розрахунок'!$F$5:$F$17,MATCH(G$4,'Розрахунок'!$A$5:$A$17,0)),"")} -> 0.061666566 | H5: {=IF(IFERROR(VLOOKUP(H$4,'Налаштування'!$F$39:$K$100,6,FALSE),"ONBOARDING")="ACTIVE",INDEX('Розрахунок'!$F$5:$F$17,MATCH(H$4,'Розрахунок'!$A$5:$A$17,0)),"")} -> 0.042414339 | I5: {=IF(IFERROR(VLOOKUP(I$4,'Налаштування'!$F$39:$K$100,6,FALSE),"ONBOARDING")="ACTIVE",INDEX('Розрахунок'!$F$5:$F$17,MATCH(I$4,'Розрахунок'!$A$5:$A$17,0)),"")} -> 0 | ... N5: {=IF(IFERROR(VLOOKUP(N$4,'Налаштування'!$F$39:$K$100,6,FALSE),"ONBOARDING")="ACTIVE",INDEX('Розрахунок'!$F$5:$F$17,MATCH(N$4,'Розрахунок'!$A$5:$A$17,0)),"")} -> 0.000358165 | O5: {=IF(IFERROR(VLOOKUP(O$4,'Налаштування'!$F$39:$K$100,6,FALSE),"ONBOARDING")="ACTIVE",INDEX('Розрахунок'!$F$5:$F$18,MATCH(O$4,'Розрахунок'!$A$5:$A$18,0)),"")} -> 0.014910861 | P5: ="Historical base: "&TEXT('Налаштування'!$G$6,"0%")&" weekday decay + "&TEXT('Налаштування'!$G$7,"0%")&" all-day decay; half-life "&'Налаштування'!$G$3&" днів." -> Historical base: 50% weekday decay + 50% all-day decay; half-life 90 днів.
A6: New test % | B6: =IFERROR(__xludf.DUMMYFUNCTION("LET(base,IF(IFERROR(VLOOKUP(B$4,'Налаштування'!$F$39:$K$100,6,FALSE),""ONBOARDING"")<>""ACTIVE"","""",IF(B$4<>""Київ"",B5,LET(dd,'Розрахунок'!$B$2,ww,'Розрахунок'!$B$3,cc,B$4,nn,COUNTIFS('Календар 365'!$A$2:$A$5111,"">=""&dd-365,'Календар 365'!$A$2:$A$511"&"1,""<""&dd,'Календар 365'!$B$2:$B$5111,ww,'Календар 365'!$C$2:$C$5111,cc,'Календар 365'!$D$2:$D$5111,""SYSTEMATIC_OSINT_V1""),shorta,IFERROR(SUM(FILTER(VALUE('Календар 365'!$E$2:$E$5111)*EXP(-LN(2)*(dd-'Календар 365'!$A$2:$A$5111)/30),'Календар 365'!$A$2:"&"$A$5111>=dd-365,'Календар 365'!$A$2:$A$5111<dd,'Календар 365'!$B$2:$B$5111=ww,'Календар 365'!$C$2:$C$5111=cc,'Календар 365'!$D$2:$D$5111=""SYSTEMATIC_OSINT_V1""))/SUM(FILTER(EXP(-LN(2)*(dd-'Календар 365'!$A$2:$A$5111)/30),'Календар 365'!$A$2:$A$5111>=dd-3"&"65,'Календар 365'!$A$2:$A$5111<dd,'Календар 365'!$B$2:$B$5111=ww,'Календар 365'!$C$2:$C$5111=cc,'Календар 365'!$D$2:$D$5111=""SYSTEMATIC_OSINT_V1"")),0),shortb,IFERROR(SUM(FILTER(VALUE('Календар 365'!$E$2:$E$5111)*EXP(-LN(2)*(dd-'Календар 365'!$A$2:$A$511"&"1)/60),'Календар 365'!$A$2:$A$5111>=dd-365,'Календар 365'!$A$2:$A$5111<dd,'Календар 365'!$B$2:$B$5111=ww,'Календар 365'!$C$2:$C$5111=cc,'Календар 365'!$D$2:$D$5111=""SYSTEMATIC_OSINT_V1""))/SUM(FILTER(EXP(-LN(2)*(dd-'Календар 365'!$A$2:$A$5111)/60),'Кален"&"дар 365'!$A$2:$A$5111>=dd-365,'Календар 365'!$A$2:$A$5111<dd,'Календар 365'!$B$2:$B$5111=ww,'Календар 365'!$C$2:$C$5111=cc,'Календар 365'!$D$2:$D$5111=""SYSTEMATIC_OSINT_V1"")),0),allday,IFERROR(SUM(FILTER(VALUE('Календар 365'!$E$2:$E$5111)*EXP(-LN(2)*(dd"&"-'Календар 365'!$A$2:$A$5111)/90),'Календар 365'!$A$2:$A$5111>=dd-365,'Календар 365'!$A$2:$A$5111<dd,'Календар 365'!$C$2:$C$5111=cc,'Календар 365'!$D$2:$D$5111=""SYSTEMATIC_OSINT_V1""))/SUM(FILTER(EXP(-LN(2)*(dd-'Календар 365'!$A$2:$A$5111)/90),'Календар "&"365'!$A$2:$A$5111>=dd-365,'Календар 365'!$A$2:$A$5111<dd,'Календар 365'!$C$2:$C$5111=cc,'Календар 365'!$D$2:$D$5111=""SYSTEMATIC_OSINT_V1"")),0),IF(nn>=45,80%*(60%*shorta+40%*shortb)+20%*allday,B5)))),delta,0.5%*(COUNTIF(B13,""Підвищує"")+COUNTIF(B16:B22,"&"""Підвищує"")-COUNTIF(B13,""Знижує"")-COUNTIF(B16:B22,""Знижує"")),IF(base="""","""",MAX(0,MIN(1,base+delta))))"),0.06634364640078039) -> 0.066343646 | C6: =LET(base,IF(IFERROR(VLOOKUP(C$4,'Налаштування'!$F$39:$K$100,6,FALSE),"ONBOARDING")="ACTIVE",C5,""),delta,0.5%*(COUNTIF(C13,"Підвищує")+COUNTIF(C16:C22,"Підвищує")-COUNTIF(C13,"Знижує")-COUNTIF(C16:C22,"Знижує")),IF(base="","",MAX(0,MIN(1,base+delta)))) -> 0.049345885 | D6: =LET(base,IF(IFERROR(VLOOKUP(D$4,'Налаштування'!$F$39:$K$100,6,FALSE),"ONBOARDING")="ACTIVE",D5,""),delta,0.5%*(COUNTIF(D13,"Підвищує")+COUNTIF(D16:D22,"Підвищує")-COUNTIF(D13,"Знижує")-COUNTIF(D16:D22,"Знижує")),IF(base="","",MAX(0,MIN(1,base+delta)))) -> 0.00029077646 | E6: =LET(base,IF(IFERROR(VLOOKUP(E$4,'Налаштування'!$F$39:$K$100,6,FALSE),"ONBOARDING")="ACTIVE",E5,""),delta,0.5%*(COUNTIF(E13,"Підвищує")+COUNTIF(E16:E22,"Підвищує")-COUNTIF(E13,"Знижує")-COUNTIF(E16:E22,"Знижує")),IF(base="","",MAX(0,MIN(1,base+delta)))) -> 0.026823138 | F6: =LET(base,IF(IFERROR(VLOOKUP(F$4,'Налаштування'!$F$39:$K$100,6,FALSE),"ONBOARDING")="ACTIVE",F5,""),delta,0.5%*(COUNTIF(F13,"Підвищує")+COUNTIF(F16:F22,"Підвищує")-COUNTIF(F13,"Знижує")-COUNTIF(F16:F22,"Знижує")),IF(base="","",MAX(0,MIN(1,base+delta)))) -> 0.0089819532 | G6: =LET(base,IF(IFERROR(VLOOKUP(G$4,'Налаштування'!$F$39:$K$100,6,FALSE),"ONBOARDING")="ACTIVE",G5,""),delta,0.5%*(COUNTIF(G13,"Підвищує")+COUNTIF(G16:G22,"Підвищує")-COUNTIF(G13,"Знижує")-COUNTIF(G16:G22,"Знижує")),IF(base="","",MAX(0,MIN(1,base+delta)))) -> 0.061666566 | H6: =LET(base,IF(IFERROR(VLOOKUP(H$4,'Налаштування'!$F$39:$K$100,6,FALSE),"ONBOARDING")="ACTIVE",H5,""),delta,0.5%*(COUNTIF(H13,"Підвищує")+COUNTIF(H16:H22,"Підвищує")-COUNTIF(H13,"Знижує")-COUNTIF(H16:H22,"Знижує")),IF(base="","",MAX(0,MIN(1,base+delta)))) -> 0.042414339 | I6: =LET(base,IF(IFERROR(VLOOKUP(I$4,'Налаштування'!$F$39:$K$100,6,FALSE),"ONBOARDING")="ACTIVE",I5,""),delta,0.5%*(COUNTIF(I13,"Підвищує")+COUNTIF(I16:I22,"Підвищує")-COUNTIF(I13,"Знижує")-COUNTIF(I16:I22,"Знижує")),IF(base="","",MAX(0,MIN(1,base+delta)))) -> 0 | J6: =LET(base,IF(IFERROR(VLOOKUP(J$4,'Налаштування'!$F$39:$K$100,6,FALSE),"ONBOARDING")="ACTIVE",J5,""),delta,0.5%*(COUNTIF(J13,"Підвищує")+COUNTIF(J16:J22,"Підвищує")-COUNTIF(J13,"Знижує")-COUNTIF(J16:J22,"Знижує")),IF(base="","",MAX(0,MIN(1,base+delta)))) -> 0.004818431 | ... O6: =LET(base,IF(IFERROR(VLOOKUP(O$4,'Налаштування'!$F$39:$K$100,6,FALSE),"ONBOARDING")="ACTIVE",O5,""),delta,0.5%*(COUNTIF(O13,"Підвищує")+COUNTIF(O16:O22,"Підвищує")-COUNTIF(O13,"Знижує")-COUNTIF(O16:O22,"Знижує")),IF(base="","",MAX(0,MIN(1,base+delta)))) -> 0.014910861 | P6: SHADOW: Київ = HL30/60 кандидат; інші ACTIVE = Smoothed base 50/50. ±0,5 п.п. за кожне Підвищує/Знижує у рядках 13,16–22; Нейтрально/Н/Д = 0. Production не змінює.
A7: R56 поточного дня (авто) | B7: {=IF(IFERROR(VLOOKUP(B$4,'Налаштування'!$F$39:$K$100,6,FALSE),"ONBOARDING")="ACTIVE",INDEX('Розрахунок'!$B$5:$B$17,MATCH(B$4,'Розрахунок'!$A$5:$A$17,0)),"")} -> 0 | C7: {=IF(IFERROR(VLOOKUP(C$4,'Налаштування'!$F$39:$K$100,6,FALSE),"ONBOARDING")="ACTIVE",INDEX('Розрахунок'!$B$5:$B$17,MATCH(C$4,'Розрахунок'!$A$5:$A$17,0)),"")} -> 0 | D7: {=IF(IFERROR(VLOOKUP(D$4,'Налаштування'!$F$39:$K$100,6,FALSE),"ONBOARDING")="ACTIVE",INDEX('Розрахунок'!$B$5:$B$17,MATCH(D$4,'Розрахунок'!$A$5:$A$17,0)),"")} -> 0 | E7: {=IF(IFERROR(VLOOKUP(E$4,'Налаштування'!$F$39:$K$100,6,FALSE),"ONBOARDING")="ACTIVE",INDEX('Розрахунок'!$B$5:$B$17,MATCH(E$4,'Розрахунок'!$A$5:$A$17,0)),"")} -> 0 | F7: {=IF(IFERROR(VLOOKUP(F$4,'Налаштування'!$F$39:$K$100,6,FALSE),"ONBOARDING")="ACTIVE",INDEX('Розрахунок'!$B$5:$B$17,MATCH(F$4,'Розрахунок'!$A$5:$A$17,0)),"")} -> 0 | G7: {=IF(IFERROR(VLOOKUP(G$4,'Налаштування'!$F$39:$K$100,6,FALSE),"ONBOARDING")="ACTIVE",INDEX('Розрахунок'!$B$5:$B$17,MATCH(G$4,'Розрахунок'!$A$5:$A$17,0)),"")} -> 0 | H7: {=IF(IFERROR(VLOOKUP(H$4,'Налаштування'!$F$39:$K$100,6,FALSE),"ONBOARDING")="ACTIVE",INDEX('Розрахунок'!$B$5:$B$17,MATCH(H$4,'Розрахунок'!$A$5:$A$17,0)),"")} -> 0 | I7: {=IF(IFERROR(VLOOKUP(I$4,'Налаштування'!$F$39:$K$100,6,FALSE),"ONBOARDING")="ACTIVE",INDEX('Розрахунок'!$B$5:$B$17,MATCH(I$4,'Розрахунок'!$A$5:$A$17,0)),"")} -> 0 | ... N7: {=IF(IFERROR(VLOOKUP(N$4,'Налаштування'!$F$39:$K$100,6,FALSE),"ONBOARDING")="ACTIVE",INDEX('Розрахунок'!$B$5:$B$17,MATCH(N$4,'Розрахунок'!$A$5:$A$17,0)),"")} -> 0 | O7: {=IF(IFERROR(VLOOKUP(O$4,'Налаштування'!$F$39:$K$100,6,FALSE),"ONBOARDING")="ACTIVE",INDEX('Розрахунок'!$B$5:$B$18,MATCH(O$4,'Розрахунок'!$A$5:$A$18,0)),"")} -> 0 | P7: Короткий режимний сигнал для поточного дня тижня
A8: Домінантний день режиму (56д) | B8: {=IF(IFERROR(VLOOKUP(B$4,'Налаштування'!$F$39:$K$100,6,FALSE),"ONBOARDING")="ACTIVE",INDEX('Розрахунок'!$G$5:$G$17,MATCH(B$4,'Розрахунок'!$A$5:$A$17,0)),"BACKFILL 365")} -> Четвер | C8: {=IF(IFERROR(VLOOKUP(C$4,'Налаштування'!$F$39:$K$100,6,FALSE),"ONBOARDING")="ACTIVE",INDEX('Розрахунок'!$G$5:$G$17,MATCH(C$4,'Розрахунок'!$A$5:$A$17,0)),"BACKFILL 365")} -> Вівторок/Середа/Субота • по 1 (нічия) | D8: {=IF(IFERROR(VLOOKUP(D$4,'Налаштування'!$F$39:$K$100,6,FALSE),"ONBOARDING")="ACTIVE",INDEX('Розрахунок'!$G$5:$G$17,MATCH(D$4,'Розрахунок'!$A$5:$A$17,0)),"BACKFILL 365")} -> Немає | E8: {=IF(IFERROR(VLOOKUP(E$4,'Налаштування'!$F$39:$K$100,6,FALSE),"ONBOARDING")="ACTIVE",INDEX('Розрахунок'!$G$5:$G$17,MATCH(E$4,'Розрахунок'!$A$5:$A$17,0)),"BACKFILL 365")} -> Середа/Четвер • по 2 (нічия) | F8: {=IF(IFERROR(VLOOKUP(F$4,'Налаштування'!$F$39:$K$100,6,FALSE),"ONBOARDING")="ACTIVE",INDEX('Розрахунок'!$G$5:$G$17,MATCH(F$4,'Розрахунок'!$A$5:$A$17,0)),"BACKFILL 365")} -> Середа/П’ятниця • по 1 (нічия) | G8: {=IF(IFERROR(VLOOKUP(G$4,'Налаштування'!$F$39:$K$100,6,FALSE),"ONBOARDING")="ACTIVE",INDEX('Розрахунок'!$G$5:$G$17,MATCH(G$4,'Розрахунок'!$A$5:$A$17,0)),"BACKFILL 365")} -> Вівторок/Середа/Четвер • по 1 (нічия) | H8: {=IF(IFERROR(VLOOKUP(H$4,'Налаштування'!$F$39:$K$100,6,FALSE),"ONBOARDING")="ACTIVE",INDEX('Розрахунок'!$G$5:$G$17,MATCH(H$4,'Розрахунок'!$A$5:$A$17,0)),"BACKFILL 365")} -> Немає | I8: {=IF(IFERROR(VLOOKUP(I$4,'Налаштування'!$F$39:$K$100,6,FALSE),"ONBOARDING")="ACTIVE",INDEX('Розрахунок'!$G$5:$G$17,MATCH(I$4,'Розрахунок'!$A$5:$A$17,0)),"BACKFILL 365")} -> Немає | ... N8: {=IF(IFERROR(VLOOKUP(N$4,'Налаштування'!$F$39:$K$100,6,FALSE),"ONBOARDING")="ACTIVE",INDEX('Розрахунок'!$G$5:$G$17,MATCH(N$4,'Розрахунок'!$A$5:$A$17,0)),"BACKFILL 365")} -> Немає | O8: {=IF(IFERROR(VLOOKUP(O$4,'Налаштування'!$F$39:$K$100,6,FALSE),"ONBOARDING")="ACTIVE",INDEX('Розрахунок'!$G$5:$G$18,MATCH(O$4,'Розрахунок'!$A$5:$A$18,0)),"BACKFILL 365")} -> Немає | P8: City-specific домінантний день серед балістичних attack-days
A9: Сила домінанти | B9: {=IF(IFERROR(VLOOKUP(B$4,'Налаштування'!$F$39:$K$100,6,FALSE),"ONBOARDING")="ACTIVE",INDEX('Розрахунок'!$H$5:$H$17,MATCH(B$4,'Розрахунок'!$A$5:$A$17,0)),"")} -> 0.33333333 | C9: {=IF(IFERROR(VLOOKUP(C$4,'Налаштування'!$F$39:$K$100,6,FALSE),"ONBOARDING")="ACTIVE",INDEX('Розрахунок'!$H$5:$H$17,MATCH(C$4,'Розрахунок'!$A$5:$A$17,0)),"")} -> 0 | D9: {=IF(IFERROR(VLOOKUP(D$4,'Налаштування'!$F$39:$K$100,6,FALSE),"ONBOARDING")="ACTIVE",INDEX('Розрахунок'!$H$5:$H$17,MATCH(D$4,'Розрахунок'!$A$5:$A$17,0)),"")} -> 0 | E9: {=IF(IFERROR(VLOOKUP(E$4,'Налаштування'!$F$39:$K$100,6,FALSE),"ONBOARDING")="ACTIVE",INDEX('Розрахунок'!$H$5:$H$17,MATCH(E$4,'Розрахунок'!$A$5:$A$17,0)),"")} -> 0 | F9: {=IF(IFERROR(VLOOKUP(F$4,'Налаштування'!$F$39:$K$100,6,FALSE),"ONBOARDING")="ACTIVE",INDEX('Розрахунок'!$H$5:$H$17,MATCH(F$4,'Розрахунок'!$A$5:$A$17,0)),"")} -> 0 | G9: {=IF(IFERROR(VLOOKUP(G$4,'Налаштування'!$F$39:$K$100,6,FALSE),"ONBOARDING")="ACTIVE",INDEX('Розрахунок'!$H$5:$H$17,MATCH(G$4,'Розрахунок'!$A$5:$A$17,0)),"")} -> 0 | H9: {=IF(IFERROR(VLOOKUP(H$4,'Налаштування'!$F$39:$K$100,6,FALSE),"ONBOARDING")="ACTIVE",INDEX('Розрахунок'!$H$5:$H$17,MATCH(H$4,'Розрахунок'!$A$5:$A$17,0)),"")} -> 0 | I9: {=IF(IFERROR(VLOOKUP(I$4,'Налаштування'!$F$39:$K$100,6,FALSE),"ONBOARDING")="ACTIVE",INDEX('Розрахунок'!$H$5:$H$17,MATCH(I$4,'Розрахунок'!$A$5:$A$17,0)),"")} -> 0 | ... N9: {=IF(IFERROR(VLOOKUP(N$4,'Налаштування'!$F$39:$K$100,6,FALSE),"ONBOARDING")="ACTIVE",INDEX('Розрахунок'!$H$5:$H$17,MATCH(N$4,'Розрахунок'!$A$5:$A$17,0)),"")} -> 0 | O9: {=IF(IFERROR(VLOOKUP(O$4,'Налаштування'!$F$39:$K$100,6,FALSE),"ONBOARDING")="ACTIVE",INDEX('Розрахунок'!$H$5:$H$18,MATCH(O$4,'Розрахунок'!$A$5:$A$18,0)),"")} -> 0 | P9: Частка домінантного дня серед attack-days за 56 днів
A10: Зсув режиму | B10: {=IF(IFERROR(VLOOKUP(B$4,'Налаштування'!$F$39:$K$100,6,FALSE),"ONBOARDING")="ACTIVE",INDEX('Розрахунок'!$J$5:$J$17,MATCH(B$4,'Розрахунок'!$A$5:$A$17,0)),"—")} -> — | C10: {=IF(IFERROR(VLOOKUP(C$4,'Налаштування'!$F$39:$K$100,6,FALSE),"ONBOARDING")="ACTIVE",INDEX('Розрахунок'!$J$5:$J$17,MATCH(C$4,'Розрахунок'!$A$5:$A$17,0)),"—")} -> — | D10: {=IF(IFERROR(VLOOKUP(D$4,'Налаштування'!$F$39:$K$100,6,FALSE),"ONBOARDING")="ACTIVE",INDEX('Розрахунок'!$J$5:$J$17,MATCH(D$4,'Розрахунок'!$A$5:$A$17,0)),"—")} -> — | E10: {=IF(IFERROR(VLOOKUP(E$4,'Налаштування'!$F$39:$K$100,6,FALSE),"ONBOARDING")="ACTIVE",INDEX('Розрахунок'!$J$5:$J$17,MATCH(E$4,'Розрахунок'!$A$5:$A$17,0)),"—")} -> — | F10: {=IF(IFERROR(VLOOKUP(F$4,'Налаштування'!$F$39:$K$100,6,FALSE),"ONBOARDING")="ACTIVE",INDEX('Розрахунок'!$J$5:$J$17,MATCH(F$4,'Розрахунок'!$A$5:$A$17,0)),"—")} -> — | G10: {=IF(IFERROR(VLOOKUP(G$4,'Налаштування'!$F$39:$K$100,6,FALSE),"ONBOARDING")="ACTIVE",INDEX('Розрахунок'!$J$5:$J$17,MATCH(G$4,'Розрахунок'!$A$5:$A$17,0)),"—")} -> — | H10: {=IF(IFERROR(VLOOKUP(H$4,'Налаштування'!$F$39:$K$100,6,FALSE),"ONBOARDING")="ACTIVE",INDEX('Розрахунок'!$J$5:$J$17,MATCH(H$4,'Розрахунок'!$A$5:$A$17,0)),"—")} -> — | I10: {=IF(IFERROR(VLOOKUP(I$4,'Налаштування'!$F$39:$K$100,6,FALSE),"ONBOARDING")="ACTIVE",INDEX('Розрахунок'!$J$5:$J$17,MATCH(I$4,'Розрахунок'!$A$5:$A$17,0)),"—")} -> — | ... N10: {=IF(IFERROR(VLOOKUP(N$4,'Налаштування'!$F$39:$K$100,6,FALSE),"ONBOARDING")="ACTIVE",INDEX('Розрахунок'!$J$5:$J$17,MATCH(N$4,'Розрахунок'!$A$5:$A$17,0)),"—")} -> — | O10: {=IF(IFERROR(VLOOKUP(O$4,'Налаштування'!$F$39:$K$100,6,FALSE),"ONBOARDING")="ACTIVE",INDEX('Розрахунок'!$J$5:$J$18,MATCH(O$4,'Розрахунок'!$A$5:$A$18,0)),"—")} -> — | P10: Порівняння останніх 56 днів з попередніми 56
A11: Домінантний день = цільовому? | B11: {=IF(IFERROR(VLOOKUP(B$4,'Налаштування'!$F$39:$K$100,6,FALSE),"ONBOARDING")="ACTIVE",INDEX('Розрахунок'!$K$5:$K$17,MATCH(B$4,'Розрахунок'!$A$5:$A$17,0)),"—")} -> Ні | C11: {=IF(IFERROR(VLOOKUP(C$4,'Налаштування'!$F$39:$K$100,6,FALSE),"ONBOARDING")="ACTIVE",INDEX('Розрахунок'!$K$5:$K$17,MATCH(C$4,'Розрахунок'!$A$5:$A$17,0)),"—")} -> — | D11: {=IF(IFERROR(VLOOKUP(D$4,'Налаштування'!$F$39:$K$100,6,FALSE),"ONBOARDING")="ACTIVE",INDEX('Розрахунок'!$K$5:$K$17,MATCH(D$4,'Розрахунок'!$A$5:$A$17,0)),"—")} -> — | E11: {=IF(IFERROR(VLOOKUP(E$4,'Налаштування'!$F$39:$K$100,6,FALSE),"ONBOARDING")="ACTIVE",INDEX('Розрахунок'!$K$5:$K$17,MATCH(E$4,'Розрахунок'!$A$5:$A$17,0)),"—")} -> — | F11: {=IF(IFERROR(VLOOKUP(F$4,'Налаштування'!$F$39:$K$100,6,FALSE),"ONBOARDING")="ACTIVE",INDEX('Розрахунок'!$K$5:$K$17,MATCH(F$4,'Розрахунок'!$A$5:$A$17,0)),"—")} -> — | G11: {=IF(IFERROR(VLOOKUP(G$4,'Налаштування'!$F$39:$K$100,6,FALSE),"ONBOARDING")="ACTIVE",INDEX('Розрахунок'!$K$5:$K$17,MATCH(G$4,'Розрахунок'!$A$5:$A$17,0)),"—")} -> — | H11: {=IF(IFERROR(VLOOKUP(H$4,'Налаштування'!$F$39:$K$100,6,FALSE),"ONBOARDING")="ACTIVE",INDEX('Розрахунок'!$K$5:$K$17,MATCH(H$4,'Розрахунок'!$A$5:$A$17,0)),"—")} -> — | I11: {=IF(IFERROR(VLOOKUP(I$4,'Налаштування'!$F$39:$K$100,6,FALSE),"ONBOARDING")="ACTIVE",INDEX('Розрахунок'!$K$5:$K$17,MATCH(I$4,'Розрахунок'!$A$5:$A$17,0)),"—")} -> — | ... N11: {=IF(IFERROR(VLOOKUP(N$4,'Налаштування'!$F$39:$K$100,6,FALSE),"ONBOARDING")="ACTIVE",INDEX('Розрахунок'!$K$5:$K$17,MATCH(N$4,'Розрахунок'!$A$5:$A$17,0)),"—")} -> — | O11: {=IF(IFERROR(VLOOKUP(O$4,'Налаштування'!$F$39:$K$100,6,FALSE),"ONBOARDING")="ACTIVE",INDEX('Розрахунок'!$K$5:$K$18,MATCH(O$4,'Розрахунок'!$A$5:$A$18,0)),"—")} -> — | P11: Автоматичний індикатор, не прогноз
A12: Загальноукраїнський тижневий цикл | B12: Очікуємо новий цикл | P12: Автоматично з «Глобальні хвилі». DESCRIPTIVE CONTEXT ONLY: не змінює % автоматично до валідованого pre-event backtest.
A13: Доставка балістичних ракет | P13: Є / Немає / Н/Д. Фіксуємо сам факт доставки, без ручної ваги.
A14: Кількість споряджених ПУ Іскандер-М / KN-23 | P14: Число ≥ 0. Порожньо = Н/Д. Не підставляти оцінку замість підтвердженої кількості.
A15: Кількість споряджених ПУ Циркон / Онікс | P15: Число ≥ 0. Порожньо = Н/Д. Не підставляти оцінку замість підтвердженої кількості.
A16: КШМ 9С552 / ППІ 9С920 | P16: Зафіксовано / Не зафіксовано / Н/Д.
A17: Активність 24 години | P17: Підвищує / Нейтрально / Знижує / Н/Д. Оцінка напряму впливу за останні 24 год.
A18: Активність 72 години | P18: Підвищує / Нейтрально / Знижує / Н/Д. Оцінка напряму впливу за останні 72 год.
A19: Дружні дані ГУР | P19: Підвищує / Нейтрально / Знижує / Н/Д. Без числової ваги до калібрування.
A20: Дружні зовнішні дані | P20: Підвищує / Нейтрально / Знижує / Н/Д. Без числової ваги до калібрування.
A21: Попередження ПС | P21: Є / Немає / Н/Д. Фіксуємо наявність попередження ПС.
A22: Попередження ГУР | P22: Є / Немає / Н/Д. Фіксуємо наявність попередження ГУР.
A23: Наші добрі дрони | P23: Вплив на базу: На полюванні −3 п.п.; Без полювання +3 п.п.; не летіли = без змін. Очищається о 05:00.
A24: Робочий % - після індикаторів | B24: =IFERROR(__xludf.DUMMYFUNCTION("IF(MOD(NOW(),1)<TIME(5,0,0),IFERROR(INDEX(FILTER('Архів оцінок'!$O$2:$O$7000,'Архів оцінок'!$B$2:$B$7000=$B$2,'Архів оцінок'!$C$2:$C$7000=B$4,'Архів оцінок'!$AG$2:$AG$7000=""OPS_FINAL""),1),""""),IF(IFERROR(VLOOKUP(B$4,'Налаштування'!$F$39:$K$100,6,FALSE)"&",""ONBOARDING"")<>""ACTIVE"","""",IF(OR(B23="""",IF(B$4=""Київ"",B5,B7)=""""),"""",MAX(0,MIN(1,IF(B$4=""Київ"",B5,B7)+IF(B23=""На полюванні"",-3%,IF(B23=""Без полювання"",3%,0)))))))"),"") | C24: =IFERROR(__xludf.DUMMYFUNCTION("IF(MOD(NOW(),1)<TIME(5,0,0),IFERROR(INDEX(FILTER('Архів оцінок'!$O$2:$O$7000,'Архів оцінок'!$B$2:$B$7000=$B$2,'Архів оцінок'!$C$2:$C$7000=C$4,'Архів оцінок'!$AG$2:$AG$7000=""OPS_FINAL""),1),""""),IF(IFERROR(VLOOKUP(C$4,'Налаштування'!$F$39:$K$100,6,FALSE)"&",""ONBOARDING"")<>""ACTIVE"","""",IF(OR(C23="""",IF(C$4=""Київ"",C5,C7)=""""),"""",MAX(0,MIN(1,IF(C$4=""Київ"",C5,C7)+IF(C23=""На полюванні"",-3%,IF(C23=""Без полювання"",3%,0)))))))"),"") | D24: =IFERROR(__xludf.DUMMYFUNCTION("IF(MOD(NOW(),1)<TIME(5,0,0),IFERROR(INDEX(FILTER('Архів оцінок'!$O$2:$O$7000,'Архів оцінок'!$B$2:$B$7000=$B$2,'Архів оцінок'!$C$2:$C$7000=D$4,'Архів оцінок'!$AG$2:$AG$7000=""OPS_FINAL""),1),""""),IF(IFERROR(VLOOKUP(D$4,'Налаштування'!$F$39:$K$100,6,FALSE)"&",""ONBOARDING"")<>""ACTIVE"","""",IF(OR(D23="""",IF(D$4=""Київ"",D5,D7)=""""),"""",MAX(0,MIN(1,IF(D$4=""Київ"",D5,D7)+IF(D23=""На полюванні"",-3%,IF(D23=""Без полювання"",3%,0)))))))"),"") | E24: =IFERROR(__xludf.DUMMYFUNCTION("IF(MOD(NOW(),1)<TIME(5,0,0),IFERROR(INDEX(FILTER('Архів оцінок'!$O$2:$O$7000,'Архів оцінок'!$B$2:$B$7000=$B$2,'Архів оцінок'!$C$2:$C$7000=E$4,'Архів оцінок'!$AG$2:$AG$7000=""OPS_FINAL""),1),""""),IF(IFERROR(VLOOKUP(E$4,'Налаштування'!$F$39:$K$100,6,FALSE)"&",""ONBOARDING"")<>""ACTIVE"","""",IF(OR(E23="""",IF(E$4=""Київ"",E5,E7)=""""),"""",MAX(0,MIN(1,IF(E$4=""Київ"",E5,E7)+IF(E23=""На полюванні"",-3%,IF(E23=""Без полювання"",3%,0)))))))"),"") | F24: =IFERROR(__xludf.DUMMYFUNCTION("IF(MOD(NOW(),1)<TIME(5,0,0),IFERROR(INDEX(FILTER('Архів оцінок'!$O$2:$O$7000,'Архів оцінок'!$B$2:$B$7000=$B$2,'Архів оцінок'!$C$2:$C$7000=F$4,'Архів оцінок'!$AG$2:$AG$7000=""OPS_FINAL""),1),""""),IF(IFERROR(VLOOKUP(F$4,'Налаштування'!$F$39:$K$100,6,FALSE)"&",""ONBOARDING"")<>""ACTIVE"","""",IF(OR(F23="""",IF(F$4=""Київ"",F5,F7)=""""),"""",MAX(0,MIN(1,IF(F$4=""Київ"",F5,F7)+IF(F23=""На полюванні"",-3%,IF(F23=""Без полювання"",3%,0)))))))"),"") | G24: =IFERROR(__xludf.DUMMYFUNCTION("IF(MOD(NOW(),1)<TIME(5,0,0),IFERROR(INDEX(FILTER('Архів оцінок'!$O$2:$O$7000,'Архів оцінок'!$B$2:$B$7000=$B$2,'Архів оцінок'!$C$2:$C$7000=G$4,'Архів оцінок'!$AG$2:$AG$7000=""OPS_FINAL""),1),""""),IF(IFERROR(VLOOKUP(G$4,'Налаштування'!$F$39:$K$100,6,FALSE)"&",""ONBOARDING"")<>""ACTIVE"","""",IF(OR(G23="""",IF(G$4=""Київ"",G5,G7)=""""),"""",MAX(0,MIN(1,IF(G$4=""Київ"",G5,G7)+IF(G23=""На полюванні"",-3%,IF(G23=""Без полювання"",3%,0)))))))"),"") | H24: =IFERROR(__xludf.DUMMYFUNCTION("IF(MOD(NOW(),1)<TIME(5,0,0),IFERROR(INDEX(FILTER('Архів оцінок'!$O$2:$O$7000,'Архів оцінок'!$B$2:$B$7000=$B$2,'Архів оцінок'!$C$2:$C$7000=H$4,'Архів оцінок'!$AG$2:$AG$7000=""OPS_FINAL""),1),""""),IF(IFERROR(VLOOKUP(H$4,'Налаштування'!$F$39:$K$100,6,FALSE)"&",""ONBOARDING"")<>""ACTIVE"","""",IF(OR(H23="""",IF(H$4=""Київ"",H5,H7)=""""),"""",MAX(0,MIN(1,IF(H$4=""Київ"",H5,H7)+IF(H23=""На полюванні"",-3%,IF(H23=""Без полювання"",3%,0)))))))"),"") | I24: =IFERROR(__xludf.DUMMYFUNCTION("IF(MOD(NOW(),1)<TIME(5,0,0),IFERROR(INDEX(FILTER('Архів оцінок'!$O$2:$O$7000,'Архів оцінок'!$B$2:$B$7000=$B$2,'Архів оцінок'!$C$2:$C$7000=I$4,'Архів оцінок'!$AG$2:$AG$7000=""OPS_FINAL""),1),""""),IF(IFERROR(VLOOKUP(I$4,'Налаштування'!$F$39:$K$100,6,FALSE)"&",""ONBOARDING"")<>""ACTIVE"","""",IF(OR(I23="""",IF(I$4=""Київ"",I5,I7)=""""),"""",MAX(0,MIN(1,IF(I$4=""Київ"",I5,I7)+IF(I23=""На полюванні"",-3%,IF(I23=""Без полювання"",3%,0)))))))"),"") | J24: =IFERROR(__xludf.DUMMYFUNCTION("IF(MOD(NOW(),1)<TIME(5,0,0),IFERROR(INDEX(FILTER('Архів оцінок'!$O$2:$O$7000,'Архів оцінок'!$B$2:$B$7000=$B$2,'Архів оцінок'!$C$2:$C$7000=J$4,'Архів оцінок'!$AG$2:$AG$7000=""OPS_FINAL""),1),""""),IF(IFERROR(VLOOKUP(J$4,'Налаштування'!$F$39:$K$100,6,FALSE)"&",""ONBOARDING"")<>""ACTIVE"","""",IF(OR(J23="""",IF(J$4=""Київ"",J5,J7)=""""),"""",MAX(0,MIN(1,IF(J$4=""Київ"",J5,J7)+IF(J23=""На полюванні"",-3%,IF(J23=""Без полювання"",3%,0)))))))"),"") | K24: =IFERROR(__xludf.DUMMYFUNCTION("IF(MOD(NOW(),1)<TIME(5,0,0),IFERROR(INDEX(FILTER('Архів оцінок'!$O$2:$O$7000,'Архів оцінок'!$B$2:$B$7000=$B$2,'Архів оцінок'!$C$2:$C$7000=K$4,'Архів оцінок'!$AG$2:$AG$7000=""OPS_FINAL""),1),""""),IF(IFERROR(VLOOKUP(K$4,'Налаштування'!$F$39:$K$100,6,FALSE)"&",""ONBOARDING"")<>""ACTIVE"","""",IF(OR(K23="""",IF(K$4=""Київ"",K5,K7)=""""),"""",MAX(0,MIN(1,IF(K$4=""Київ"",K5,K7)+IF(K23=""На полюванні"",-3%,IF(K23=""Без полювання"",3%,0)))))))"),"") | L24: =IFERROR(__xludf.DUMMYFUNCTION("IF(MOD(NOW(),1)<TIME(5,0,0),IFERROR(INDEX(FILTER('Архів оцінок'!$O$2:$O$7000,'Архів оцінок'!$B$2:$B$7000=$B$2,'Архів оцінок'!$C$2:$C$7000=L$4,'Архів оцінок'!$AG$2:$AG$7000=""OPS_FINAL""),1),""""),IF(IFERROR(VLOOKUP(L$4,'Налаштування'!$F$39:$K$100,6,FALSE)"&",""ONBOARDING"")<>""ACTIVE"","""",IF(OR(L23="""",IF(L$4=""Київ"",L5,L7)=""""),"""",MAX(0,MIN(1,IF(L$4=""Київ"",L5,L7)+IF(L23=""На полюванні"",-3%,IF(L23=""Без полювання"",3%,0)))))))"),"") | M24: =IFERROR(__xludf.DUMMYFUNCTION("IF(MOD(NOW(),1)<TIME(5,0,0),IFERROR(INDEX(FILTER('Архів оцінок'!$O$2:$O$7000,'Архів оцінок'!$B$2:$B$7000=$B$2,'Архів оцінок'!$C$2:$C$7000=M$4,'Архів оцінок'!$AG$2:$AG$7000=""OPS_FINAL""),1),""""),IF(IFERROR(VLOOKUP(M$4,'Налаштування'!$F$39:$K$100,6,FALSE)"&",""ONBOARDING"")<>""ACTIVE"","""",IF(OR(M23="""",IF(M$4=""Київ"",M5,M7)=""""),"""",MAX(0,MIN(1,IF(M$4=""Київ"",M5,M7)+IF(M23=""На полюванні"",-3%,IF(M23=""Без полювання"",3%,0)))))))"),"") | N24: =IFERROR(__xludf.DUMMYFUNCTION("IF(MOD(NOW(),1)<TIME(5,0,0),IFERROR(INDEX(FILTER('Архів оцінок'!$O$2:$O$7000,'Архів оцінок'!$B$2:$B$7000=$B$2,'Архів оцінок'!$C$2:$C$7000=N$4,'Архів оцінок'!$AG$2:$AG$7000=""OPS_FINAL""),1),""""),IF(IFERROR(VLOOKUP(N$4,'Налаштування'!$F$39:$K$100,6,FALSE)"&",""ONBOARDING"")<>""ACTIVE"","""",IF(OR(N23="""",IF(N$4=""Київ"",N5,N7)=""""),"""",MAX(0,MIN(1,IF(N$4=""Київ"",N5,N7)+IF(N23=""На полюванні"",-3%,IF(N23=""Без полювання"",3%,0)))))))"),"") | O24: =IFERROR(__xludf.DUMMYFUNCTION("IF(MOD(NOW(),1)<TIME(5,0,0),IFERROR(INDEX(FILTER('Архів оцінок'!$O$2:$O$7000,'Архів оцінок'!$B$2:$B$7000=$B$2,'Архів оцінок'!$C$2:$C$7000=O$4,'Архів оцінок'!$AG$2:$AG$7000=""OPS_FINAL""),1),""""),IF(IFERROR(VLOOKUP(O$4,'Налаштування'!$F$39:$K$100,6,FALSE)"&",""ONBOARDING"")<>""ACTIVE"","""",IF(OR(O23="""",IF(O$4=""Київ"",O5,O7)=""""),"""",MAX(0,MIN(1,IF(O$4=""Київ"",O5,O7)+IF(O23=""На полюванні"",-3%,IF(O23=""Без полювання"",3%,0)))))))"),"") | P24: Авто після 05:00: Київ = Smoothed base 50/50; інші ACTIVE міста = R56 поточного дня; далі ±3 п.п. за «Наші добрі дрони». До 05:00 показується archived OPS_FINAL.
A25: Коментар / рішення на ніч

Sheet Реєстр
A1: ID | B1: Місто / модель | C1: Категорія загрози | D1: Дата балістичної фази | E1: День тижня | F1: № тижня місяця | G1: Частина місяця | H1: Атак цієї доби | I1: Географія | J1: Тип ракети / засобу | K1: Комбінована атака | L1: Рівень підтвердження | M1: Короткий опис | N1: Джерело 1 | O1: Джерело 2 | P1: Примітка | Q1: Початок усієї операції | R1: Час балістичної фази | S1: Балістичних ракет по регіону | T1: Статус кількості ракет | U1: Прямі влучання балістики в житло | V1: Статус атрибуції | W1: Географія влучання | X1: Тип житла | Y1: Пошкоджено житлових будинків (усі засоби) | Z1: Джерело наслідків | AA1: Примітка до наслідків | AB1: Зона моделі | AC1: Статус аудиту | AD1: ID епізоду | AE1: Балістика | AF1: Крилаті ракети | AG1: Х-101/Х-555 | AH1: Shahed/Герань | AI1: Онікс | AJ1: Бандероль | AK1: Іскандер-К | AL1: Інші ракети | AM1: К-сть БПЛА | AN1: К-сть ракет | AO1: Профіль атаки | AP1: Статус профілю | AQ1: Період режиму | AR1: Використання в моделі
A2: 1 | B2: Дніпро | C2: Балістика / швидкісні ракети | D2: 2024-11-21 | E2: Четвер | F2: 3 | G2: Кінець | H2: 1 | I2: Дніпро | J2: Орєшнік / балістична ракета середньої дальності | K2: Так | L2: A — пряма локальна прив’язка | M2: 21 листопада Дніпро атаковано новою балістичною ракетою, Кинджалом та сімома Х-101. | N2: https://suspilne.media/dnipro/884789-armia-rf-atakuvala-dnipro-mizkontinentalnou-balisticnou-raketou-kindzalom-i-h-101/ | P2: У реєстрі зберігаємо підтверджений факт балістичного компонента; остаточна технічна назва не впливає на епізод. | Q2: 05:00 | R2: 05:00–07:00 | S2: 1 | T2: Підтверджено | V2: Підтверджено | W2: Дніпро | Z2: https://suspilne.media/dnipro/884789-armia-rf-atakuvala-dnipro-mizkontinentalnou-balisticnou-raketou-kindzalom-i-h-101/ | AB2: Дніпро | AC2: Включено — прямий підтверджений балістичний епізод по Дніпру | AD2: DNI-20241121-003 | AE2: Так | AF2: Так | AG2: Так | AH2: Ні | AL2: Так | AN2: 9 | AO2: балістика + Х-101/Х-555 + інші ракети | AP2: Підтверджено джерелом | AQ2: =IF(D2="","",IF(IFERROR(DATEVALUE(D2),0)<DATE(2024,9,1),"ERA-1 • масовані/ракетно-комбіновані",IF(IFERROR(DATEVALUE(D2),0)<DATE(2025,7,1),"ERA-2 • drone-saturation transition",IF(IFERROR(DATEVALUE(D2),0)<DATE(2026,4,1),"ERA-3 • змішаний / зростання балістики","ERA-4 • поточний балістично-насичений")))) -> ERA-2 • drone-saturation transition | AR2: =IF(D2="","",IF(IFERROR(DATEVALUE(D2),0)>='Розрахунок'!$B$2-365,"MODEL-365","HISTORICAL_ONLY")) -> HISTORICAL_ONLY
A3: 2 | B3: Дніпро | C3: Балістика / швидкісні ракети | D3: 2025-04-10 | E3: Четвер | F3: 2 | G3: Початок | H3: 1 | I3: Дніпро | J3: Балістичне озброєння | K3: Ні | L3: A — пряма локальна прив’язка | M3: 10 квітня по Дніпру застосовано балістичне озброєння; є загиблий і поранені. | N3: https://suspilne.media/dnipro/991861-u-dnipri-prolunali-zvuki-vibuhu/ | P3: Повітряні сили повідомляли про балістичне озброєння та швидкісну ціль на Дніпро. | T3: Тип/кількість локально не уточнюємо | V3: Підтверджено | W3: Дніпро | Z3: https://suspilne.media/dnipro/991861-u-dnipri-prolunali-zvuki-vibuhu/ | AB3: Дніпро | AC3: Включено — прямий підтверджений балістичний епізод по Дніпру | AD3: DNI-20250410-002 | AE3: Так | AF3: Ні | AH3: Ні | AO3: балістика | AP3: Підтверджено джерелом | AQ3: =IF(D3="","",IF(IFERROR(DATEVALUE(D3),0)<DATE(2024,9,1),"ERA-1 • масовані/ракетно-комбіновані",IF(IFERROR(DATEVALUE(D3),0)<DATE(2025,7,1),"ERA-2 • drone-saturation transition",IF(IFERROR(DATEVALUE(D3),0)<DATE(2026,4,1),"ERA-3 • змішаний / зростання балістики","ERA-4 • поточний балістично-насичений")))) -> ERA-2 • drone-saturation transition | AR3: =IF(D3="","",IF(IFERROR(DATEVALUE(D3),0)>='Розрахунок'!$B$2-365,"MODEL-365","HISTORICAL_ONLY")) -> HISTORICAL_ONLY
A4: 3 | B4: Харків | C4: Балістика / швидкісні ракети | D4: 2025-06-02 | E4: Понеділок | F4: 1 | G4: Початок | H4: 1 | I4: Харків | J4: 2 балістичні ракети; KN-23 / 9М723 Іскандер — остаточний subtype не встановлено | K4: Так | L4: A — пряма локальна прив’язка | M4: На світанку 2 червня по Київському району Харкова РФ вдарила двома засобами балістичного ураження. | N4: https://kharkivoda.gov.ua/news/131680 | O4: https://suspilne.media/kharkiv/1032343-dla-udaru-po-harkovu-rosiani-jmovirno-vikoristali-pivnicnokorejski-kn-23-comu-ne-vdaetsa-utocniti-tip-raket/ | P4: Балістичний клас і кількість підтверджені; точний subtype не фіксуємо без остаточної експертизи. | R4: ~04:08 | S4: 2 | T4: Підтверджено: 2 | V4: Балістика підтверджена | W4: Харків | Z4: https://suspilne.media/kharkiv/1032343-dla-udaru-po-harkovu-rosiani-jmovirno-vikoristali-pivnicnokorejski-kn-23-comu-ne-vdaetsa-utocniti-tip-raket/ | AA4: Наслідки в Київському районі; паралельно місто атакували БпЛА. | AB4: Харків | AC4: Включено — пряме підтвердження двох балістичних ракет по Харкову | AD4: KHR-20250602-180 | AE4: Так | AH4: Так | AN4: 2 | AO4: балістика + БпЛА | AP4: Профіль підтверджено за двома джерелами | AQ4: =IF(D4="","",IF(IFERROR(DATEVALUE(D4),0)<DATE(2024,9,1),"ERA-1 • масовані/ракетно-комбіновані",IF(IFERROR(DATEVALUE(D4),0)<DATE(2025,7,1),"ERA-2 • drone-saturation transition",IF(IFERROR(DATEVALUE(D4),0)<DATE(2026,4,1),"ERA-3 • змішаний / зростання балістики","ERA-4 • поточний балістично-насичений")))) -> ERA-2 • drone-saturation transition | AR4: =IF(D4="","",IF(IFERROR(DATEVALUE(D4),0)>='Розрахунок'!$B$2-365,"MODEL-365","HISTORICAL_ONLY")) -> HISTORICAL_ONLY
A5: 4 | B5: Київ | C5: Балістика / швидкісні ракети | D5: 2025-06-06 | E5: П’ятниця | F5: 1 | G5: Початок | H5: 1 | I5: Київ + область | J5: Core ballistic | K5: Так | L5: A — пряма/локальна прив’язка | M5: Масована комбінована атака Києва та області із застосуванням балістики | N5: https://www.pravda.com.ua/news/2025/06/06/7515869/ | O5: https://suspilne.media/kyiv/1035803-armia-rf-atakuvala-kiivsinu-poskodzeni-privatni-budinki/ | P5: Пряме підтвердження балістичної складової по столиці. | AB5: Київ | AC5: Включено — 06.06: КМВА прямо підтвердила комбіновану атаку Києва балістикою та ударними БпЛА | AD5: KYI-20250606-139 | AE5: Так | AO5: балістика | AP5: Профіль підтверджено за джерелами аудованого реєстру | AQ5: =IF(D5="","",IF(IFERROR(DATEVALUE(D5),0)<DATE(2024,9,1),"ERA-1 • масовані/ракетно-комбіновані",IF(IFERROR(DATEVALUE(D5),0)<DATE(2025,7,1),"ERA-2 • drone-saturation transition",IF(IFERROR(DATEVALUE(D5),0)<DATE(2026,4,1),"ERA-3 • змішаний / зростання балістики","ERA-4 • поточний балістично-насичений")))) -> ERA-2 • drone-saturation transition | AR5: =IF(D5="","",IF(IFERROR(DATEVALUE(D5),0)>='Розрахунок'!$B$2-365,"MODEL-365","HISTORICAL_ONLY")) -> HISTORICAL_ONLY
A6: 5 | B6: Київ | C6: Балістика / швидкісні ракети | D6: 2025-06-10 | E6: Вівторок | F6: 2 | G6: Початок | H6: 1 | I6: Київ + область | J6: Core ballistic | K6: Так | L6: A — пряма/локальна прив’язка | M6: Масована атака Києва та області: БпЛА, крилаті та балістичні ракети | N6: https://www.pravda.com.ua/news/2025/06/10/7516465/ | O6: https://suspilne.media/kyiv/1038329-u-kievi-8-ludej-postrazdali-cerez-ataku-rf-10-cervna/ | P6: Пряме підтвердження балістики по Києву. | AB6: Київ | AC6: Включено — 10.06: Повітряні сили повідомили про балістичну ракету, що підлітала до Києва; у столиці пролунала серія вибухів | AD6: KYI-20250610-138 | AE6: Так | AF6: Так | AH6: Так | AO6: балістика + БпЛА | AP6: Профіль підтверджено за джерелами аудованого реєстру | AQ6: =IF(D6="","",IF(IFERROR(DATEVALUE(D6),0)<DATE(2024,9,1),"ERA-1 • масовані/ракетно-комбіновані",IF(IFERROR(DATEVALUE(D6),0)<DATE(2025,7,1),"ERA-2 • drone-saturation transition",IF(IFERROR(DATEVALUE(D6),0)<DATE(2026,4,1),"ERA-3 • змішаний / зростання балістики","ERA-4 • поточний балістично-насичений")))) -> ERA-2 • drone-saturation transition | AR6: =IF(D6="","",IF(IFERROR(DATEVALUE(D6),0)>='Розрахунок'!$B$2-365,"MODEL-365","HISTORICAL_ONLY")) -> HISTORICAL_ONLY
A7: 6 | B7: Київ | C7: Балістика / швидкісні ракети | D7: 2025-06-17 | E7: Вівторок | F7: 3 | G7: Середина | H7: 1 | I7: Київ + область | J7: Core ballistic | K7: Так | L7: A — пряма/локальна прив’язка | M7: Масована атака Києва та області з балістичною складовою | N7: https://suspilne.media/kyiv/1044811-rf-atakuvala-kiiv-balistikou-ta-dronami-e-poraneni/ | O7: https://www.pravda.com.ua/news/2025/06/17/7517421/ | P7: Пряме підтвердження балістики по столиці. | AB7: Київ | AC7: Включено — 17.06: офіційна київська інформація прямо підтверджує застосування по столиці крилатих і балістичних ракет та БпЛА | AD7: KYI-20250617-137 | AE7: Так | AO7: балістика | AP7: Профіль підтверджено за джерелами аудованого реєстру | AQ7: =IF(D7="","",IF(IFERROR(DATEVALUE(D7),0)<DATE(2024,9,1),"ERA-1 • масовані/ракетно-комбіновані",IF(IFERROR(DATEVALUE(D7),0)<DATE(2025,7,1),"ERA-2 • drone-saturation transition",IF(IFERROR(DATEVALUE(D7),0)<DATE(2026,4,1),"ERA-3 • змішаний / зростання балістики","ERA-4 • поточний балістично-насичений")))) -> ERA-2 • drone-saturation transition | AR7: =IF(D7="","",IF(IFERROR(DATEVALUE(D7),0)>='Розрахунок'!$B$2-365,"MODEL-365","HISTORICAL_ONLY")) -> HISTORICAL_ONLY
A8: 7 | B8: Київ | C8: Балістика / швидкісні ракети | D8: 2025-06-23 | E8: Понеділок | F8: 4 | G8: Кінець | H8: 1 | I8: Київ + область | J8: Core ballistic | K8: Так | L8: A — пряма/локальна прив’язка | M8: Комбінована атака Києва та Київщини балістикою, крилатими ракетами та БпЛА | N8: https://suspilne.media/kyiv/1051535-ataka-na-kiiv-ta-oblast-e-zagibli-ta-poraneni/ | O8: https://www.pravda.com.ua/news/2025/06/23/7518527/ | P8: Пряме підтвердження балістики по Києву. | AB8: Київ | AC8: Включено — 23.06: комбінована атака Києва із застосуванням балістики підтверджена; серії вибухів у столиці під час балістичної загрози | AD8: KYI-20250623-135 | AE8: Так | AF8: Так | AH8: Так | AO8: балістика + БпЛА | AP8: Профіль підтверджено за джерелами аудованого реєстру | AQ8: =IF(D8="","",IF(IFERROR(DATEVALUE(D8),0)<DATE(2024,9,1),"ERA-1 • масовані/ракетно-комбіновані",IF(IFERROR(DATEVALUE(D8),0)<DATE(2025,7,1),"ERA-2 • drone-saturation transition",IF(IFERROR(DATEVALUE(D8),0)<DATE(2026,4,1),"ERA-3 • змішаний / зростання балістики","ERA-4 • поточний балістично-насичений")))) -> ERA-2 • drone-saturation transition | AR8: =IF(D8="","",IF(IFERROR(DATEVALUE(D8),0)>='Розрахунок'!$B$2-365,"MODEL-365","HISTORICAL_ONLY")) -> HISTORICAL_ONLY
A9: 8 | B9: Одеса | C9: Балістика / швидкісні ракети | D9: 2025-06-23 | E9: Понеділок | F9: 4 | G9: Кінець | H9: 1 | I9: Одеса + Одеська область | J9: Балістичні ракети — тип не уточнений | K9: Ні/окремий ракетний епізод | L9: A — пряма/локальна прив’язка | M9: Удень 23 червня Білгород-Дністровський атаковано двома балістичними ракетами; зруйновано ліцей, є загиблі та поранені. | N9: https://suspilne.media/odesa/1049495-rf-atakuvala-bilgorod-dnistrovskij-balistikou-pid-zavalami-navcalnogo-zakladu-mozut-buti-ludi/ | O9: https://suspilne.media/odesa/1067853-udar-po-bilgorod-dnistrovskomu-liceu-na-odesini-ekologi-pidrahuvali-zbitki/ | P9: Пряма локальна прив’язка; кількість 2 підтверджена у пізнішому матеріалі Суспільного. | S9: 2 | T9: Підтверджено | V9: Балістика підтверджена | AB9: Одеса + Одеська область | AC9: Включено — 23.06: прямий підтверджений балістичний удар по Білгороду-Дністровському | AD9: ODS-20250623-136 | AE9: Так | AO9: балістика | AP9: Профіль підтверджено за джерелами аудованого реєстру | AQ9: =IF(D9="","",IF(IFERROR(DATEVALUE(D9),0)<DATE(2024,9,1),"ERA-1 • масовані/ракетно-комбіновані",IF(IFERROR(DATEVALUE(D9),0)<DATE(2025,7,1),"ERA-2 • drone-saturation transition",IF(IFERROR(DATEVALUE(D9),0)<DATE(2026,4,1),"ERA-3 • змішаний / зростання балістики","ERA-4 • поточний балістично-насичений")))) -> ERA-2 • drone-saturation transition | AR9: =IF(D9="","",IF(IFERROR(DATEVALUE(D9),0)>='Розрахунок'!$B$2-365,"MODEL-365","HISTORICAL_ONLY")) -> HISTORICAL_ONLY
A10: 9 | B10: Одеса | C10: Балістика / швидкісні ракети | D10: 2025-06-24 | E10: Вівторок | F10: 4 | G10: Кінець | H10: 1 | I10: Одеса + Одеська область | J10: Іскандер-М | K10: Ні/окремий ракетний епізод | L10: A — офіційне підтвердження ПК Південь | M10: Удень 24 червня Одещину атаковано двома балістичними ракетами Іскандер-М із ТОТ Криму. | N10: https://ivms.mil.gov.ua/wp-content/uploads/2025/07/dovidka-22.06-30.06.2025-1.pdf | P10: Окремий епізод наступної доби; не зливати з ударом по Білгороду-Дністровському 23.06. | S10: 2 | T10: Підтверджено | V10: Іскандер-М підтверджено | AB10: Одеса + Одеська область | AC10: Включено — 24.06: ПК Південь підтверджує 2 Іскандер-М по Одещині | AD10: ODS-20250624-134 | AE10: Так | AO10: балістика | AP10: Профіль підтверджено за джерелами аудованого реєстру | AQ10: =IF(D10="","",IF(IFERROR(DATEVALUE(D10),0)<DATE(2024,9,1),"ERA-1 • масовані/ракетно-комбіновані",IF(IFERROR(DATEVALUE(D10),0)<DATE(2025,7,1),"ERA-2 • drone-saturation transition",IF(IFERROR(DATEVALUE(D10),0)<DATE(2026,4,1),"ERA-3 • змішаний / зростання балістики","ERA-4 • поточний балістично-насичений")))) -> ERA-2 • drone-saturation transition | AR10: =IF(D10="","",IF(IFERROR(DATEVALUE(D10),0)>='Розрахунок'!$B$2-365,"MODEL-365","HISTORICAL_ONLY")) -> HISTORICAL_ONLY
A11: 10 | B11: Дніпро | C11: Балістика / швидкісні ракети | D11: 2025-06-24 | E11: Вівторок | F11: 4 | G11: Кінець | H11: 1 | I11: Дніпро | J11: Балістичні ракети | K11: Так | L11: A — пряма локальна прив’язка | M11: 24 червня 2025 Дніпро зазнав масованої атаки; балістичними ракетами уражено промислове підприємство, пошкоджено понад сотню будівель. | N11: https://suspilne.media/dnipro/1406366-svitla-ne-bulo-majze-piv-roku-u-dnipri-vidremontuvali-gurtozitok-pisla-udaru-rf-u-cervni-2025-roku/ | P11: Пряме ретроспективне підтвердження балістичного удару саме по Дніпру. | T11: Кількість локально не встановлена | V11: Підтверджено | W11: Дніпро | Z11: https://suspilne.media/dnipro/1406366-svitla-ne-bulo-majze-piv-roku-u-dnipri-vidremontuvali-gurtozitok-pisla-udaru-rf-u-cervni-2025-roku/ | AB11: Дніпро | AC11: Включено — прямий підтверджений балістичний епізод по Дніпру | AD11: DNI-20250624-009 | AE11: Так | AH11: Так | AO11: балістика + БпЛА | AP11: Підтверджено джерелом | AQ11: =IF(D11="","",IF(IFERROR(DATEVALUE(D11),0)<DATE(2024,9,1),"ERA-1 • масовані/ракетно-комбіновані",IF(IFERROR(DATEVALUE(D11),0)<DATE(2025,7,1),"ERA-2 • drone-saturation transition",IF(IFERROR(DATEVALUE(D11),0)<DATE(2026,4,1),"ERA-3 • змішаний / зростання балістики","ERA-4 • поточний балістично-насичений")))) -> ERA-2 • drone-saturation transition | AR11: =IF(D11="","",IF(IFERROR(DATEVALUE(D11),0)>='Розрахунок'!$B$2-365,"MODEL-365","HISTORICAL_ONLY")) -> HISTORICAL_ONLY
A12: 11 | B12: Київ | C12: Балістика / швидкісні ракети | D12: 2025-06-29 | E12: Неділя | F12: 5 | G12: Кінець | H12: 1 | I12: Київ + область | J12: Core ballistic | K12: Так | L12: A — пряма/локальна прив’язка | M12: Масована атака Києва та області: дрони, крилаті й балістичні ракети | N12: https://www.pravda.com.ua/news/2025/06/29/7519537/ | O12: https://suspilne.media/kyiv/1057335-ataka-na-kiiv-ta-oblast-e-zagibli-ta-poraneni/ | P12: Пряме підтвердження балістики по Києву. | AB12: Поза city-only / архів аудиту | AC12: Виключено — 29.06: загальноукраїнська атака містила балістику, але локально по Києву підтверджена атака БпЛА; прямої прив’язки балістичного епізоду до столиці не встановлено | AD12: KYI-20250629-133 | AE12: Ні | AH12: Так | AO12: БпЛА | AP12: Профіль не включено до чистої моделі; локально підтверджено БпЛА | AQ12: =IF(D12="","",IF(IFERROR(DATEVALUE(D12),0)<DATE(2024,9,1),"ERA-1 • масовані/ракетно-комбіновані",IF(IFERROR(DATEVALUE(D12),0)<DATE(2025,7,1),"ERA-2 • drone-saturation transition",IF(IFERROR(DATEVALUE(D12),0)<DATE(2026,4,1),"ERA-3 • змішаний / зростання балістики","ERA-4 • поточний балістично-насичений")))) -> ERA-2 • drone-saturation transition | AR12: =IF(D12="","",IF(IFERROR(DATEVALUE(D12),0)>='Розрахунок'!$B$2-365,"MODEL-365","HISTORICAL_ONLY")) -> HISTORICAL_ONLY
A13: 12 | B13: Київ | C13: Балістика / швидкісні ракети | D13: 2025-07-04 | E13: П’ятниця | F13: 1 | G13: Початок | H13: 1 | I13: Київ + область | J13: Core ballistic | K13: Так | L13: A — пряма/локальна прив’язка | M13: Масована атака Києва та області з балістичною складовою | N13: https://www.pravda.com.ua/news/2025/07/04/7520247/ | O13: https://suspilne.media/kyiv/1061729-rf-atakuvala-kiiv-balistikou-ta-dronami/ | P13: Пряме підтвердження балістики по столиці. | AB13: Київ | AC13: Включено — 04.07: Повітряні сили прямо повідомили «балістика на Київ»; у столиці пролунала серія вибухів | AD13: KYI-20250704-132 | AE13: Так | AO13: балістика | AP13: Профіль підтверджено за джерелами аудованого реєстру | AQ13: =IF(D13="","",IF(IFERROR(DATEVALUE(D13),0)<DATE(2024,9,1),"ERA-1 • масовані/ракетно-комбіновані",IF(IFERROR(DATEVALUE(D13),0)<DATE(2025,7,1),"ERA-2 • drone-saturation transition",IF(IFERROR(DATEVALUE(D13),0)<DATE(2026,4,1),"ERA-3 • змішаний / зростання балістики","ERA-4 • поточний балістично-насичений")))) -> ERA-3 • змішаний / зростання балістики | AR13: =IF(D13="","",IF(IFERROR(DATEVALUE(D13),0)>='Розрахунок'!$B$2-365,"MODEL-365","HISTORICAL_ONLY")) -> HISTORICAL_ONLY
A14: 13 | B14: Дніпро | C14: Балістика / швидкісні ракети | D14: 2025-07-04 | E14: П’ятниця | F14: 1 | G14: Початок | H14: 1 | I14: Дніпро | J14: Іскандер-М | K14: Ні | L14: B — локальна прив’язка підтверджена кількома джерелами | M14: Вдень 4 липня підтверджено балістичний удар по Дніпру; зведені дані ідентифікують Іскандер-М. | N14: https://dp.informator.ua/uk/dnipro-v-ukrittya-vorog-vdariv-balistichnoyu-raketoyu-bulo-chutno-vibuh | O14: https://suspilne.media/dnipro/1058981-armia-rf-atakuvala-cotiri-rajoni-dnipropetrovsini-e-poraneni-ta-rujnuvanna/ | P14: Не змішувати з нічною атакою по Києву та іншими ударами по області. | R14: ~16:00 | S14: 1 | T14: Підтверджено зведеними джерелами | V14: Підтверджено | W14: Дніпро | AB14: Дніпро | AC14: Включено — підтверджений балістичний епізод по Дніпру | AD14: DNI-20250704-011 | AE14: Так | AH14: Ні | AN14: 1 | AO14: балістика | AP14: Підтверджено перехресними джерелами | AQ14: =IF(D14="","",IF(IFERROR(DATEVALUE(D14),0)<DATE(2024,9,1),"ERA-1 • масовані/ракетно-комбіновані",IF(IFERROR(DATEVALUE(D14),0)<DATE(2025,7,1),"ERA-2 • drone-saturation transition",IF(IFERROR(DATEVALUE(D14),0)<DATE(2026,4,1),"ERA-3 • змішаний / зростання балістики","ERA-4 • поточний балістично-насичений")))) -> ERA-3 • змішаний / зростання балістики | AR14: =IF(D14="","",IF(IFERROR(DATEVALUE(D14),0)>='Розрахунок'!$B$2-365,"MODEL-365","HISTORICAL_ONLY")) -> HISTORICAL_ONLY
A15: 14 | B15: Київ | C15: Балістика / швидкісні ракети | D15: 2025-07-10 | E15: Четвер | F15: 2 | G15: Початок | H15: 1 | I15: Київ + область | J15: Core ballistic | K15: Так | L15: A — пряма/локальна прив’язка | M15: Масована атака Києва та області балістикою та БпЛА | N15: https://www.pravda.com.ua/news/2025/07/10/7521195/ | O15: https://suspilne.media/kyiv/1067715-ataka-na-kiiv-ta-oblast-e-zagibli-ta-poraneni/ | P15: Пряме підтвердження балістичної складової. | AB15: Київ | AC15: Включено — 10.07: КМВА прямо підтвердила комбіновану атаку Києва балістикою та ударними БпЛА | AD15: KYI-20250710-131 | AE15: Так | AH15: Так | AO15: балістика + БпЛА | AP15: Профіль підтверджено за джерелами аудованого реєстру | AQ15: =IF(D15="","",IF(IFERROR(DATEVALUE(D15),0)<DATE(2024,9,1),"ERA-1 • масовані/ракетно-комбіновані",IF(IFERROR(DATEVALUE(D15),0)<DATE(2025,7,1),"ERA-2 • drone-saturation transition",IF(IFERROR(DATEVALUE(D15),0)<DATE(2026,4,1),"ERA-3 • змішаний / зростання балістики","ERA-4 • поточний балістично-насичений")))) -> ERA-3 • змішаний / зростання балістики | AR15: =IF(D15="","",IF(IFERROR(DATEVALUE(D15),0)>='Розрахунок'!$B$2-365,"MODEL-365","HISTORICAL_ONLY")) -> HISTORICAL_ONLY
A16: 15 | B16: Київ | C16: Балістика / швидкісні ракети | D16: 2025-07-12 | E16: Субота | F16: 2 | G16: Початок | H16: 1 | I16: Київ + область | J16: Core ballistic | K16: Так | L16: A — пряма/локальна прив’язка | M16: Нічна атака Києва та Київщини балістикою і БпЛА | N16: https://www.pravda.com.ua/news/2025/07/12/7521514/ | O16: https://suspilne.media/kyiv/1069595-rf-atakuvala-kiiv-balistikou-ta-dronami/ | P16: Пряме підтвердження балістики по столиці. | AB16: Поза city-only / архів аудиту | AC16: Виключено — 12.07: у перевіреному зведенні атаки підтверджені БпЛА та крилаті Х-101; прямого балістичного епізоду по Києву не встановлено | AD16: KYI-20250712-130 | AE16: Ні | AH16: Так | AO16: БпЛА | AP16: Профіль не включено до чистої моделі; збережено для аудиту | AQ16: =IF(D16="","",IF(IFERROR(DATEVALUE(D16),0)<DATE(2024,9,1),"ERA-1 • масовані/ракетно-комбіновані",IF(IFERROR(DATEVALUE(D16),0)<DATE(2025,7,1),"ERA-2 • drone-saturation transition",IF(IFERROR(DATEVALUE(D16),0)<DATE(2026,4,1),"ERA-3 • змішаний / зростання балістики","ERA-4 • поточний балістично-насичений")))) -> ERA-3 • змішаний / зростання балістики | AR16: =IF(D16="","",IF(IFERROR(DATEVALUE(D16),0)>='Розрахунок'!$B$2-365,"MODEL-365","HISTORICAL_ONLY")) -> HISTORICAL_ONLY
A17: 16 | B17: Одеса | C17: Балістика / швидкісні ракети | D17: 2025-07-14 | E17: Понеділок | F17: 2 | G17: Середина | H17: 1 | I17: Одеса + Одеська область | J17: Іскандер-М | K17: Ні/окремий ракетний епізод | L17: A — пряма/локальна прив’язка | M17: Удень 14 липня Одещину атаковано балістичною ракетою Іскандер-М. | N17: https://suspilne.media/odesa/1073433-obstril-odesini-14-lipna-ekologi-pidrahuvali-zbitki/ | P17: ПК Південь прямо підтвердило Іскандер-М. | S17: 1 | T17: Підтверджено | V17: Іскандер-М підтверджено | AB17: Одеса + Одеська область | AC17: Включено — 14.07: пряме підтвердження Іскандер-М по Одещині | AD17: ODS-20250714-129 | AE17: Так | AO17: балістика | AP17: Профіль підтверджено за джерелами аудованого реєстру | AQ17: =IF(D17="","",IF(IFERROR(DATEVALUE(D17),0)<DATE(2024,9,1),"ERA-1 • масовані/ракетно-комбіновані",IF(IFERROR(DATEVALUE(D17),0)<DATE(2025,7,1),"ERA-2 • drone-saturation transition",IF(IFERROR(DATEVALUE(D17),0)<DATE(2026,4,1),"ERA-3 • змішаний / зростання балістики","ERA-4 • поточний балістично-насичений")))) -> ERA-3 • змішаний / зростання балістики | AR17: =IF(D17="","",IF(IFERROR(DATEVALUE(D17),0)>='Розрахунок'!$B$2-365,"MODEL-365","HISTORICAL_ONLY")) -> HISTORICAL_ONLY
A18: 17 | B18: Кривий Ріг | C18: Балістика / швидкісні ракети | D18: 2025-07-16 | E18: Середа | F18: 3 | G18: Середина | H18: 1 | I18: Кривий Ріг | J18: Балістична ракета — тип не уточнений | K18: Так | L18: A — пряма локальна прив’язка | M18: 16 липня Кривий Ріг атаковано балістичною ракетою та 28 ударними БпЛА; пошкоджено промислову й енергетичну інфраструктуру. | N18: https://www.pravda.com.ua/news/2025/07/16/7521929/ | O18: https://1kr.ua/ua/news-108347.html | P18: Балістична складова й локальна прив’язка підтверджені; тип ракети не уточнюємо. | S18: 1 | T18: Одна балістична ракета за локальними повідомленнями | V18: Балістика підтверджена | W18: Кривий Ріг | Z18: https://www.pravda.com.ua/news/2025/07/16/7521929/ | AB18: Кривий Ріг | AC18: Включено — пряме підтвердження балістичного удару по Кривому Рогу | AD18: KRR-20250716-157 | AE18: Так | AH18: Так | AM18: 28 | AN18: 1 | AO18: балістика + БпЛА | AP18: Профіль підтверджено | AQ18: =IF(D18="","",IF(IFERROR(DATEVALUE(D18),0)<DATE(2024,9,1),"ERA-1 • масовані/ракетно-комбіновані",IF(IFERROR(DATEVALUE(D18),0)<DATE(2025,7,1),"ERA-2 • drone-saturation transition",IF(IFERROR(DATEVALUE(D18),0)<DATE(2026,4,1),"ERA-3 • змішаний / зростання балістики","ERA-4 • поточний балістично-насичений")))) -> ERA-3 • змішаний / зростання балістики | AR18: =IF(D18="","",IF(IFERROR(DATEVALUE(D18),0)>='Розрахунок'!$B$2-365,"MODEL-365","HISTORICAL_ONLY")) -> HISTORICAL_ONLY
A19: 18 | B19: Київ | C19: Балістика / швидкісні ракети | D19: 2025-07-21 | E19: Понеділок | F19: 4 | G19: Кінець | H19: 1 | I19: Київ + область | J19: Х-47М2 Кинджал + Калібр + Іскандер-К + Х-101 | K19: Так | L19: B — прямий комбінований удар по Києву; аеробалістичний компонент підтверджено в тому самому пакеті | M19: 21 липня Київ зазнав комбінованого удару; Повітряні сили повідомляли про ракету на Київ, а пакет атаки містив 5 аеробалістичних Х-47М2 «Кинджал», Калібри, Іскандер-К та Х-101. | N19: https://www.pravda.com.ua/news/2025/07/21/7522668/ | O19: https://www.pravda.com.ua/news/2025/07/21/7522688/ | P19: Включено за canonical combined-package rule: точний subtype київської ракети не переносимо, але city-directed combined attack + Kinzhal у тому самому пакеті підтверджені. | AB19: Київ + ближня агломерація | AC19: Включено з B-рівнем — Київ під комбінованим ракетним ударом; пакет містив підтверджений аеробалістичний компонент | AD19: KYI-20250721-128 | AE19: Так | AF19: Так | AH19: Так | AK19: Так | AO19: Кинджал + крилаті ракети + БпЛА | AP19: Delta-check 29.09.2026: переведено з extended-only до BADK ballistic layer за combined-package rule. | AQ19: =IF(D19="","",IF(IFERROR(DATEVALUE(D19),0)<DATE(2024,9,1),"ERA-1 • масовані/ракетно-комбіновані",IF(IFERROR(DATEVALUE(D19),0)<DATE(2025,7,1),"ERA-2 • drone-saturation transition",IF(IFERROR(DATEVALUE(D19),0)<DATE(2026,4,1),"ERA-3 • змішаний / зростання балістики","ERA-4 • поточний балістично-насичений")))) -> ERA-3 • змішаний / зростання балістики | AR19: =IF(D19="","",IF(IFERROR(DATEVALUE(D19),0)>='Розрахунок'!$B$2-365,"MODEL-365","HISTORICAL_ONLY")) -> HISTORICAL_ONLY
A20: 19 | B20: Харків | C20: Балістика / швидкісні ракети | D20: 2025-07-26 | E20: Субота | F20: 4 | G20: Кінець | H20: 1 | I20: Харків | J20: Балістичні ракети — subtype не уточнений | K20: Так | L20: A — пряма локальна прив’язка | M20: У ніч на 26 липня Харків зазнав комбінованої атаки КАБами, балістичними ракетами та ударними БпЛА; міська влада підсумувала два балістичні удари. | N20: https://suspilne.media/kharkiv/1075995-harkiv-i-peredmista-atakuvali-balistikou-ce-druga-seria-vibuhiv-za-nic-26-lipna/ | O20: https://www.pravda.com.ua/news/2025/07/26/7523489/ | P20: До clean-моделі зараховується city attack-day; два ракетні удари поза містом не додаються до локальної кількості. | R20: ~01:30–03:00 | S20: 2 | T20: Підтверджено міською владою: 2 | V20: Балістика підтверджена | W20: Харків | Z20: https://suspilne.media/kharkiv/1075995-harkiv-i-peredmista-atakuvali-balistikou-ce-druga-seria-vibuhiv-za-nic-26-lipna/ | AA20: Комбінований удар; наслідки не приписувати виключно балістиці. | AB20: Харків | AC20: Включено — прямі балістичні удари по Харкову | AD20: KHR-20250726-181 | AE20: Так | AH20: Так | AM20: 15 | AN20: 2 | AO20: КАБ + балістика + БпЛА | AP20: Профіль підтверджено за двома джерелами | AQ20: =IF(D20="","",IF(IFERROR(DATEVALUE(D20),0)<DATE(2024,9,1),"ERA-1 • масовані/ракетно-комбіновані",IF(IFERROR(DATEVALUE(D20),0)<DATE(2025,7,1),"ERA-2 • drone-saturation transition",IF(IFERROR(DATEVALUE(D20),0)<DATE(2026,4,1),"ERA-3 • змішаний / зростання балістики","ERA-4 • поточний балістично-насичений")))) -> ERA-3 • змішаний / зростання балістики | AR20: =IF(D20="","",IF(IFERROR(DATEVALUE(D20),0)>='Розрахунок'!$B$2-365,"MODEL-365","HISTORICAL_ONLY")) -> HISTORICAL_ONLY
A21: 20 | B21: Київ | C21: Крилаті ракети / Іскандер-К | D21: 2025-07-31 | E21: Четвер | F21: 5 | G21: Кінець | H21: 1 | I21: Київ + область | J21: Іскандер-К | K21: Так | L21: A — пряма/локальна прив’язка | M21: Масована атака Києва та Київщини балістикою та БпЛА | N21: https://www.pravda.com.ua/news/2025/07/31/7524472/ | O21: https://suspilne.media/kyiv/1087825-ataka-na-kiiv-ta-oblast-e-zagibli-ta-poraneni/ | P21: Пряме підтвердження балістичної складової. | AB21: Київ | AC21: Включено до розширеного ракетного % — 31.07: по Києву підтверджено 8 крилатих Іскандер-К; не рахувати в чистому балістичному % | AD21: KYI-20250731-127 | AE21: Ні | AF21: Так | AH21: Так | AK21: Так | AO21: Іскандер-К + БпЛА | AP21: Підтверджено — Іскандер-К є крилатою ракетою; лише розширений ракетний шар | AQ21: =IF(D21="","",IF(IFERROR(DATEVALUE(D21),0)<DATE(2024,9,1),"ERA-1 • масовані/ракетно-комбіновані",IF(IFERROR(DATEVALUE(D21),0)<DATE(2025,7,1),"ERA-2 • drone-saturation transition",IF(IFERROR(DATEVALUE(D21),0)<DATE(2026,4,1),"ERA-3 • змішаний / зростання балістики","ERA-4 • поточний балістично-насичений")))) -> ERA-3 • змішаний / зростання балістики | AR21: =IF(D21="","",IF(IFERROR(DATEVALUE(D21),0)>='Розрахунок'!$B$2-365,"MODEL-365","HISTORICAL_ONLY")) -> HISTORICAL_ONLY
A22: 21 | B22: Одеса | C22: Балістика / швидкісні ракети | D22: 2025-08-05 | E22: Вівторок | F22: 1 | G22: Початок | H22: 1 | I22: Одеса + Одеська область | J22: Іскандер-М | K22: Так | L22: A — пряма/локальна прив’язка | M22: Уночі 5 серпня Одещину атаковано балістичною ракетою Іскандер-М із ТОТ Криму. | N22: https://suspilne.media/odesa/1083097-1259-den-vijni-hronika-podij-v-odesi-j-odeskij-oblasti/ | P22: ПК Південь. | S22: 1 | T22: Підтверджено | V22: Іскандер-М підтверджено | AB22: Одеса + Одеська область | AC22: Включено — 05.08: ПК Південь підтверджує Іскандер-М по Одещині | AD22: ODS-20250805-126 | AE22: Так | AO22: балістика | AP22: Профіль підтверджено за джерелами аудованого реєстру | AQ22: =IF(D22="","",IF(IFERROR(DATEVALUE(D22),0)<DATE(2024,9,1),"ERA-1 • масовані/ракетно-комбіновані",IF(IFERROR(DATEVALUE(D22),0)<DATE(2025,7,1),"ERA-2 • drone-saturation transition",IF(IFERROR(DATEVALUE(D22),0)<DATE(2026,4,1),"ERA-3 • змішаний / зростання балістики","ERA-4 • поточний балістично-насичений")))) -> ERA-3 • змішаний / зростання балістики | AR22: =IF(D22="","",IF(IFERROR(DATEVALUE(D22),0)>='Розрахунок'!$B$2-365,"MODEL-365","HISTORICAL_ONLY")) -> HISTORICAL_ONLY
A23: 22 | B23: Київ | C23: Балістика / швидкісні ракети | D23: 2025-08-07 | E23: Четвер | F23: 1 | G23: Початок | H23: 1 | I23: Київ + область | J23: Core ballistic | K23: Так | L23: A — пряма/локальна прив’язка | M23: Масована нічна атака Києва та області балістикою і БпЛА | N23: https://www.pravda.com.ua/news/2025/08/07/7525534/ | O23: https://suspilne.media/kyiv/1094935-rf-atakuvala-kiiv-balistikou-ta-dronami/ | P23: Пряме підтвердження балістики по столиці. | AB23: Поза city-only / архів аудиту | AC23: Виключено — 07.08: Повітряні сили зафіксували нічну атаку лише 112 БпЛА; балістичного удару по Києву не було | AD23: KYI-20250807-125 | AE23: Ні | AH23: Так | AO23: БпЛА | AP23: Профіль не включено до чистої моделі; збережено для аудиту | AQ23: =IF(D23="","",IF(IFERROR(DATEVALUE(D23),0)<DATE(2024,9,1),"ERA-1 • масовані/ракетно-комбіновані",IF(IFERROR(DATEVALUE(D23),0)<DATE(2025,7,1),"ERA-2 • drone-saturation transition",IF(IFERROR(DATEVALUE(D23),0)<DATE(2026,4,1),"ERA-3 • змішаний / зростання балістики","ERA-4 • поточний балістично-насичений")))) -> ERA-3 • змішаний / зростання балістики | AR23: =IF(D23="","",IF(IFERROR(DATEVALUE(D23),0)>='Розрахунок'!$B$2-365,"MODEL-365","HISTORICAL_ONLY")) -> HISTORICAL_ONLY
A24: 23 | B24: Київ | C24: Балістика / швидкісні ракети | D24: 2025-08-08 | E24: П’ятниця | F24: 2 | G24: Початок | H24: 1 | I24: Київ + область | J24: Core ballistic | K24: Ні | L24: A — пряма/локальна прив’язка | M24: Ракетна атака Києва з балістичною складовою | N24: https://www.pravda.com.ua/news/2025/08/08/7525714/ | O24: https://suspilne.media/kyiv/1096015-rf-atakuvala-kiiv-balistikou/ | P24: Пряме підтвердження балістики по столиці. | AB24: Поза city-only / архів аудиту | AC24: Виключено — 08.08: Повітряні сили зафіксували БпЛА та швидкісні реактивні БпЛА; балістичного удару по Києву не було | AD24: KYI-20250808-124 | AE24: Ні | AP24: Профіль не включено до чистої моделі; збережено для аудиту | AQ24: =IF(D24="","",IF(IFERROR(DATEVALUE(D24),0)<DATE(2024,9,1),"ERA-1 • масовані/ракетно-комбіновані",IF(IFERROR(DATEVALUE(D24),0)<DATE(2025,7,1),"ERA-2 • drone-saturation transition",IF(IFERROR(DATEVALUE(D24),0)<DATE(2026,4,1),"ERA-3 • змішаний / зростання балістики","ERA-4 • поточний балістично-насичений")))) -> ERA-3 • змішаний / зростання балістики | AR24: =IF(D24="","",IF(IFERROR(DATEVALUE(D24),0)>='Розрахунок'!$B$2-365,"MODEL-365","HISTORICAL_ONLY")) -> HISTORICAL_ONLY
A25: 24 | B25: Харків | C25: Балістика / швидкісні ракети | D25: 2025-08-17 | E25: Неділя | F25: 3 | G25: Середина | H25: 1 | I25: Харків | J25: Іскандер-М — за сукупністю локальних даних | K25: Так | L25: A — пряма локальна прив’язка | M25: Близько 22:50 17 серпня балістична ракета влучила в Індустріальному районі Харкова. | N25: https://suspilne.media/kharkiv/1092810-rosijska-balisticna-raketa-vlucila-v-industrialnomu-rajoni-harkova-aki-naslidki/ | O25: https://www.pravda.com.ua/news/2025/08/17/7526619/ | P25: Пряме локальне підтвердження балістичного класу; ХОВА у добовому зведенні вказала Іскандер-М. | R25: ~22:50 | S25: 1 | T25: Підтверджено: 1 | V25: Балістика підтверджена | W25: Харків | Z25: https://suspilne.media/kharkiv/1092810-rosijska-balisticna-raketa-vlucila-v-industrialnomu-rajoni-harkova-aki-naslidki/ | AA25: Влучання поблизу житлової забудови; не приписуємо конкретні пошкодження без окремої атрибуції. | AB25: Харків | AC25: Включено — прямий балістичний удар по Харкову | AD25: KHR-20250817-182 | AE25: Так | AH25: Так | AN25: 1 | AO25: балістика + БпЛА | AP25: Профіль підтверджено за двома джерелами | AQ25: =IF(D25="","",IF(IFERROR(DATEVALUE(D25),0)<DATE(2024,9,1),"ERA-1 • масовані/ракетно-комбіновані",IF(IFERROR(DATEVALUE(D25),0)<DATE(2025,7,1),"ERA-2 • drone-saturation transition",IF(IFERROR(DATEVALUE(D25),0)<DATE(2026,4,1),"ERA-3 • змішаний / зростання балістики","ERA-4 • поточний балістично-насичений")))) -> ERA-3 • змішаний / зростання балістики | AR25: =IF(D25="","",IF(IFERROR(DATEVALUE(D25),0)>='Розрахунок'!$B$2-365,"MODEL-365","HISTORICAL_ONLY")) -> HISTORICAL_ONLY
A26: 25 | B26: Одеса | C26: Балістика / швидкісні ракети | D26: 2025-08-19 | E26: Вівторок | F26: 3 | G26: Середина | H26: 2 | I26: Одеса + Одеська область | J26: Іскандер-М | K26: Ні/окремий ракетний епізод | L26: A — офіційне локальне підтвердження | M26: Пізно ввечері 19 серпня Одещину атаковано двома балістичними ракетами Іскандер-М; одну збито. | N26: https://ivms.mil.gov.ua/wp-content/uploads/2025/08/dovidka-15.08-21.08.2025-1.pdf | P26: Другий окремий балістичний епізод цієї доби; не зливати з нічним ударом. | R26: пізно ввечері | S26: 2 | T26: Підтверджено | V26: Іскандер-М підтверджено | AB26: Одеса + Одеська область | AC26: Включено — 19.08 вечір: окремий удар 2 Іскандер-М по Одещині | AD26: ODS-20250819-122 | AE26: Так | AO26: балістика | AP26: Профіль підтверджено за джерелами аудованого реєстру | AQ26: =IF(D26="","",IF(IFERROR(DATEVALUE(D26),0)<DATE(2024,9,1),"ERA-1 • масовані/ракетно-комбіновані",IF(IFERROR(DATEVALUE(D26),0)<DATE(2025,7,1),"ERA-2 • drone-saturation transition",IF(IFERROR(DATEVALUE(D26),0)<DATE(2026,4,1),"ERA-3 • змішаний / зростання балістики","ERA-4 • поточний балістично-насичений")))) -> ERA-3 • змішаний / зростання балістики | AR26: =IF(D26="","",IF(IFERROR(DATEVALUE(D26),0)>='Розрахунок'!$B$2-365,"MODEL-365","HISTORICAL_ONLY")) -> HISTORICAL_ONLY
A27: 26 | B27: Одеса | C27: Балістика / швидкісні ракети | D27: 2025-08-19 | E27: Вівторок | F27: 3 | G27: Середина | H27: 2 | I27: Одеса + Одеська область | J27: Іскандер-М (ймовірно) | K27: Ні/окремий ракетний епізод | L27: A — офіційне локальне підтвердження | M27: Уночі 19 серпня Одещину атаковано однією балістичною ракетою, ймовірно Іскандер-М. | N27: https://suspilne.media/odesa/1093696-1273-den-vijni-hronika-podij-v-odesi-j-odeskij-oblasti/ | O27: https://ivms.mil.gov.ua/wp-content/uploads/2025/08/dovidka-15.08-21.08.2025-1.pdf | P27: Перший із двох окремих балістичних епізодів 19.08. | R27: ніч | S27: 1 | T27: Підтверджено | V27: Балістика підтверджена; Іскандер-М імовірно | AB27: Одеса + Одеська область | AC27: Включено — 19.08 ніч: окремий підтверджений балістичний епізод по Одещині | AD27: ODS-20250819-123 | AE27: Так | AO27: балістика | AP27: Профіль підтверджено за джерелами аудованого реєстру | AQ27: =IF(D27="","",IF(IFERROR(DATEVALUE(D27),0)<DATE(2024,9,1),"ERA-1 • масовані/ракетно-комбіновані",IF(IFERROR(DATEVALUE(D27),0)<DATE(2025,7,1),"ERA-2 • drone-saturation transition",IF(IFERROR(DATEVALUE(D27),0)<DATE(2026,4,1),"ERA-3 • змішаний / зростання балістики","ERA-4 • поточний балістично-насичений")))) -> ERA-3 • змішаний / зростання балістики | AR27: =IF(D27="","",IF(IFERROR(DATEVALUE(D27),0)>='Розрахунок'!$B$2-365,"MODEL-365","HISTORICAL_ONLY")) -> HISTORICAL_ONLY
A28: 27 | B28: Одеса | C28: Балістика / швидкісні ракети | D28: 2025-08-20 | E28: Середа | F28: 3 | G28: Середина | H28: 1 | I28: Одеса + Одеська область | J28: Іскандер-М | K28: Ні/окремий ракетний епізод | L28: A — пряма/локальна прив’язка | M28: Увечері 20 серпня Одещину атаковано двома балістичними ракетами Іскандер-М із ТОТ Криму. | N28: https://suspilne.media/odesa/1095450-1275-den-vijni-hronika-podij-v-odesi-j-odeskij-oblasti/ | O28: https://ivms.mil.gov.ua/wp-content/uploads/2025/08/dovidka-15.08-21.08.2025-1.pdf | P28: Окремий епізод наступної доби. | R28: вечір | S28: 2 | T28: Підтверджено | V28: Іскандер-М підтверджено | AB28: Одеса + Одеська область | AC28: Включено — 20.08: пряме підтвердження 2 Іскандер-М по Одещині | AD28: ODS-20250820-121 | AE28: Так | AO28: балістика | AP28: Профіль підтверджено за джерелами аудованого реєстру | AQ28: =IF(D28="","",IF(IFERROR(DATEVALUE(D28),0)<DATE(2024,9,1),"ERA-1 • масовані/ракетно-комбіновані",IF(IFERROR(DATEVALUE(D28),0)<DATE(2025,7,1),"ERA-2 • drone-saturation transition",IF(IFERROR(DATEVALUE(D28),0)<DATE(2026,4,1),"ERA-3 • змішаний / зростання балістики","ERA-4 • поточний балістично-насичений")))) -> ERA-3 • змішаний / зростання балістики | AR28: =IF(D28="","",IF(IFERROR(DATEVALUE(D28),0)>='Розрахунок'!$B$2-365,"MODEL-365","HISTORICAL_ONLY")) -> HISTORICAL_ONLY
A29: 28 | B29: Київ | C29: Балістика / швидкісні ракети | D29: 2025-08-28 | E29: Четвер | F29: 4 | G29: Кінець | H29: 1 | I29: Київ + область | J29: Core ballistic | K29: Так | L29: A — пряма/локальна прив’язка | M29: Масована атака Києва та області балістикою і БпЛА | N29: https://www.pravda.com.ua/news/2025/08/28/7528865/ | O29: https://suspilne.media/kyiv/1116335-ataka-na-kiiv-ta-oblast-e-zagibli-ta-poraneni/ | P29: Пряме підтвердження балістичної складової. | AB29: Київ | AC29: Включено — 28.08: масований удар по Києву із застосуванням Іскандер-М/KN-23 та інших засобів; балістична складова і наслідки в столиці підтверджені | AD29: KYI-20250828-120 | AE29: Так | AH29: Так | AO29: балістика + БпЛА | AP29: Профіль підтверджено за джерелами аудованого реєстру | AQ29: =IF(D29="","",IF(IFERROR(DATEVALUE(D29),0)<DATE(2024,9,1),"ERA-1 • масовані/ракетно-комбіновані",IF(IFERROR(DATEVALUE(D29),0)<DATE(2025,7,1),"ERA-2 • drone-saturation transition",IF(IFERROR(DATEVALUE(D29),0)<DATE(2026,4,1),"ERA-3 • змішаний / зростання балістики","ERA-4 • поточний балістично-насичений")))) -> ERA-3 • змішаний / зростання балістики | AR29: =IF(D29="","",IF(IFERROR(DATEVALUE(D29),0)>='Розрахунок'!$B$2-365,"MODEL-365","HISTORICAL_ONLY")) -> HISTORICAL_ONLY
A30: 29 | B30: Київ | C30: Крилаті ракети / Іскандер-К | D30: 2025-09-07 | E30: Неділя | F30: 1 | G30: Початок | H30: 1 | I30: Київ + область | J30: Іскандер-К | K30: Так | L30: A — пряма/локальна прив’язка | M30: Масована комбінована атака Києва та області з балістичною складовою | N30: https://www.pravda.com.ua/news/2025/09/07/7530561/ | O30: https://suspilne.media/kyiv/1126595-ataka-na-kiiv-ta-oblast-e-zagibli-ta-poraneni/ | P30: Пряме підтвердження балістики по столиці. | AB30: Київ | AC30: Включено до розширеного ракетного % — 07.09: по Києву підтверджений крилатий Іскандер-К; балістичні Іскандер-М/KN-23 цієї ночі по столиці не підтверджені, тому в чистий балістичний % не входить | AD30: KYI-20250907-119 | AE30: Ні | AF30: Так | AH30: Так | AK30: Так | AO30: Іскандер-К + БпЛА | AP30: Підтверджено — Іскандер-К є крилатою ракетою; лише розширений ракетний шар | AQ30: =IF(D30="","",IF(IFERROR(DATEVALUE(D30),0)<DATE(2024,9,1),"ERA-1 • масовані/ракетно-комбіновані",IF(IFERROR(DATEVALUE(D30),0)<DATE(2025,7,1),"ERA-2 • drone-saturation transition",IF(IFERROR(DATEVALUE(D30),0)<DATE(2026,4,1),"ERA-3 • змішаний / зростання балістики","ERA-4 • поточний балістично-насичений")))) -> ERA-3 • змішаний / зростання балістики | AR30: =IF(D30="","",IF(IFERROR(DATEVALUE(D30),0)>='Розрахунок'!$B$2-365,"MODEL-365","HISTORICAL_ONLY")) -> HISTORICAL_ONLY
A31: 30 | B31: Кривий Ріг | C31: Балістика / швидкісні ракети | D31: 2025-09-07 | E31: Неділя | F31: 1 | G31: Початок | H31: 1 | I31: Кривий Ріг | J31: Балістичні ракети — тип не уточнений | K31: Так | L31: A — пряма локальна прив’язка | M31: 7 вересня Кривий Ріг зазнав масованої комбінованої атаки: балістичні та крилаті ракети, а також ударні БпЛА. | N31: https://www.pravda.com.ua/news/2025/09/07/7529685/ | O31: https://1kr.ua/ua/news-105296.html | P31: Локальні джерела розходяться в точній кількості балістичних ракет, тому число не фіксуємо як офіційне. | T31: Точна локальна кількість не встановлена | V31: Балістика підтверджена | W31: Кривий Ріг | AB31: Кривий Ріг | AC31: Включено — пряме підтвердження балістичної складової по Кривому Рогу | AD31: KRR-20250907-158 | AE31: Так | AF31: Так | AH31: Так | AO31: балістика + крилаті ракети + БпЛА | AP31: Профіль підтверджено | AQ31: =IF(D31="","",IF(IFERROR(DATEVALUE(D31),0)<DATE(2024,9,1),"ERA-1 • масовані/ракетно-комбіновані",IF(IFERROR(DATEVALUE(D31),0)<DATE(2025,7,1),"ERA-2 • drone-saturation transition",IF(IFERROR(DATEVALUE(D31),0)<DATE(2026,4,1),"ERA-3 • змішаний / зростання балістики","ERA-4 • поточний балістично-насичений")))) -> ERA-3 • змішаний / зростання балістики | AR31: =IF(D31="","",IF(IFERROR(DATEVALUE(D31),0)>='Розрахунок'!$B$2-365,"MODEL-365","HISTORICAL_ONLY")) -> HISTORICAL_ONLY
A32: 31 | B32: Дніпро | C32: Балістика / швидкісні ракети | D32: 2025-09-13 | E32: Субота | F32: 2 | G32: Середина | H32: 1 | I32: Дніпро | J32: Іскандер-М/KN-23 | K32: Ні | L32: A — пряма локальна прив’язка | M32: Увечері 13 вересня РФ завдала ракетного удару по Дніпру; Повітряні сили повідомили про Іскандер-М/KN-23. | N32: https://suspilne.media/dnipro/1114358-raketna-ataka-na-dnipro-obstrili-prifrontovih-gromad-ppo-zbila-cotiri-droni-ak-minula-nic-proti-14-veresna/ | P32: Пряме підтвердження типу і міста. | S32: 1 | T32: Підтверджено ПС | V32: Підтверджено | W32: Дніпро | Z32: https://suspilne.media/dnipro/1114358-raketna-ataka-na-dnipro-obstrili-prifrontovih-gromad-ppo-zbila-cotiri-droni-ak-minula-nic-proti-14-veresna/ | AB32: Дніпро | AC32: Включено — прямий підтверджений балістичний епізод по Дніпру | AD32: DNI-20250913-001 | AE32: Так | AF32: Ні | AH32: Ні | AN32: 1 | AO32: балістика | AP32: Підтверджено джерелом | AQ32: =IF(D32="","",IF(IFERROR(DATEVALUE(D32),0)<DATE(2024,9,1),"ERA-1 • масовані/ракетно-комбіновані",IF(IFERROR(DATEVALUE(D32),0)<DATE(2025,7,1),"ERA-2 • drone-saturation transition",IF(IFERROR(DATEVALUE(D32),0)<DATE(2026,4,1),"ERA-3 • змішаний / зростання балістики","ERA-4 • поточний балістично-насичений")))) -> ERA-3 • змішаний / зростання балістики | AR32: =IF(D32="","",IF(IFERROR(DATEVALUE(D32),0)>='Розрахунок'!$B$2-365,"MODEL-365","HISTORICAL_ONLY")) -> HISTORICAL_ONLY
A33: 32 | B33: Київ | C33: Балістика / швидкісні ракети | D33: 2025-09-20 | E33: Субота | F33: 3 | G33: Середина | H33: 1 | I33: Київ + область | J33: Іскандер-М/KN-23 + Х-101 — локальний subtype в агломерації не рознесено | K33: Так | L33: B — комбінована ракетна атака ближньої агломерації + підтверджений балістичний пакет | M33: 20 вересня Київщину атакували ракетами та БпЛА; наслідки зафіксовано у Бучанському та Бориспільському районах, що входять у scope моделі Києва. Загальний пакет містив 8 Іскандер-М/KN-23 та 32 Х-101. | N33: https://www.pravda.com.ua/news/2025/09/20/7531690/ | O33: https://www.pravda.com.ua/news/2025/09/20/7531685/ | P33: Не приписуємо конкретний subtype конкретній локації. Включення базується на city/agglomeration scope + локальній комбінованій ракетній атаці + підтвердженому балістичному компоненті пакета. | AB33: Київ + ближня агломерація | AC33: Включено з B-рівнем — Бучанський/Бориспільський напрямки у scope; локальна ракетна атака + балістичний пакет | AD33: KYI-20250920-118 | AE33: Так | AH33: Так | AO33: балістика + Х-101 + БпЛА | AP33: Delta-check 29.09.2026: старе city-only виключення скасовано; agglomeration scope застосовано. | AQ33: =IF(D33="","",IF(IFERROR(DATEVALUE(D33),0)<DATE(2024,9,1),"ERA-1 • масовані/ракетно-комбіновані",IF(IFERROR(DATEVALUE(D33),0)<DATE(2025,7,1),"ERA-2 • drone-saturation transition",IF(IFERROR(DATEVALUE(D33),0)<DATE(2026,4,1),"ERA-3 • змішаний / зростання балістики","ERA-4 • поточний балістично-насичений")))) -> ERA-3 • змішаний / зростання балістики | AR33: =IF(D33="","",IF(IFERROR(DATEVALUE(D33),0)>='Розрахунок'!$B$2-365,"MODEL-365","HISTORICAL_ONLY")) -> HISTORICAL_ONLY
A34: 33 | B34: Одеса | C34: Балістика / швидкісні ракети | D34: 2025-09-23 | E34: Вівторок | F34: 4 | G34: Кінець | H34: 1 | I34: Одеса + Одеська область | J34: Іскандер-М | K34: Так | L34: A — пряма/локальна прив’язка | M34: Одещину атаковано трьома балістичними ракетами Іскандер-М. | N34: https://www.ukr.net/news/details/russianaggression/113619232.html | O34: https://www.pravda.com.ua/news/2025/09/23/7532067/ | P34: ПК Південь: 3 Іскандер-М по Одещині. | S34: 3 | T34: Підтверджено | V34: Підтверджено | AB34: Одеса + Одеська область | AC34: Включено — 23.09: ПК Південь підтвердило 3 Іскандер-М по Одещині | AD34: ODS-20250923-117 | AE34: Так | AO34: балістика | AP34: Профіль підтверджено за джерелами аудованого реєстру | AQ34: =IF(D34="","",IF(IFERROR(DATEVALUE(D34),0)<DATE(2024,9,1),"ERA-1 • масовані/ракетно-комбіновані",IF(IFERROR(DATEVALUE(D34),0)<DATE(2025,7,1),"ERA-2 • drone-saturation transition",IF(IFERROR(DATEVALUE(D34),0)<DATE(2026,4,1),"ERA-3 • змішаний / зростання балістики","ERA-4 • поточний балістично-насичений")))) -> ERA-3 • змішаний / зростання балістики | AR34: =IF(D34="","",IF(IFERROR(DATEVALUE(D34),0)>='Розрахунок'!$B$2-365,"MODEL-365","HISTORICAL_ONLY")) -> HISTORICAL_ONLY
A35: 34 | B35: Київ | C35: Балістика / швидкісні ракети | D35: 2025-09-28 | E35: Неділя | F35: 4 | G35: Кінець | H35: 1 | I35: Київ + область | J35: Core ballistic | K35: Так | L35: A — пряма/локальна прив’язка | M35: Масована атака Києва та області з балістичною складовою | N35: https://www.pravda.com.ua/news/2025/09/28/7534015/ | O35: https://suspilne.media/kyiv/1147805-ataka-na-kiiv-ta-oblast-e-zagibli-ta-poraneni/ | P35: Пряме підтвердження балістики по столиці. | AB35: Поза city-only / архів аудиту | AC35: Виключено — 28.09: Київ і область зазнали масованої комбінованої атаки, але Повітряні сили для Київщини підтверджують БпЛА та крилаті ракети; прямого підтвердження балістичного епізоду по Києву для чистої city-only бази не встановлено | AD35: KYI-20250928-116 | AE35: Ні | AP35: Профіль не включено до чистої моделі; збережено для аудиту | AQ35: =IF(D35="","",IF(IFERROR(DATEVALUE(D35),0)<DATE(2024,9,1),"ERA-1 • масовані/ракетно-комбіновані",IF(IFERROR(DATEVALUE(D35),0)<DATE(2025,7,1),"ERA-2 • drone-saturation transition",IF(IFERROR(DATEVALUE(D35),0)<DATE(2026,4,1),"ERA-3 • змішаний / зростання балістики","ERA-4 • поточний балістично-насичений")))) -> ERA-3 • змішаний / зростання балістики | AR35: =IF(D35="","",IF(IFERROR(DATEVALUE(D35),0)>='Розрахунок'!$B$2-365,"MODEL-365","HISTORICAL_ONLY")) -> HISTORICAL_ONLY
A36: 35 | B36: Павлоград | C36: Балістика / швидкісні ракети | D36: 2025-10-03 | E36: П’ятниця | F36: 1 | G36: Початок | H36: 1 | I36: Павлоград | J36: Балістична ракета; Іскандер — імовірно | K36: Ні | L36: B — ПС: ракета на Павлоград + балістична загроза; subtype з моніторингу | M36: Увечері 3 жовтня в Павлограді пролунали два вибухи. Повітряні сили повідомляли про ракету на Павлоград і загрозу балістичного озброєння; Іскандер — імовірна атрибуція. | N36: https://24tv.ua/rosiyani-atakuyut-pavlograd-misti-prolunali-vibuhi_n2927019/ | O36: https://pv-district.dp.ua/2025/10/04/6951/ | P36: Включено як B-рівень: напрям ракети й балістична загроза підтверджені ПС, але завершена локальна форензика subtype відсутня. | R36: ~22:01–22:09 | T36: Кількість/тип локально не встановлені | V36: Балістична складова ймовірна, B-рівень | W36: Павлоград | AB36: Павлоград | AC36: Включено з B-рівнем — ракетний удар на тлі прямого попередження ПС про балістику | AD36: PVL-20251003-199 | AE36: Так | AO36: балістика B-рівень | AP36: Профіль включено з B-рівнем | AQ36: =IF(D36="","",IF(IFERROR(DATEVALUE(D36),0)<DATE(2024,9,1),"ERA-1 • масовані/ракетно-комбіновані",IF(IFERROR(DATEVALUE(D36),0)<DATE(2025,7,1),"ERA-2 • drone-saturation transition",IF(IFERROR(DATEVALUE(D36),0)<DATE(2026,4,1),"ERA-3 • змішаний / зростання балістики","ERA-4 • поточний балістично-насичений")))) -> ERA-3 • змішаний / зростання балістики | AR36: =IF(D36="","",IF(IFERROR(DATEVALUE(D36),0)>='Розрахунок'!$B$2-365,"MODEL-365","HISTORICAL_ONLY")) -> HISTORICAL_ONLY
A37: 36 | B37: Київ | C37: Балістика / швидкісні ракети | D37: 2025-10-10 | E37: П’ятниця | F37: 2 | G37: Початок | H37: 1 | I37: Київ + область | J37: Core ballistic | K37: Так | L37: A — пряма/локальна прив’язка | M37: Масована комбінована атака Києва та області з балістичною складовою | N37: https://www.pravda.com.ua/news/2025/10/10/7535951/ | O37: https://suspilne.media/kyiv/1159965-ataka-na-kiiv-ta-oblast-e-zagibli-ta-poraneni/ | P37: Пряме підтвердження балістики по столиці. | AB37: Київ | AC37: Включено — 10.10: Повітряні сили прямо повідомляли про атаку Києва балістикою та ударними БпЛА | AD37: KYI-20251010-115 | AE37: Так | AO37: балістика | AP37: Профіль підтверджено за джерелами аудованого реєстру | AQ37: =IF(D37="","",IF(IFERROR(DATEVALUE(D37),0)<DATE(2024,9,1),"ERA-1 • масовані/ракетно-комбіновані",IF(IFERROR(DATEVALUE(D37),0)<DATE(2025,7,1),"ERA-2 • drone-saturation transition",IF(IFERROR(DATEVALUE(D37),0)<DATE(2026,4,1),"ERA-3 • змішаний / зростання балістики","ERA-4 • поточний балістично-насичений")))) -> ERA-3 • змішаний / зростання балістики | AR37: =IF(D37="","",IF(IFERROR(DATEVALUE(D37),0)>='Розрахунок'!$B$2-365,"MODEL-365","HISTORICAL_ONLY")) -> HISTORICAL_ONLY
A38: 37 | B38: Кривий Ріг | C38: Крилаті ракети / аудит | D38: 2025-10-10 | E38: П’ятниця | F38: 2 | G38: Початок | H38: 1 | I38: Кривий Ріг | J38: Крилата ракета | K38: Ні | L38: A — subtype локально підтверджено | M38: 10 жовтня Кривий Ріг зазнав ракетного удару; локально підтверджено саме влучання крилатої ракети. | N38: https://kr.informator.ua/2025/10/10/vorog-vdaryv-po-kryvomu-rogu-raketoyu-naslidky-ataky/ | O38: https://1kr.ua/ua/news-108347.html | P38: Збережено для аудиту, але не рахувати як балістичний епізод. | T38: Не застосовується | V38: Підтверджена крилата ракета | W38: Кривий Ріг | AB38: Кривий Ріг | AC38: Виключено — 10.10.2025: підтверджена крилата ракета, не балістика | AD38: KRR-20251010-159 | AE38: Ні | AF38: Так | AN38: 1 | AO38: крилата ракета | AP38: Аудит: виключено з чистої балістичної моделі | AQ38: =IF(D38="","",IF(IFERROR(DATEVALUE(D38),0)<DATE(2024,9,1),"ERA-1 • масовані/ракетно-комбіновані",IF(IFERROR(DATEVALUE(D38),0)<DATE(2025,7,1),"ERA-2 • drone-saturation transition",IF(IFERROR(DATEVALUE(D38),0)<DATE(2026,4,1),"ERA-3 • змішаний / зростання балістики","ERA-4 • поточний балістично-насичений")))) -> ERA-3 • змішаний / зростання балістики | AR38: =IF(D38="","",IF(IFERROR(DATEVALUE(D38),0)>='Розрахунок'!$B$2-365,"MODEL-365","HISTORICAL_ONLY")) -> HISTORICAL_ONLY
A39: 38 | B39: Київ | C39: Балістика / швидкісні ракети | D39: 2025-10-16 | E39: Четвер | F39: 3 | G39: Середина | H39: 1 | I39: Київ + область | J39: Core ballistic | K39: Так | L39: A — пряма/локальна прив’язка | M39: Масована атака Києва та області з балістичною складовою | N39: https://www.pravda.com.ua/news/2025/10/16/7536904/ | O39: https://suspilne.media/kyiv/1166005-rf-atakuvala-kiiv-balistikou-ta-dronami/ | P39: Пряме підтвердження балістики по столиці. | AB39: Поза city-only / архів аудиту | AC39: Виключено з city-only — 16.10: масована атака містила балістику, але основний удар припав на Полтавщину та Харківщину; прямої прив’язки балістичного удару до Києва не встановлено | AD39: KYI-20251016-114 | AE39: Ні | AP39: Профіль не включено до чистої моделі; збережено для аудиту | AQ39: =IF(D39="","",IF(IFERROR(DATEVALUE(D39),0)<DATE(2024,9,1),"ERA-1 • масовані/ракетно-комбіновані",IF(IFERROR(DATEVALUE(D39),0)<DATE(2025,7,1),"ERA-2 • drone-saturation transition",IF(IFERROR(DATEVALUE(D39),0)<DATE(2026,4,1),"ERA-3 • змішаний / зростання балістики","ERA-4 • поточний балістично-насичений")))) -> ERA-3 • змішаний / зростання балістики | AR39: =IF(D39="","",IF(IFERROR(DATEVALUE(D39),0)>='Розрахунок'!$B$2-365,"MODEL-365","HISTORICAL_ONLY")) -> MODEL-365
A40: 39 | B40: Одеса | C40: Балістика / швидкісні ракети | D40: 2025-10-20 | E40: Понеділок | F40: 3 | G40: Середина | H40: 1 | I40: Одеса + Одеська область | J40: Іскандер-М/KN-23 | K40: Так | L40: A — пряма/локальна прив’язка | M40: У ніч на 20 жовтня Одещину атаковано трьома балістичними ракетами Іскандер-М/KN-23 та ударними БпЛА. | N40: https://suspilne.media/odesa/1143492-vnoci-rosia-atakuvala-odesinu-troma-balisticnimi-raketami/ | O40: https://www.pravda.com.ua/news/2025/10/20/8003488/ | P40: ПК Південь: 3 балістичні ракети по Одещині. | AB40: Одеса + Одеська область | AC40: Включено — 20.10: пряме підтвердження трьох Іскандер-М/KN-23 по Одещині | AD40: ODS-20251020-113 | AE40: Так | AH40: Так | AO40: балістика + БпЛА | AP40: Профіль підтверджено за джерелами аудованого реєстру | AQ40: =IF(D40="","",IF(IFERROR(DATEVALUE(D40),0)<DATE(2024,9,1),"ERA-1 • масовані/ракетно-комбіновані",IF(IFERROR(DATEVALUE(D40),0)<DATE(2025,7,1),"ERA-2 • drone-saturation transition",IF(IFERROR(DATEVALUE(D40),0)<DATE(2026,4,1),"ERA-3 • змішаний / зростання балістики","ERA-4 • поточний балістично-насичений")))) -> ERA-3 • змішаний / зростання балістики | AR40: =IF(D40="","",IF(IFERROR(DATEVALUE(D40),0)>='Розрахунок'!$B$2-365,"MODEL-365","HISTORICAL_ONLY")) -> MODEL-365
A41: 40 | B41: Київ | C41: Балістика / швидкісні ракети | D41: 2025-10-22 | E41: Середа | F41: 4 | G41: Кінець | H41: 1 | I41: Київ + область | J41: Core ballistic | K41: Так | L41: A — пряма/локальна прив’язка | M41: Масована атака Києва та області балістикою та БпЛА | N41: https://www.pravda.com.ua/news/2025/10/22/7537852/ | O41: https://suspilne.media/kyiv/1172155-ataka-na-kiiv-ta-oblast-e-zagibli-ta-poraneni/ | P41: Пряме підтвердження балістичної складової. | AB41: Київ | AC41: Включено — 22.10: атака Києва із застосуванням балістичного озброєння прямо підтверджена | AD41: KYI-20251022-112 | AE41: Так | AH41: Так | AO41: балістика + БпЛА | AP41: Профіль підтверджено за джерелами аудованого реєстру | AQ41: =IF(D41="","",IF(IFERROR(DATEVALUE(D41),0)<DATE(2024,9,1),"ERA-1 • масовані/ракетно-комбіновані",IF(IFERROR(DATEVALUE(D41),0)<DATE(2025,7,1),"ERA-2 • drone-saturation transition",IF(IFERROR(DATEVALUE(D41),0)<DATE(2026,4,1),"ERA-3 • змішаний / зростання балістики","ERA-4 • поточний балістично-насичений")))) -> ERA-3 • змішаний / зростання балістики | AR41: =IF(D41="","",IF(IFERROR(DATEVALUE(D41),0)>='Розрахунок'!$B$2-365,"MODEL-365","HISTORICAL_ONLY")) -> MODEL-365
A42: 41 | B42: Київ | C42: Балістика / швидкісні ракети | D42: 2025-10-25 | E42: Субота | F42: 4 | G42: Кінець | H42: 1 | I42: Київ + область | J42: Core ballistic | K42: Так | L42: A — пряма/локальна прив’язка | M42: Нічна комбінована атака Києва та Київщини з балістичною складовою | N42: https://www.pravda.com.ua/news/2025/10/25/7538350/ | O42: https://suspilne.media/kyiv/1175265-rf-atakuvala-kiiv-balistikou-ta-dronami/ | P42: Пряме підтвердження балістики по столиці. | AB42: Київ | AC42: Включено — 25.10: пряме підтвердження балістичної атаки Києва; Іскандер-М | AD42: KYI-20251025-111 | AE42: Так | AO42: балістика | AP42: Профіль підтверджено за джерелами аудованого реєстру | AQ42: =IF(D42="","",IF(IFERROR(DATEVALUE(D42),0)<DATE(2024,9,1),"ERA-1 • масовані/ракетно-комбіновані",IF(IFERROR(DATEVALUE(D42),0)<DATE(2025,7,1),"ERA-2 • drone-saturation transition",IF(IFERROR(DATEVALUE(D42),0)<DATE(2026,4,1),"ERA-3 • змішаний / зростання балістики","ERA-4 • поточний балістично-насичений")))) -> ERA-3 • змішаний / зростання балістики | AR42: =IF(D42="","",IF(IFERROR(DATEVALUE(D42),0)>='Розрахунок'!$B$2-365,"MODEL-365","HISTORICAL_ONLY")) -> MODEL-365
A43: 42 | B43: Павлоград | C43: Балістика / швидкісні ракети | D43: 2025-10-26 | E43: Неділя | F43: 4 | G43: Кінець | H43: 1 | I43: Павлоград | J43: Іскандер-М — попередня оперативна атрибуція | K43: Ні | L43: B — локальний вибух + оперативна атрибуція Іскандер-М | M43: 26 жовтня в межах Павлограда пролунали вибухи; оперативні повідомлення атрибутували удар балістичній ракеті Іскандер-М. | N43: https://24tv.ua/vibuh-krivomu-rozi-rosiya-atakuye-kabami_n2940706 | O43: https://t.me/s/war_monitor?before=34365 | P43: B-рівень: прямого пізнішого локального форензичного підтвердження не знайдено; зберігаємо для sensitivity. | R43: ~11:37 | T43: Кількість локально не встановлена | V43: Балістична складова ймовірна, B-рівень | W43: Павлоград | AB43: Павлоград | AC43: Включено з B-рівнем — оперативно атрибутовано Іскандер-М по Павлограду | AD43: PVL-20251026-200 | AE43: Так | AN43: 1 | AO43: балістика B-рівень | AP43: Профіль включено з B-рівнем | AQ43: =IF(D43="","",IF(IFERROR(DATEVALUE(D43),0)<DATE(2024,9,1),"ERA-1 • масовані/ракетно-комбіновані",IF(IFERROR(DATEVALUE(D43),0)<DATE(2025,7,1),"ERA-2 • drone-saturation transition",IF(IFERROR(DATEVALUE(D43),0)<DATE(2026,4,1),"ERA-3 • змішаний / зростання балістики","ERA-4 • поточний балістично-насичений")))) -> ERA-3 • змішаний / зростання балістики | AR43: =IF(D43="","",IF(IFERROR(DATEVALUE(D43),0)>='Розрахунок'!$B$2-365,"MODEL-365","HISTORICAL_ONLY")) -> MODEL-365
A44: 43 | B44: Миколаїв | C44: Балістика / швидкісні ракети | D44: 2025-11-01 | E44: Субота | F44: 1 | G44: Початок | H44: 1 | I44: Передмістя Миколаєва | J44: Балістична ракета; касетна БЧ | K44: Ні | L44: B — пряма прив’язка до передмістя, населений пункт публічно не уточнений | M44: 1 листопада близько 07:20 РФ завдала удару балістичною ракетою по передмістю Миколаєва; загинув чоловік, поранені цивільні. | N44: https://suspilne.media/mykolaiv/1154136-balisticna-raketa-ta-12-udariv-fpv-dronami-ak-minula-doba-u-mikolaevi-ta-oblasti/ | O44: https://mk.npu.gov.ua/news/vnaslidok-raketnoho-udaru-po-mykolaievu-zahynuv-cholovik-ta-postrazhdaly-19-liudei-sered-nykh-dvoie-ditei-politsiia-dokumentuie-naslidky-voiennoho-zlochynu | P44: Включено до city+near-agglomeration з B-рівнем географії: джерело прямо називає передмістя Миколаєва, але не розкриває конкретний населений пункт. | R44: ~07:20 | S44: 1 | T44: Підтверджено: 1 | V44: Балістика підтверджена | W44: Передмістя Миколаєва | Y44: 1 | Z44: https://suspilne.media/mykolaiv/1154136-balisticna-raketa-ta-12-udariv-fpv-dronami-ak-minula-doba-u-mikolaevi-ta-oblasti/ | AA44: Пошкоджено АЗС, авто, приватний будинок та ЛЕП. | AB44: Ближня агломерація Миколаєва | AC44: Включено з B-рівнем географії — прямий балістичний удар по передмістю Миколаєва | AD44: MYK-20251101-196 | AE44: Так | AN44: 1 | AO44: балістика | AP44: Профіль включено з B-рівнем географії | AQ44: =IF(D44="","",IF(IFERROR(DATEVALUE(D44),0)<DATE(2024,9,1),"ERA-1 • масовані/ракетно-комбіновані",IF(IFERROR(DATEVALUE(D44),0)<DATE(2025,7,1),"ERA-2 • drone-saturation transition",IF(IFERROR(DATEVALUE(D44),0)<DATE(2026,4,1),"ERA-3 • змішаний / зростання балістики","ERA-4 • поточний балістично-насичений")))) -> ERA-3 • змішаний / зростання балістики | AR44: =IF(D44="","",IF(IFERROR(DATEVALUE(D44),0)>='Розрахунок'!$B$2-365,"MODEL-365","HISTORICAL_ONLY")) -> MODEL-365
A45: 44 | B45: Київ | C45: Балістика / швидкісні ракети | D45: 2025-11-08 | E45: Субота | F45: 2 | G45: Початок | H45: 1 | I45: Київ + область | J45: Іскандер-М/KN-23 + Х-47М2 Кинджал + Іскандер-К + Калібр — локальний subtype не рознесено | K45: Так | L45: B — Київщина основний напрямок; локальна ракетна атака агломерації + підтверджений балістичний/аеробалістичний пакет | M45: 8 листопада Київщина була одним з основних напрямків удару. Київська ОВА підтвердила масовану атаку ракетами та дронами, з наслідками у Бориспільському й Вишгородському районах; пакет містив 25 Іскандер-М/KN-23 і 7 «Кинджалів». | N45: https://www.pravda.com.ua/news/2025/11/08/8006418/ | O45: https://www.pravda.com.ua/news/2025/11/08/8006416/ | P45: Локальний subtype не розносимо; включаємо за combined-package + agglomeration rule. | AB45: Київ + ближня агломерація | AC45: Включено з B-рівнем — основний напрямок Київщина; Бориспіль/Вишгород у scope + підтверджений балістичний/аеробалістичний пакет | AD45: KYI-20251108-110 | AE45: Так | AO45: Іскандер-М/KN-23 + Кинджал + крилаті ракети + БпЛА | AP45: Delta-check 29.09.2026: старе city-only виключення скасовано. | AQ45: =IF(D45="","",IF(IFERROR(DATEVALUE(D45),0)<DATE(2024,9,1),"ERA-1 • масовані/ракетно-комбіновані",IF(IFERROR(DATEVALUE(D45),0)<DATE(2025,7,1),"ERA-2 • drone-saturation transition",IF(IFERROR(DATEVALUE(D45),0)<DATE(2026,4,1),"ERA-3 • змішаний / зростання балістики","ERA-4 • поточний балістично-насичений")))) -> ERA-3 • змішаний / зростання балістики | AR45: =IF(D45="","",IF(IFERROR(DATEVALUE(D45),0)>='Розрахунок'!$B$2-365,"MODEL-365","HISTORICAL_ONLY")) -> MODEL-365
A46: 45 | B46: Одеса | C46: Балістика / швидкісні ракети | D46: 2025-11-12 | E46: Середа | F46: 2 | G46: Середина | H46: 1 | I46: Одеса + Одеська область | J46: Іскандер-М (ймовірно) | K46: Так | L46: B — факт ракети підтверджено, тип імовірний | M46: Одещину атаковано балістичною ракетою, ймовірно Іскандер-М; також застосовано Х-31. | N46: https://suspilne.media/odesa/1163256-1359-den-vijni-hronika-podij-v-odesi-ta-odeskij-oblasti/ | O46: https://ivms.mil.gov.ua/wp-content/uploads/2025/11/dovidka-08.11-14.11.2025.pdf | P46: Внесено за правилом: підтверджена балістична ракета + ймовірний тип. | S46: 1 | T46: Підтверджено факт; тип імовірний | V46: Імовірно Іскандер-М | AB46: Одеса + Одеська область | AC46: Включено — підтверджений балістичний епізод по моделі Одеса + Одеська область | AD46: ODS-20251112-109 | AE46: Так | AF46: Так | AL46: Так | AO46: балістика + інші ракети | AP46: Профіль підтверджено за джерелами аудованого реєстру | AQ46: =IF(D46="","",IF(IFERROR(DATEVALUE(D46),0)<DATE(2024,9,1),"ERA-1 • масовані/ракетно-комбіновані",IF(IFERROR(DATEVALUE(D46),0)<DATE(2025,7,1),"ERA-2 • drone-saturation transition",IF(IFERROR(DATEVALUE(D46),0)<DATE(2026,4,1),"ERA-3 • змішаний / зростання балістики","ERA-4 • поточний балістично-насичений")))) -> ERA-3 • змішаний / зростання балістики | AR46: =IF(D46="","",IF(IFERROR(DATEVALUE(D46),0)>='Розрахунок'!$B$2-365,"MODEL-365","HISTORICAL_ONLY")) -> MODEL-365
A47: 46 | B47: Київ | C47: Балістика / швидкісні ракети | D47: 2025-11-14 | E47: П’ятниця | F47: 2 | G47: Початок | H47: 1 | I47: Київ + область | J47: Core ballistic | K47: Так | L47: A — пряма/локальна прив’язка | M47: Масована атака Києва та області балістикою та БпЛА | N47: https://www.pravda.com.ua/news/2025/11/14/7541674/ | O47: https://suspilne.media/kyiv/1195615-rf-atakuvala-kiiv-balistikou-ta-dronami/ | P47: Пряме підтвердження балістичної складової. | AB47: Київ | AC47: Включено — 14.11: масована комбінована атака Києва із застосуванням балістичних ракет прямо підтверджена | AD47: KYI-20251114-108 | AE47: Так | AH47: Так | AO47: балістика + БпЛА | AP47: Профіль підтверджено за джерелами аудованого реєстру | AQ47: =IF(D47="","",IF(IFERROR(DATEVALUE(D47),0)<DATE(2024,9,1),"ERA-1 • масовані/ракетно-комбіновані",IF(IFERROR(DATEVALUE(D47),0)<DATE(2025,7,1),"ERA-2 • drone-saturation transition",IF(IFERROR(DATEVALUE(D47),0)<DATE(2026,4,1),"ERA-3 • змішаний / зростання балістики","ERA-4 • поточний балістично-насичений")))) -> ERA-3 • змішаний / зростання балістики | AR47: =IF(D47="","",IF(IFERROR(DATEVALUE(D47),0)>='Розрахунок'!$B$2-365,"MODEL-365","HISTORICAL_ONLY")) -> MODEL-365
A48: 47 | B48: Київ | C48: Балістика / швидкісні ракети | D48: 2025-11-19 | E48: Середа | F48: 3 | G48: Середина | H48: 1 | I48: Київ + область | J48: Core ballistic | K48: Так | L48: A — пряма/локальна прив’язка | M48: Комбінована атака Києва та Київщини з балістичною складовою | N48: https://www.pravda.com.ua/news/2025/11/19/7542521/ | O48: https://suspilne.media/kyiv/1200765-ataka-na-kiiv-ta-oblast-e-zagibli-ta-poraneni/ | P48: Пряме підтвердження балістики по столиці. | AB48: Поза city-only / архів аудиту | AC48: Виключено — 19.11: перевірені локальні матеріали не підтверджують балістичний удар по Києву; сама загроза балістики не рахується епізодом | AD48: KYI-20251119-107 | AE48: Ні | AP48: Профіль не включено до чистої моделі; збережено для аудиту | AQ48: =IF(D48="","",IF(IFERROR(DATEVALUE(D48),0)<DATE(2024,9,1),"ERA-1 • масовані/ракетно-комбіновані",IF(IFERROR(DATEVALUE(D48),0)<DATE(2025,7,1),"ERA-2 • drone-saturation transition",IF(IFERROR(DATEVALUE(D48),0)<DATE(2026,4,1),"ERA-3 • змішаний / зростання балістики","ERA-4 • поточний балістично-насичений")))) -> ERA-3 • змішаний / зростання балістики | AR48: =IF(D48="","",IF(IFERROR(DATEVALUE(D48),0)>='Розрахунок'!$B$2-365,"MODEL-365","HISTORICAL_ONLY")) -> MODEL-365
A49: 48 | B49: Київ | C49: Балістика / швидкісні ракети | D49: 2025-11-25 | E49: Вівторок | F49: 4 | G49: Кінець | H49: 1 | I49: Київ + область | J49: Core ballistic | K49: Так | L49: A — пряма/локальна прив’язка | M49: Масована атака Києва та області з балістичною складовою | N49: https://www.pravda.com.ua/news/2025/11/25/7543517/ | O49: https://suspilne.media/kyiv/1206875-rf-atakuvala-kiiv-balistikou-ta-dronami/ | P49: Пряме підтвердження балістики по столиці. | AB49: Київ | AC49: Включено — 25.11: Повітряні сили підтвердили балістичні ракети по столиці; три балістичні ракети на Київ були збиті | AD49: KYI-20251125-106 | AE49: Так | AO49: балістика | AP49: Профіль підтверджено за джерелами аудованого реєстру | AQ49: =IF(D49="","",IF(IFERROR(DATEVALUE(D49),0)<DATE(2024,9,1),"ERA-1 • масовані/ракетно-комбіновані",IF(IFERROR(DATEVALUE(D49),0)<DATE(2025,7,1),"ERA-2 • drone-saturation transition",IF(IFERROR(DATEVALUE(D49),0)<DATE(2026,4,1),"ERA-3 • змішаний / зростання балістики","ERA-4 • поточний балістично-насичений")))) -> ERA-3 • змішаний / зростання балістики | AR49: =IF(D49="","",IF(IFERROR(DATEVALUE(D49),0)>='Розрахунок'!$B$2-365,"MODEL-365","HISTORICAL_ONLY")) -> MODEL-365
A50: 49 | B50: Одеса | C50: Балістика / швидкісні ракети | D50: 2025-11-27 | E50: Четвер | F50: 4 | G50: Кінець | H50: 1 | I50: Одеса + Одеська область | J50: Іскандер-М | K50: Так | L50: A — пряма/локальна прив’язка | M50: Увечері Одещину атаковано балістичною ракетою Іскандер-М з ТОТ Криму. | N50: https://suspilne.media/odesa/1175866-rf-atakuvala-odesinu-balisticnou-raketou-so-vidomo/ | O50: https://www.pravda.com.ua/news/2025/11/28/8009356/ | P50: Пряме підтвердження ПК Південь. | S50: 1 | T50: Підтверджено | V50: Підтверджено | AB50: Одеса + Одеська область | AC50: Включено — 27.11: ПК Південь підтвердило Іскандер-М по Одещині | AD50: ODS-20251127-105 | AE50: Так | AO50: балістика | AP50: Профіль підтверджено за джерелами аудованого реєстру | AQ50: =IF(D50="","",IF(IFERROR(DATEVALUE(D50),0)<DATE(2024,9,1),"ERA-1 • масовані/ракетно-комбіновані",IF(IFERROR(DATEVALUE(D50),0)<DATE(2025,7,1),"ERA-2 • drone-saturation transition",IF(IFERROR(DATEVALUE(D50),0)<DATE(2026,4,1),"ERA-3 • змішаний / зростання балістики","ERA-4 • поточний балістично-насичений")))) -> ERA-3 • змішаний / зростання балістики | AR50: =IF(D50="","",IF(IFERROR(DATEVALUE(D50),0)>='Розрахунок'!$B$2-365,"MODEL-365","HISTORICAL_ONLY")) -> MODEL-365
A51: 50 | B51: Київ | C51: Балістика / швидкісні ракети | D51: 2025-11-29 | E51: Субота | F51: 5 | G51: Кінець | H51: 1 | I51: Київ + область | J51: Core ballistic | K51: Так | L51: A — пряма/локальна прив’язка | M51: Масована комбінована атака Києва та області з балістичною складовою | N51: https://www.pravda.com.ua/news/2025/11/29/7544201/ | O51: https://suspilne.media/kyiv/1210935-ataka-na-kiiv-ta-oblast-e-zagibli-ta-poraneni/ | P51: Пряме підтвердження балістики по столиці. | AB51: Київ | AC51: Включено — 29.11: пряме повідомлення про швидкісну ціль на Київ і серію вибухів під час балістичної фази; залишити в чистій базі | AD51: KYI-20251129-103 | AE51: Так | AO51: балістика | AP51: Профіль підтверджено за джерелами аудованого реєстру | AQ51: =IF(D51="","",IF(IFERROR(DATEVALUE(D51),0)<DATE(2024,9,1),"ERA-1 • масовані/ракетно-комбіновані",IF(IFERROR(DATEVALUE(D51),0)<DATE(2025,7,1),"ERA-2 • drone-saturation transition",IF(IFERROR(DATEVALUE(D51),0)<DATE(2026,4,1),"ERA-3 • змішаний / зростання балістики","ERA-4 • поточний балістично-насичений")))) -> ERA-3 • змішаний / зростання балістики | AR51: =IF(D51="","",IF(IFERROR(DATEVALUE(D51),0)>='Розрахунок'!$B$2-365,"MODEL-365","HISTORICAL_ONLY")) -> MODEL-365
A52: 51 | B52: Одеса | C52: Балістика / швидкісні ракети | D52: 2025-11-29 | E52: Субота | F52: 5 | G52: Кінець | H52: 1 | I52: Одеса + Одеська область | J52: Іскандер-М | K52: Так | L52: A — пряма/локальна прив’язка | M52: Увечері 29 листопада Одещину атаковано двома балістичними ракетами Іскандер-М із ТОТ Криму. | N52: https://suspilne.media/odesa/1177278-rf-atakuvala-odesinu-dvoma-balisticnimi-raketami-so-vidomo/ | O52: https://www.blackseanews.net/amp/read/240196 | P52: ПК Південь: 2 Іскандер-М по Одеській області. | S52: 2 | T52: Підтверджено | V52: Підтверджено | AB52: Одеса + Одеська область | AC52: Включено — 29.11: ПК Південь підтвердило 2 Іскандер-М по Одещині | AD52: ODS-20251129-104 | AE52: Так | AO52: балістика | AP52: Профіль підтверджено за джерелами аудованого реєстру | AQ52: =IF(D52="","",IF(IFERROR(DATEVALUE(D52),0)<DATE(2024,9,1),"ERA-1 • масовані/ракетно-комбіновані",IF(IFERROR(DATEVALUE(D52),0)<DATE(2025,7,1),"ERA-2 • drone-saturation transition",IF(IFERROR(DATEVALUE(D52),0)<DATE(2026,4,1),"ERA-3 • змішаний / зростання балістики","ERA-4 • поточний балістично-насичений")))) -> ERA-3 • змішаний / зростання балістики | AR52: =IF(D52="","",IF(IFERROR(DATEVALUE(D52),0)>='Розрахунок'!$B$2-365,"MODEL-365","HISTORICAL_ONLY")) -> MODEL-365
A53: 52 | B53: Дніпро | C53: Балістика / швидкісні ракети | D53: 2025-12-01 | E53: Понеділок | F53: 1 | G53: Початок | H53: 1 | I53: Дніпро | J53: Балістична ракета — тип не уточнено | K53: Ні | L53: A — пряма локальна прив’язка | M53: Вранці 1 грудня РФ вдарила по середмістю Дніпра балістичною ракетою; є загиблі та десятки поранених. | N53: https://suspilne.media/dnipro/1177852-vijska-rf-vdarili-po-dnipru-raketou/ | O53: https://www.pravda.com.ua/news/2025/12/01/8009742/ | P53: Міський голова прямо назвав ракету балістичною; перед вибухом ПС повідомляли про загрозу балістичного озброєння. | R53: 10:14 | T53: Тип і кількість локально не уточнюємо | V53: Підтверджено | W53: Дніпро | Y53: 4 багатоповерхівки | Z53: https://suspilne.media/dnipro/1177852-vijska-rf-vdarili-po-dnipru-raketou/ | AB53: Дніпро | AC53: Включено — прямий підтверджений балістичний епізод по Дніпру | AD53: DNI-20251201-010 | AE53: Так | AH53: Ні | AO53: балістика | AP53: Підтверджено джерелом | AQ53: =IF(D53="","",IF(IFERROR(DATEVALUE(D53),0)<DATE(2024,9,1),"ERA-1 • масовані/ракетно-комбіновані",IF(IFERROR(DATEVALUE(D53),0)<DATE(2025,7,1),"ERA-2 • drone-saturation transition",IF(IFERROR(DATEVALUE(D53),0)<DATE(2026,4,1),"ERA-3 • змішаний / зростання балістики","ERA-4 • поточний балістично-насичений")))) -> ERA-3 • змішаний / зростання балістики | AR53: =IF(D53="","",IF(IFERROR(DATEVALUE(D53),0)>='Розрахунок'!$B$2-365,"MODEL-365","HISTORICAL_ONLY")) -> MODEL-365
A54: 53 | B54: Кривий Ріг | C54: Балістика / швидкісні ракети | D54: 2025-12-03 | E54: Середа | F54: 1 | G54: Початок | H54: 1 | I54: Кривий Ріг | J54: Іскандер-М — попередньо | K54: Ні | L54: A — пряма локальна прив’язка | M54: 3 грудня Росія вдарила балістичною ракетою по Кривому Рогу; влучання припало по адміністративній будівлі, пошкоджено житлові будинки. | N54: https://suspilne.media/dnipro/1180258-vijska-rf-vdarili-balistikou-po-krivomu-rogu-so-vidomo/ | O54: https://fakty.com.ua/ua/proisshestvija/20251203-vybuhy-u-kryvomu-rozi-shho-stalosya-sogodni-3-grudnya-2025/ | P54: Іскандер-М — попередня атрибуція місцевої влади; балістичний клас підтверджено. | S54: 1 | T54: Одна балістична ракета | V54: Балістика підтверджена; subtype попередній | W54: Кривий Ріг | Y54: 44 | Z54: https://suspilne.media/dnipro/1180258-vijska-rf-vdarili-balistikou-po-krivomu-rogu-so-vidomo/ | AA54: Пошкоджено 15 багатоквартирних і 29 приватних будинків; пряме влучання було не в житло. | AB54: Кривий Ріг | AC54: Включено — пряме підтвердження балістичного удару по Кривому Рогу | AD54: KRR-20251203-160 | AE54: Так | AN54: 1 | AO54: балістика | AP54: Профіль підтверджено | AQ54: =IF(D54="","",IF(IFERROR(DATEVALUE(D54),0)<DATE(2024,9,1),"ERA-1 • масовані/ракетно-комбіновані",IF(IFERROR(DATEVALUE(D54),0)<DATE(2025,7,1),"ERA-2 • drone-saturation transition",IF(IFERROR(DATEVALUE(D54),0)<DATE(2026,4,1),"ERA-3 • змішаний / зростання балістики","ERA-4 • поточний балістично-насичений")))) -> ERA-3 • змішаний / зростання балістики | AR54: =IF(D54="","",IF(IFERROR(DATEVALUE(D54),0)>='Розрахунок'!$B$2-365,"MODEL-365","HISTORICAL_ONLY")) -> MODEL-365
A55: 54 | B55: Харків | C55: Балістика / швидкісні ракети | D55: 2025-12-03 | E55: Середа | F55: 1 | G55: Початок | H55: 1 | I55: Харків | J55: Іскандер-М — регіональний weapon list; локальний subtype не остаточний | K55: Ні | L55: B — локальний ракетний удар + регіональна балістична атрибуція | M55: 3 грудня ракета вдарила по Слобідському району Харкова; ХОВА у зведенні за добу вказала застосування однієї ракети Іскандер-М по Харківщині. | N55: https://kharkivoda.gov.ua/news/133777 | O55: https://hk.npu.gov.ua/news/na-kharkivshchyni-politseiski-zadokumentuvaly-naslidky-voiennykh-zlochyniv-04-12-25 | P55: B-рівень: локальний ракетний удар підтверджений, але subtype Іскандер-М не атрибутовано місту окремою форензикою. | R55: ~20:15 | S55: 1 | T55: Регіонально: 1 Іскандер-М; локальна атрибуція B | V55: Балістична складова ймовірна, B-рівень | W55: Харків | Z55: https://kharkivoda.gov.ua/news/133777 | AA55: Не використовувати точний subtype як локально доведений. | AB55: Харків | AC55: Включено з B-рівнем — локальний удар + регіональна балістична атрибуція | AD55: KHR-20251203-183 | AE55: Так | AN55: 1 | AO55: балістика B-рівень | AP55: Профіль включено з позначкою B | AQ55: =IF(D55="","",IF(IFERROR(DATEVALUE(D55),0)<DATE(2024,9,1),"ERA-1 • масовані/ракетно-комбіновані",IF(IFERROR(DATEVALUE(D55),0)<DATE(2025,7,1),"ERA-2 • drone-saturation transition",IF(IFERROR(DATEVALUE(D55),0)<DATE(2026,4,1),"ERA-3 • змішаний / зростання балістики","ERA-4 • поточний балістично-насичений")))) -> ERA-3 • змішаний / зростання балістики | AR55: =IF(D55="","",IF(IFERROR(DATEVALUE(D55),0)>='Розрахунок'!$B$2-365,"MODEL-365","HISTORICAL_ONLY")) -> MODEL-365
A56: 55 | B56: Київ | C56: Балістика / швидкісні ракети | D56: 2025-12-06 | E56: Субота | F56: 1 | G56: Початок | H56: 1 | I56: Київ + область | J56: Х-47М2 Кинджал + Іскандер-М/KN-23 + Х-101/Іскандер-К/Калібр — локальний subtype не рознесено | K56: Так | L56: B — ракетно-дронова атака агломерації + підтверджений балістичний/аеробалістичний пакет | M56: 6 грудня Київщина зазнала масованої ракетно-дронової атаки; Вишгородський і Бучанський райони входять у scope моделі. Загальний пакет містив 3 «Кинджали» та 14 Іскандер-М/KN-23 поряд із крилатими ракетами. | N56: https://www.pravda.com.ua/news/2025/12/06/8010650/ | O56: https://www.pravda.com.ua/news/2025/12/06/8010638/ | P56: Не приписуємо subtype конкретному району; включаємо за agglomeration + confirmed ballistic/aeroballistic package rule. | AB56: Київ + ближня агломерація | AC56: Включено з B-рівнем — Вишгородський/Бучанський напрямки у scope + підтверджений балістичний/аеробалістичний пакет | AD56: KYI-20251206-101 | AE56: Так | AH56: Так | AO56: Кинджал + Іскандер-М/KN-23 + крилаті ракети + БпЛА | AP56: Delta-check 29.09.2026: старе city-only виключення скасовано. | AQ56: =IF(D56="","",IF(IFERROR(DATEVALUE(D56),0)<DATE(2024,9,1),"ERA-1 • масовані/ракетно-комбіновані",IF(IFERROR(DATEVALUE(D56),0)<DATE(2025,7,1),"ERA-2 • drone-saturation transition",IF(IFERROR(DATEVALUE(D56),0)<DATE(2026,4,1),"ERA-3 • змішаний / зростання балістики","ERA-4 • поточний балістично-насичений")))) -> ERA-3 • змішаний / зростання балістики | AR56: =IF(D56="","",IF(IFERROR(DATEVALUE(D56),0)>='Розрахунок'!$B$2-365,"MODEL-365","HISTORICAL_ONLY")) -> MODEL-365
A57: 56 | B57: Одеса | C57: Балістика / швидкісні ракети | D57: 2025-12-06 | E57: Субота | F57: 1 | G57: Початок | H57: 1 | I57: Одеса + Одеська область | J57: Іскандер-М | K57: Так | L57: A — пряма/локальна прив’язка | M57: Уночі 6 грудня Одещину атаковано двома балістичними ракетами Іскандер-М; пошкоджено енергетичну та портову інфраструктуру. | N57: https://suspilne.media/odesa/1182418-rf-atakuvala-odesinu-dvoma-balisticnimi-raketami-rezultati-roboti-ppo-na-pivdni/ | O57: https://suspilne.media/odesa/1182400-unoci-rf-atakuvala-energeticnu-infrastrukturu-odesini-rozpocato-rozsliduvanna/ | P57: Пряме підтвердження ПК Південь; 2 Іскандер-М. | S57: 2 | T57: Підтверджено | V57: Підтверджено | AB57: Одеса + Одеська область | AC57: Включено — 06.12: ПК Південь підтвердило 2 Іскандер-М по Одещині | AD57: ODS-20251206-102 | AE57: Так | AO57: балістика | AP57: Профіль підтверджено за джерелами аудованого реєстру | AQ57: =IF(D57="","",IF(IFERROR(DATEVALUE(D57),0)<DATE(2024,9,1),"ERA-1 • масовані/ракетно-комбіновані",IF(IFERROR(DATEVALUE(D57),0)<DATE(2025,7,1),"ERA-2 • drone-saturation transition",IF(IFERROR(DATEVALUE(D57),0)<DATE(2026,4,1),"ERA-3 • змішаний / зростання балістики","ERA-4 • поточний балістично-насичений")))) -> ERA-3 • змішаний / зростання балістики | AR57: =IF(D57="","",IF(IFERROR(DATEVALUE(D57),0)>='Розрахунок'!$B$2-365,"MODEL-365","HISTORICAL_ONLY")) -> MODEL-365
A58: 57 | B58: Одеса | C58: Балістика / швидкісні ракети | D58: 2025-12-12 | E58: П’ятниця | F58: 2 | G58: Середина | H58: 1 | I58: Одеса + Одеська область | J58: Іскандер-М/KN-23 | K58: Так | L58: A — пряма/локальна прив’язка | M58: По припортовій інфраструктурі Одещини спрямовано три Іскандер-М/KN-23. | N58: https://ivms.mil.gov.ua/wp-content/uploads/2025/12/dovidka-08.12-14.12.2025.pdf | O58: https://bessarabiainform.com/2025/12/stalo-vidomo-yakymy-typamy-raket-atakuvaly-odesku-oblast-za-mynulu-dobu/ | P58: Окремий денний/вечірній епізод 12.12 перед нічною атакою 13.12. | S58: 3 | T58: Підтверджено | V58: Підтверджено | AB58: Одеса + Одеська область | AC58: Включено — підтверджений балістичний епізод по моделі Одеса + Одеська область | AD58: ODS-20251212-100 | AE58: Так | AO58: балістика | AP58: Профіль підтверджено за джерелами аудованого реєстру | AQ58: =IF(D58="","",IF(IFERROR(DATEVALUE(D58),0)<DATE(2024,9,1),"ERA-1 • масовані/ракетно-комбіновані",IF(IFERROR(DATEVALUE(D58),0)<DATE(2025,7,1),"ERA-2 • drone-saturation transition",IF(IFERROR(DATEVALUE(D58),0)<DATE(2026,4,1),"ERA-3 • змішаний / зростання балістики","ERA-4 • поточний балістично-насичений")))) -> ERA-3 • змішаний / зростання балістики | AR58: =IF(D58="","",IF(IFERROR(DATEVALUE(D58),0)>='Розрахунок'!$B$2-365,"MODEL-365","HISTORICAL_ONLY")) -> MODEL-365
A59: 58 | B59: Київ | C59: Балістика / швидкісні ракети | D59: 2025-12-13 | E59: Субота | F59: 2 | G59: Початок | H59: 1 | I59: Київ + область | J59: Core ballistic | K59: Так | L59: A — пряма/локальна прив’язка | M59: Нічна атака Києва та Київщини з балістичною складовою | N59: https://www.pravda.com.ua/news/2025/12/13/7546542/ | O59: https://suspilne.media/kyiv/1225185-ataka-na-kiiv-ta-oblast-e-zagibli-ta-poraneni/ | P59: Пряме підтвердження балістики по столиці. | AB59: Поза city-only / архів аудиту | AC59: Виключено — 13.12: загальна ракетна небезпека/комбінований удар підтверджені, але прямого балістичного епізоду по Києву не встановлено | AD59: KYI-20251213-098 | AE59: Ні | AP59: Профіль не включено до чистої моделі; збережено для аудиту | AQ59: =IF(D59="","",IF(IFERROR(DATEVALUE(D59),0)<DATE(2024,9,1),"ERA-1 • масовані/ракетно-комбіновані",IF(IFERROR(DATEVALUE(D59),0)<DATE(2025,7,1),"ERA-2 • drone-saturation transition",IF(IFERROR(DATEVALUE(D59),0)<DATE(2026,4,1),"ERA-3 • змішаний / зростання балістики","ERA-4 • поточний балістично-насичений")))) -> ERA-3 • змішаний / зростання балістики | AR59: =IF(D59="","",IF(IFERROR(DATEVALUE(D59),0)>='Розрахунок'!$B$2-365,"MODEL-365","HISTORICAL_ONLY")) -> MODEL-365
A60: 59 | B60: Одеса | C60: Балістика / швидкісні ракети | D60: 2025-12-13 | E60: Субота | F60: 2 | G60: Середина | H60: 1 | I60: Одеса + Одеська область | J60: Іскандер-М/KN-23 | K60: Так | L60: A — пряма/локальна прив’язка | M60: Нічна масована атака Одещини: п’ять Іскандер-М/KN-23; також застосовано Кинджали та інші засоби. | N60: https://ivms.mil.gov.ua/wp-content/uploads/2025/12/dovidka-08.12-14.12.2025.pdf | O60: https://www.blackseanews.net/amp/read/240196 | P60: Балістична фаза після 00:00 — дата епізоду 13.12. | S60: 5 | T60: Підтверджено | V60: Підтверджено | AB60: Одеса + Одеська область | AC60: Включено — підтверджений балістичний епізод по моделі Одеса + Одеська область | AD60: ODS-20251213-099 | AE60: Так | AL60: Так | AO60: балістика + інші ракети | AP60: Профіль підтверджено за джерелами аудованого реєстру | AQ60: =IF(D60="","",IF(IFERROR(DATEVALUE(D60),0)<DATE(2024,9,1),"ERA-1 • масовані/ракетно-комбіновані",IF(IFERROR(DATEVALUE(D60),0)<DATE(2025,7,1),"ERA-2 • drone-saturation transition",IF(IFERROR(DATEVALUE(D60),0)<DATE(2026,4,1),"ERA-3 • змішаний / зростання балістики","ERA-4 • поточний балістично-насичений")))) -> ERA-3 • змішаний / зростання балістики | AR60: =IF(D60="","",IF(IFERROR(DATEVALUE(D60),0)>='Розрахунок'!$B$2-365,"MODEL-365","HISTORICAL_ONLY")) -> MODEL-365
A61: 60 | B61: Одеса | C61: Балістика / швидкісні ракети | D61: 2025-12-19 | E61: П’ятниця | F61: 3 | G61: Середина | H61: 1 | I61: Одеса + Одеська область | J61: Іскандер-М | K61: Так | L61: A — пряма/локальна прив’язка | M61: Одещину атаковано чотирма балістичними ракетами Іскандер-М з ТОТ Криму. | N61: https://ivms.mil.gov.ua/wp-content/uploads/2025/12/dovidka-15.12-21.12.2025.pdf | O61: https://od.vgorode.ua/ukr/news/sobytyia/a1285299-rf-udarila-po-odeshchini-chotirma-raketami-usi-buli-balistichnimi | P61: Дата виправлена: 19.12, не 20.12. | S61: 4 | T61: Підтверджено | V61: Підтверджено | AB61: Одеса + Одеська область | AC61: Включено — підтверджений балістичний епізод по моделі Одеса + Одеська область | AD61: ODS-20251219-097 | AE61: Так | AO61: балістика | AP61: Профіль підтверджено за джерелами аудованого реєстру | AQ61: =IF(D61="","",IF(IFERROR(DATEVALUE(D61),0)<DATE(2024,9,1),"ERA-1 • масовані/ракетно-комбіновані",IF(IFERROR(DATEVALUE(D61),0)<DATE(2025,7,1),"ERA-2 • drone-saturation transition",IF(IFERROR(DATEVALUE(D61),0)<DATE(2026,4,1),"ERA-3 • змішаний / зростання балістики","ERA-4 • поточний балістично-насичений")))) -> ERA-3 • змішаний / зростання балістики | AR61: =IF(D61="","",IF(IFERROR(DATEVALUE(D61),0)>='Розрахунок'!$B$2-365,"MODEL-365","HISTORICAL_ONLY")) -> MODEL-365
A62: 61 | B62: Київ | C62: Балістика / швидкісні ракети | D62: 2025-12-23 | E62: Вівторок | F62: 4 | G62: Кінець | H62: 1 | I62: Київ + область | J62: Core ballistic | K62: Так | L62: A — пряма/локальна прив’язка | M62: Масована комбінована атака Києва та області з балістичною складовою | N62: https://www.pravda.com.ua/news/2025/12/23/7548236/ | O62: https://suspilne.media/kyiv/1235375-rf-atakuvala-kiiv-balistikou-ta-dronami/ | P62: Пряме підтвердження балістики по столиці. | AB62: Поза city-only / архів аудиту | AC62: Виключено — 23.12: наслідки в Києві пов’язані з БпЛА; підтвердження балістичного удару по столиці не встановлено | AD62: KYI-20251223-096 | AE62: Ні | AP62: Профіль не включено до чистої моделі; збережено для аудиту | AQ62: =IF(D62="","",IF(IFERROR(DATEVALUE(D62),0)<DATE(2024,9,1),"ERA-1 • масовані/ракетно-комбіновані",IF(IFERROR(DATEVALUE(D62),0)<DATE(2025,7,1),"ERA-2 • drone-saturation transition",IF(IFERROR(DATEVALUE(D62),0)<DATE(2026,4,1),"ERA-3 • змішаний / зростання балістики","ERA-4 • поточний балістично-насичений")))) -> ERA-3 • змішаний / зростання балістики | AR62: =IF(D62="","",IF(IFERROR(DATEVALUE(D62),0)>='Розрахунок'!$B$2-365,"MODEL-365","HISTORICAL_ONLY")) -> MODEL-365
A63: 62 | B63: Київ | C63: Балістика / швидкісні ракети | D63: 2025-12-27 | E63: Субота | F63: 4 | G63: Кінець | H63: 1 | I63: Київ + область | J63: Core ballistic | K63: Так | L63: A — пряма/локальна прив’язка | M63: Масована атака Києва та області балістикою та БпЛА | N63: https://www.pravda.com.ua/news/2025/12/27/7548874/ | O63: https://suspilne.media/kyiv/1239455-ataka-na-kiiv-ta-oblast-e-zagibli-ta-poraneni/ | P63: Пряме підтвердження балістичної складової. | AB63: Київ | AC63: Включено — 27.12: масований комбінований удар, основний напрямок Київщина; балістичні/швидкісні цілі на Київ підтверджені | AD63: KYI-20251227-095 | AE63: Так | AH63: Так | AO63: балістика + БпЛА | AP63: Профіль підтверджено за джерелами аудованого реєстру | AQ63: =IF(D63="","",IF(IFERROR(DATEVALUE(D63),0)<DATE(2024,9,1),"ERA-1 • масовані/ракетно-комбіновані",IF(IFERROR(DATEVALUE(D63),0)<DATE(2025,7,1),"ERA-2 • drone-saturation transition",IF(IFERROR(DATEVALUE(D63),0)<DATE(2026,4,1),"ERA-3 • змішаний / зростання балістики","ERA-4 • поточний балістично-насичений")))) -> ERA-3 • змішаний / зростання балістики | AR63: =IF(D63="","",IF(IFERROR(DATEVALUE(D63),0)>='Розрахунок'!$B$2-365,"MODEL-365","HISTORICAL_ONLY")) -> MODEL-365
A64: 63 | B64: Одеса | C64: Балістика / швидкісні ракети | D64: 2025-12-30 | E64: Вівторок | F64: 5 | G64: Кінець | H64: 1 | I64: Одеса + Одеська область | J64: Іскандер-М | K64: Так | L64: A — пряма/локальна прив’язка | M64: Уночі Одещину атаковано балістичною ракетою Іскандер-М із ТОТ Криму. | N64: https://suspilne.media/odesa/1201578-unoci-rf-atakuvala-odesinu-balisticnou-raketou/ | O64: https://www.pravda.com.ua/news/2025/12/30/8013947/ | P64: З двох Іскандер-М по Україні одна локально підтверджена по Одещині. | S64: 1 | T64: Локально підтверджено | V64: Підтверджено | AB64: Одеса + Одеська область | AC64: Включено — 30.12: ПК Південь підтвердило Іскандер-М по Одещині | AD64: ODS-20251230-094 | AE64: Так | AO64: балістика | AP64: Профіль підтверджено за джерелами аудованого реєстру | AQ64: =IF(D64="","",IF(IFERROR(DATEVALUE(D64),0)<DATE(2024,9,1),"ERA-1 • масовані/ракетно-комбіновані",IF(IFERROR(DATEVALUE(D64),0)<DATE(2025,7,1),"ERA-2 • drone-saturation transition",IF(IFERROR(DATEVALUE(D64),0)<DATE(2026,4,1),"ERA-3 • змішаний / зростання балістики","ERA-4 • поточний балістично-насичений")))) -> ERA-3 • змішаний / зростання балістики | AR64: =IF(D64="","",IF(IFERROR(DATEVALUE(D64),0)>='Розрахунок'!$B$2-365,"MODEL-365","HISTORICAL_ONLY")) -> MODEL-365
A65: 64 | B65: Харків | C65: Балістика / швидкісні ракети | D65: 2026-01-02 | E65: П’ятниця | F65: 1 | G65: Початок | H65: 1 | I65: Харків | J65: Іскандер-М, 2 ракети | K65: Ні | L65: A — пряма локальна прив’язка | M65: 2 січня дві ракети Іскандер-М вдарили по Київському району Харкова. | N65: https://suspilne.media/kharkiv/1204206-u-seredmisti-harkova-bulo-cuti-vibuhi-terehov-povidomiv-pro-rosijsku-ataku/ | O65: https://kharkivoda.gov.ua/news/134153 | P65: Кількість і subtype підтверджені локальними джерелами. | R65: ~14:30 | S65: 2 | T65: Підтверджено: 2 Іскандер-М | V65: Балістика підтверджена | W65: Харків | Z65: https://suspilne.media/amp/kharkiv/1204450-sonajmense-27-budivel-zaznali-poskodzen-cerez-vibuhi-u-harkovi-2-sicna-miska-rada/ | AA65: Пошкодження будівель спричинені балістичною атакою; прямі влучання у житло окремо не встановлюємо. | AB65: Харків | AC65: Включено — два Іскандер-М по Харкову | AD65: KHR-20260102-184 | AE65: Так | AN65: 2 | AO65: балістика Іскандер-М | AP65: Профіль підтверджено за двома джерелами | AQ65: =IF(D65="","",IF(IFERROR(DATEVALUE(D65),0)<DATE(2024,9,1),"ERA-1 • масовані/ракетно-комбіновані",IF(IFERROR(DATEVALUE(D65),0)<DATE(2025,7,1),"ERA-2 • drone-saturation transition",IF(IFERROR(DATEVALUE(D65),0)<DATE(2026,4,1),"ERA-3 • змішаний / зростання балістики","ERA-4 • поточний балістично-насичений")))) -> ERA-3 • змішаний / зростання балістики | AR65: =IF(D65="","",IF(IFERROR(DATEVALUE(D65),0)>='Розрахунок'!$B$2-365,"MODEL-365","HISTORICAL_ONLY")) -> MODEL-365
A66: 65 | B66: Чернігів | C66: Балістика / швидкісні ракети | D66: 2026-01-05 | E66: Понеділок | F66: 1 | G66: Початок | H66: 1 | I66: Чернігів | J66: Балістичні ракети — тип і локальна кількість публічно не рознесені | K66: Так | L66: A — пряма локальна прив’язка балістики | M66: У ніч на 5 січня російські війська атакували Чернігів балістичними ракетами та ударними БпЛА. Міська влада, Суспільне та поліція підтвердили комбінований ракетно-дроновий удар по місту. | N66: https://suspilne.media/chernihiv/1205486-rf-balisticnimi-raketami-ta-bpla-atakuvala-cernigiv/ | O66: https://cn.npu.gov.ua/news/politsiia-dokumentuie-naslidky-rosiiskoi-ataky-po-chernihovu | P66: Локальну кількість балістичних ракет не встановлюємо; загальноукраїнські кількості не переносимо на Чернігів. | Q66: 2026-01-05 | R66: ~02:56 | T66: Локальна кількість не встановлена | V66: Балістична складова підтверджена; конкретні влучання по житлу не рознесені за типом засобу | W66: Чернігів | X66: Житлові райони / підприємство | Z66: https://chernigiv-rada.gov.ua/news/id-168568/ | AA66: Наслідки комбінованої атаки не приписувати виключно балістиці. | AB66: Чернігів | AC66: Включено — пряме локальне підтвердження балістики | AD66: CHN-20260105-206 | AE66: Так | AH66: Так | AO66: балістика + БпЛА | AP66: Профіль підтверджено; локальна кількість ракет невідома | AQ66: ERA-3 • змішаний / зростання балістики | AR66: MODEL-365
A67: 66 | B67: Одеса | C67: Балістика / швидкісні ракети | D67: 2026-01-07 | E67: Середа | F67: 1 | G67: Початок | H67: 1 | I67: Одеса + Одеська область | J67: Іскандер-М | K67: Так | L67: A — пряма/локальна прив’язка | M67: Порт Південний атаковано двома балістичними ракетами Іскандер-М. | N67: https://suspilne.media/odesa/1208354-rosia-vdarila-po-odesini-dvoma-balisticnimi-raketami-iskander-m/ | O67: https://bessarabiainform.com/2026/01/rf-atakuvala-dvoma-iskanderamy-port-na-odeschyni/ | P67: Пряма локальна прив’язка до Одеської області. | S67: 2 | T67: Підтверджено | V67: Підтверджено | AB67: Одеса + Одеська область | AC67: Включено — підтверджений балістичний епізод по моделі Одеса + Одеська область | AD67: ODS-20260107-093 | AE67: Так | AO67: балістика | AP67: Профіль підтверджено за джерелами аудованого реєстру | AQ67: =IF(D67="","",IF(IFERROR(DATEVALUE(D67),0)<DATE(2024,9,1),"ERA-1 • масовані/ракетно-комбіновані",IF(IFERROR(DATEVALUE(D67),0)<DATE(2025,7,1),"ERA-2 • drone-saturation transition",IF(IFERROR(DATEVALUE(D67),0)<DATE(2026,4,1),"ERA-3 • змішаний / зростання балістики","ERA-4 • поточний балістично-насичений")))) -> ERA-3 • змішаний / зростання балістики | AR67: =IF(D67="","",IF(IFERROR(DATEVALUE(D67),0)>='Розрахунок'!$B$2-365,"MODEL-365","HISTORICAL_ONLY")) -> MODEL-365
A68: 67 | B68: Кривий Ріг | C68: Балістика / швидкісні ракети | D68: 2026-01-08 | E68: Четвер | F68: 2 | G68: Початок | H68: 1 | I68: Кривий Ріг | J68: Іскандер-М | K68: Так | L68: A — пряма локальна прив’язка | M68: 8 січня Кривий Ріг атаковано двома балістичними ракетами Іскандер-М та ударними БпЛА; удар припав по житловій забудові. | N68: https://suspilne.media/dnipro/1208946-armia-rf-atakuvala-krivij-rig-balistikou-ta-dronami-so-vidomo/ | O68: https://suspilne.media/dnipro/1209458-tazka-politravma-ta-minno-vibuhovi-poranenna-ak-pocuvautsa-gospitalizovani-cerez-balisticnu-ataku-rf-po-krivomu-rogu/ | P68: Дві балістичні ракети та дронова складова підтверджені локально. | S68: 2 | T68: Підтверджено: 2 | U68: 2 | V68: Прямий удар по багатоквартирній житловій забудові | W68: Кривий Ріг | X68: багатоквартирні будинки | Y68: 29 | Z68: https://suspilne.media/dnipro/1208946-armia-rf-atakuvala-krivij-rig-balistikou-ta-dronami-so-vidomo/ | AA68: Пошкоджено 29 багатоквартирних будинків; наслідки комбінованої атаки. | AB68: Кривий Ріг | AC68: Включено — пряме підтвердження 2 Іскандер-М по Кривому Рогу | AD68: KRR-20260108-161 | AE68: Так | AH68: Так | AO68: балістика + БпЛА | AP68: Профіль підтверджено | AQ68: =IF(D68="","",IF(IFERROR(DATEVALUE(D68),0)<DATE(2024,9,1),"ERA-1 • масовані/ракетно-комбіновані",IF(IFERROR(DATEVALUE(D68),0)<DATE(2025,7,1),"ERA-2 • drone-saturation transition",IF(IFERROR(DATEVALUE(D68),0)<DATE(2026,4,1),"ERA-3 • змішаний / зростання балістики","ERA-4 • поточний балістично-насичений")))) -> ERA-3 • змішаний / зростання балістики | AR68: =IF(D68="","",IF(IFERROR(DATEVALUE(D68),0)>='Розрахунок'!$B$2-365,"MODEL-365","HISTORICAL_ONLY")) -> MODEL-365
A69: 68 | B69: Київ | C69: Балістика / швидкісні ракети | D69: 2026-01-09 | E69: П’ятниця | F69: 2 | G69: Початок | H69: 1 | I69: Київ + область | J69: Core ballistic | K69: Так | L69: A — пряма/локальна прив’язка | M69: Масована атака Києва та області з балістичною складовою | N69: https://www.pravda.com.ua/news/2026/01/09/7551025/ | O69: https://suspilne.media/kyiv/1252715-rf-atakuvala-kiiv-balistikou-ta-dronami/ | P69: Пряме підтвердження балістики по столиці. | AB69: Київ | AC69: Включено — 09.01: Повітряні сили повідомляли про балістичні ракети наземного базування, спрямовані на Київ; масована комбінована атака столиці підтверджена | AD69: KYI-20260109-092 | AE69: Так | AO69: балістика | AP69: Профіль підтверджено за джерелами аудованого реєстру | AQ69: =IF(D69="","",IF(IFERROR(DATEVALUE(D69),0)<DATE(2024,9,1),"ERA-1 • масовані/ракетно-комбіновані",IF(IFERROR(DATEVALUE(D69),0)<DATE(2025,7,1),"ERA-2 • drone-saturation transition",IF(IFERROR(DATEVALUE(D69),0)<DATE(2026,4,1),"ERA-3 • змішаний / зростання балістики","ERA-4 • поточний балістично-насичений")))) -> ERA-3 • змішаний / зростання балістики | AR69: =IF(D69="","",IF(IFERROR(DATEVALUE(D69),0)>='Розрахунок'!$B$2-365,"MODEL-365","HISTORICAL_ONLY")) -> MODEL-365
A70: 69 | B70: Харків | C70: Балістика / швидкісні ракети | D70: 2026-01-09 | E70: П’ятниця | F70: 2 | G70: Початок | H70: 1 | I70: Харків | J70: Іскандер-М, попередня форензика | K70: Ні | L70: A — пряма локальна прив’язка | M70: 9 січня РФ завдала ракетного удару по Слобідському району Харкова; прокуратура попередньо ідентифікувала Іскандер. | N70: https://suspilne.media/kharkiv/1210058-rf-zavdala-udaru-po-slobidskomu-rajonu-harkova-9-sicna-de-same-zafiksuvali-vlucanna/ | O70: https://t.me/s/prokuratura_kharkiv/26384 | P70: Subtype попередній; city attack-day балістики підтверджено. | R70: ~19:20 | S70: 1 | T70: Підтверджено: 1; subtype попередньо Іскандер-М | V70: Балістика підтверджена | W70: Харків | Z70: https://suspilne.media/kharkiv/1210058-rf-zavdala-udaru-po-slobidskomu-rajonu-harkova-9-sicna-de-same-zafiksuvali-vlucanna/ | AA70: Удар по Слобідському району. | AB70: Харків | AC70: Включено — прямий балістичний удар по Харкову | AD70: KHR-20260109-185 | AE70: Так | AN70: 1 | AO70: балістика Іскандер-М (попередньо) | AP70: Профіль підтверджено за двома джерелами | AQ70: =IF(D70="","",IF(IFERROR(DATEVALUE(D70),0)<DATE(2024,9,1),"ERA-1 • масовані/ракетно-комбіновані",IF(IFERROR(DATEVALUE(D70),0)<DATE(2025,7,1),"ERA-2 • drone-saturation transition",IF(IFERROR(DATEVALUE(D70),0)<DATE(2026,4,1),"ERA-3 • змішаний / зростання балістики","ERA-4 • поточний балістично-насичений")))) -> ERA-3 • змішаний / зростання балістики | AR70: =IF(D70="","",IF(IFERROR(DATEVALUE(D70),0)>='Розрахунок'!$B$2-365,"MODEL-365","HISTORICAL_ONLY")) -> MODEL-365
A71: 70 | B71: Київ | C71: Балістика / швидкісні ракети | D71: 2026-01-13 | E71: Вівторок | F71: 2 | G71: Середина | H71: 1 | I71: Київ | J71: Балістичні ракети | K71: Ні/ракетний епізод | L71: A — пряма локальна прив’язка до Києва | M71: У ніч на 13 січня російська армія завдала ударів по Києву балістичними ракетами; КМВА прямо повідомила про балістичну атаку. | N71: https://suspilne.media/kyiv/1212090-rf-u-nic-na-13-sicna-atakuvala-stolicu-balistikou/ | O71: https://lb.ua/society/2026/01/13/716516_rosiyani_atakuvali_balistikoyu.html | P71: Пряме локальне підтвердження; кількість і підтип ракет локально не домислюємо. | T71: Локальну кількість не встановлюємо | V71: Балістика підтверджена | W71: Київ | Z71: https://suspilne.media/kyiv/1212090-rf-u-nic-na-13-sicna-atakuvala-stolicu-balistikou/ | AA71: Новий епізод, знайдений під час суцільного календарного аудиту. | AB71: Київ | AC71: Включено — аудит 365: пряме локальне/агломераційне підтвердження | AD71: KYI-20260113-091 | AE71: Так | AP71: Профіль включено після повторного аудиту 365 | AQ71: =IF(D71="","",IF(IFERROR(DATEVALUE(D71),0)<DATE(2024,9,1),"ERA-1 • масовані/ракетно-комбіновані",IF(IFERROR(DATEVALUE(D71),0)<DATE(2025,7,1),"ERA-2 • drone-saturation transition",IF(IFERROR(DATEVALUE(D71),0)<DATE(2026,4,1),"ERA-3 • змішаний / зростання балістики","ERA-4 • поточний балістично-насичений")))) -> ERA-3 • змішаний / зростання балістики | AR71: =IF(D71="","",IF(IFERROR(DATEVALUE(D71),0)>='Розрахунок'!$B$2-365,"MODEL-365","HISTORICAL_ONLY")) -> MODEL-365
A72: 71 | B72: Одеса | C72: Балістика / швидкісні ракети | D72: 2026-01-15 | E72: Четвер | F72: 3 | G72: Середина | H72: 1 | I72: Одеський район | J72: Балістична ракета — тип не уточнений | K72: Ні/окремий ракетний епізод | L72: A — пряма/локальна прив’язка | M72: 15 січня балістична ракета влучила в район причалу з контейнерами в Одеському районі; пошкоджено цивільне судно. | N72: https://oda.od.gov.ua/ua/news/sogodni-vden-vorog-znov-zavdav-udaru-po-portovij-infrastrukturi-odeshhini | O72: https://amp.dw.com/uk/rosia-vdarila-balistikou-po-portu-cornomorska/a-75525764 | P72: Офіційне повідомлення Одеської ОДА; тип ракети не вигадуємо. | AB72: Одеса + Одеська область | AC72: Включено — 15.01: офіційно підтверджене влучання балістичної ракети в Одеському районі | AD72: ODS-20260115-090 | AE72: Так | AO72: балістика | AP72: Профіль підтверджено за джерелами аудованого реєстру | AQ72: =IF(D72="","",IF(IFERROR(DATEVALUE(D72),0)<DATE(2024,9,1),"ERA-1 • масовані/ракетно-комбіновані",IF(IFERROR(DATEVALUE(D72),0)<DATE(2025,7,1),"ERA-2 • drone-saturation transition",IF(IFERROR(DATEVALUE(D72),0)<DATE(2026,4,1),"ERA-3 • змішаний / зростання балістики","ERA-4 • поточний балістично-насичений")))) -> ERA-3 • змішаний / зростання балістики | AR72: =IF(D72="","",IF(IFERROR(DATEVALUE(D72),0)>='Розрахунок'!$B$2-365,"MODEL-365","HISTORICAL_ONLY")) -> MODEL-365
A73: 72 | B73: Миколаїв | C73: Балістика / швидкісні ракети | D73: 2026-01-15 | E73: Четвер | F73: 3 | G73: Середина | H73: 1 | I73: Передмістя Миколаєва | J73: Іскандер-М — попередньо; 2 балістичні ракети | K73: Ні | L73: B — балістика підтверджена, exact suburb не розкритий | M73: Вранці 15 січня РФ завдала балістичного удару по передмістю Миколаєва. Повідомлялося про дві балістичні ракети; попередньо — Іскандер-М. | N73: https://suspilne.media/mykolaiv/1215064-udar-iskanderom-ta-ataka-droniv-ak-minula-doba-na-mikolaivsini/ | O73: https://unn.ua/news/u-mykolaievi-vybukhy-na-tli-zahrozy-balistyky | P73: Включено до city+near-agglomeration з B-рівнем географії: передмістя підтверджене, конкретний населений пункт публічно не названий. | R73: ~07:20–09:30 | S73: 2 | T73: Підтверджено: 2; subtype попередньо Іскандер-М | V73: Балістика підтверджена | W73: Передмістя Миколаєва | Z73: https://suspilne.media/mykolaiv/1215064-udar-iskanderom-ta-ataka-droniv-ak-minula-doba-na-mikolaivsini/ | AA73: Удар по відкритій місцевості; без викликів екстрених служб. | AB73: Ближня агломерація Миколаєва | AC73: Включено з B-рівнем географії — дві балістичні ракети по передмістю Миколаєва | AD73: MYK-20260115-201 | AE73: Так | AN73: 2 | AO73: балістика Іскандер-М (попередньо) | AP73: Профіль включено з B-рівнем географії | AQ73: =IF(D73="","",IF(IFERROR(DATEVALUE(D73),0)<DATE(2024,9,1),"ERA-1 • масовані/ракетно-комбіновані",IF(IFERROR(DATEVALUE(D73),0)<DATE(2025,7,1),"ERA-2 • drone-saturation transition",IF(IFERROR(DATEVALUE(D73),0)<DATE(2026,4,1),"ERA-3 • змішаний / зростання балістики","ERA-4 • поточний балістично-насичений")))) -> ERA-3 • змішаний / зростання балістики | AR73: =IF(D73="","",IF(IFERROR(DATEVALUE(D73),0)>='Розрахунок'!$B$2-365,"MODEL-365","HISTORICAL_ONLY")) -> MODEL-365
A74: 73 | B74: Київ | C74: Балістика / швидкісні ракети | D74: 2026-01-20 | E74: Вівторок | F74: 3 | G74: Середина | H74: 1 | I74: Київ + область | J74: Core ballistic | K74: Так | L74: A — пряма/локальна прив’язка | M74: Масована комбінована атака Києва та області з балістичною складовою | N74: https://www.pravda.com.ua/news/2026/01/20/7552801/ | O74: https://suspilne.media/kyiv/1263915-ataka-na-kiiv-ta-oblast-e-zagibli-ta-poraneni/ | P74: Пряме підтвердження балістики по столиці. | AB74: Київ | AC74: Включено — 20.01: комбінований удар із балістичними ракетами, основний напрямок — Київщина; локальні наслідки в Києві підтверджені | AD74: KYI-20260120-089 | AE74: Так | AO74: балістика | AP74: Профіль підтверджено за джерелами аудованого реєстру | AQ74: =IF(D74="","",IF(IFERROR(DATEVALUE(D74),0)<DATE(2024,9,1),"ERA-1 • масовані/ракетно-комбіновані",IF(IFERROR(DATEVALUE(D74),0)<DATE(2025,7,1),"ERA-2 • drone-saturation transition",IF(IFERROR(DATEVALUE(D74),0)<DATE(2026,4,1),"ERA-3 • змішаний / зростання балістики","ERA-4 • поточний балістично-насичений")))) -> ERA-3 • змішаний / зростання балістики | AR74: =IF(D74="","",IF(IFERROR(DATEVALUE(D74),0)>='Розрахунок'!$B$2-365,"MODEL-365","HISTORICAL_ONLY")) -> MODEL-365
A75: 74 | B75: Кривий Ріг | C75: Балістика / швидкісні ракети | D75: 2026-01-21 | E75: Середа | F75: 3 | G75: Кінець | H75: 1 | I75: Кривий Ріг | J75: Іскандер-М | K75: Ні | L75: A — пряма локальна прив’язка | M75: 21 січня Кривий Ріг атаковано балістичною ракетою Іскандер-М; удар припав по житловій забудові. | N75: https://fakty.com.ua/ua/proisshestvija/20260121-unochi-rf-raketoyu-vdaryla-po-kryvomu-rogu-poshkodzheni-budynky-ta-avtivky/ | O75: https://1kr.ua/ua/news-108954.html | P75: Пряме підтвердження балістичної ракети та типу Іскандер-М. | S75: 1 | T75: Одна ракета | V75: Балістика та subtype підтверджені | W75: Кривий Ріг | Y75: 14 | Z75: https://fakty.com.ua/ua/proisshestvija/20260121-unochi-rf-raketoyu-vdaryla-po-kryvomu-rogu-poshkodzheni-budynky-ta-avtivky/ | AA75: Пошкоджено 9 приватних та 5 багатоквартирних будинків; не прирівнюємо це до 14 прямих балістичних влучань. | AB75: Кривий Ріг | AC75: Включено — прямий удар Іскандер-М по Кривому Рогу | AD75: KRR-20260121-162 | AE75: Так | AN75: 1 | AO75: балістика | AP75: Профіль підтверджено | AQ75: =IF(D75="","",IF(IFERROR(DATEVALUE(D75),0)<DATE(2024,9,1),"ERA-1 • масовані/ракетно-комбіновані",IF(IFERROR(DATEVALUE(D75),0)<DATE(2025,7,1),"ERA-2 • drone-saturation transition",IF(IFERROR(DATEVALUE(D75),0)<DATE(2026,4,1),"ERA-3 • змішаний / зростання балістики","ERA-4 • поточний балістично-насичений")))) -> ERA-3 • змішаний / зростання балістики | AR75: =IF(D75="","",IF(IFERROR(DATEVALUE(D75),0)>='Розрахунок'!$B$2-365,"MODEL-365","HISTORICAL_ONLY")) -> MODEL-365
A76: 75 | B76: Кривий Ріг | C76: Балістика / швидкісні ракети | D76: 2026-01-22 | E76: Четвер | F76: 4 | G76: Кінець | H76: 1 | I76: Кривий Ріг | J76: Іскандер-М — попередньо | K76: Так | L76: A — пряма локальна прив’язка | M76: 22 січня комбінована атака Кривого Рогу тривала майже добу: понад 70 БпЛА та балістична ракета, попередньо Іскандер-М. | N76: https://hromadske.ua/viyna/258307-kombinovana-ataka-po-kryvomu-rohu-tryvala-mayze-dobu-vilkul | O76: https://russian-torturers.org/en/crimes/22-sicnia-2026-roku-m-krivii-rig-dnipropetrovskoyi-oblasti | P76: Точну кількість БпЛА в числове поле не переносимо: джерело дає «понад 70». | S76: 1 | T76: Одна балістична ракета | V76: Балістика підтверджена; Іскандер-М попередньо | W76: Кривий Ріг | AA76: Комбінована атака; наслідки не приписуємо виключно балістиці. | AB76: Кривий Ріг | AC76: Включено — підтверджена балістична фаза комбінованої атаки | AD76: KRR-20260122-163 | AE76: Так | AH76: Так | AO76: балістика + понад 70 БпЛА | AP76: Профіль підтверджено | AQ76: =IF(D76="","",IF(IFERROR(DATEVALUE(D76),0)<DATE(2024,9,1),"ERA-1 • масовані/ракетно-комбіновані",IF(IFERROR(DATEVALUE(D76),0)<DATE(2025,7,1),"ERA-2 • drone-saturation transition",IF(IFERROR(DATEVALUE(D76),0)<DATE(2026,4,1),"ERA-3 • змішаний / зростання балістики","ERA-4 • поточний балістично-насичений")))) -> ERA-3 • змішаний / зростання балістики | AR76: =IF(D76="","",IF(IFERROR(DATEVALUE(D76),0)>='Розрахунок'!$B$2-365,"MODEL-365","HISTORICAL_ONLY")) -> MODEL-365
A77: 76 | B77: Київ | C77: Балістика / швидкісні ракети | D77: 2026-01-24 | E77: Субота | F77: 4 | G77: Кінець | H77: 1 | I77: Київ + область | J77: Core ballistic | K77: Так | L77: A — пряма/локальна прив’язка | M77: Нічна атака Києва та Київщини балістикою та БпЛА | N77: https://www.pravda.com.ua/news/2026/01/24/7553468/ | O77: https://suspilne.media/kyiv/1267995-rf-atakuvala-kiiv-balistikou-ta-dronami/ | P77: Пряме підтвердження балістичної складової. | AB77: Київ | AC77: Включено — 24.01: масована комбінована атака Києва із застосуванням балістичних ракет підтверджена | AD77: KYI-20260124-088 | AE77: Так | AH77: Так | AO77: балістика + БпЛА | AP77: Профіль підтверджено за джерелами аудованого реєстру | AQ77: =IF(D77="","",IF(IFERROR(DATEVALUE(D77),0)<DATE(2024,9,1),"ERA-1 • масовані/ракетно-комбіновані",IF(IFERROR(DATEVALUE(D77),0)<DATE(2025,7,1),"ERA-2 • drone-saturation transition",IF(IFERROR(DATEVALUE(D77),0)<DATE(2026,4,1),"ERA-3 • змішаний / зростання балістики","ERA-4 • поточний балістично-насичений")))) -> ERA-3 • змішаний / зростання балістики | AR77: =IF(D77="","",IF(IFERROR(DATEVALUE(D77),0)>='Розрахунок'!$B$2-365,"MODEL-365","HISTORICAL_ONLY")) -> MODEL-365
A78: 77 | B78: Харків | C78: Балістика / швидкісні ракети | D78: 2026-01-24 | E78: Субота | F78: 4 | G78: Кінець | H78: 1 | I78: Харків | J78: Іскандер-М, попередня форензика | K78: Ні | L78: A — пряма локальна прив’язка | M78: 24 січня ракета, попередньо Іскандер-М, вдарила по цивільному підприємству в Індустріальному районі Харкова. | N78: https://suspilne.media/kharkiv/1222080-armia-rf-poperedno-vdarila-po-civilnomu-pidpriemstvu-v-harkovi-raketou-iskander-oblprokuratura/ | O78: https://www.objectiv.tv/uk/objectively/2026/01/24/ponad-100-shahediv-litali-nad-regionom-po-harkovu-vdarila-i-raketa-foto/ | P78: Subtype попередній; локальна ракетна/балістична атрибуція підтверджена прокуратурою. | S78: 1 | T78: Підтверджено: 1; subtype попередній | V78: Балістика підтверджена | W78: Харків | Z78: https://suspilne.media/kharkiv/1222080-armia-rf-poperedno-vdarila-po-civilnomu-pidpriemstvu-v-harkovi-raketou-iskander-oblprokuratura/ | AA78: Пряме локальне влучання. | AB78: Харків | AC78: Включено — прямий балістичний удар по Харкову | AD78: KHR-20260124-186 | AE78: Так | AN78: 1 | AO78: балістика Іскандер-М (попередньо) | AP78: Профіль підтверджено за двома джерелами | AQ78: =IF(D78="","",IF(IFERROR(DATEVALUE(D78),0)<DATE(2024,9,1),"ERA-1 • масовані/ракетно-комбіновані",IF(IFERROR(DATEVALUE(D78),0)<DATE(2025,7,1),"ERA-2 • drone-saturation transition",IF(IFERROR(DATEVALUE(D78),0)<DATE(2026,4,1),"ERA-3 • змішаний / зростання балістики","ERA-4 • поточний балістично-насичений")))) -> ERA-3 • змішаний / зростання балістики | AR78: =IF(D78="","",IF(IFERROR(DATEVALUE(D78),0)>='Розрахунок'!$B$2-365,"MODEL-365","HISTORICAL_ONLY")) -> MODEL-365
A79: 78 | B79: Кривий Ріг | C79: Балістика / швидкісні ракети | D79: 2026-01-28 | E79: Середа | F79: 4 | G79: Кінець | H79: 1 | I79: Кривий Ріг | J79: Балістична ракета — тип не уточнений | K79: Ні | L79: A — пряма локальна прив’язка | M79: 28 січня Росія вдарила балістичною ракетою по об’єкту інфраструктури у Кривому Розі; є поранені. | N79: https://war.obozrevatel.com/ukr/rosiya-vdarila-balistikoyu-po-obektu-infrastrukturi-v-krivomu-rozi-e-poraneni.htm | O79: https://fakty.com.ua/ua/proisshestvija/20260128-raketna-ataka-kryvogo-rogu-28-sichnya-2026-roku-naslidky-ataky/ | P79: Тип ракети не уточнюємо без прямого підтвердження. | S79: 1 | T79: Одна балістична ракета за повідомленнями про удар | V79: Балістика підтверджена | W79: Кривий Ріг | AB79: Кривий Ріг | AC79: Включено — пряме підтвердження балістичного удару | AD79: KRR-20260128-164 | AE79: Так | AN79: 1 | AO79: балістика | AP79: Профіль підтверджено | AQ79: =IF(D79="","",IF(IFERROR(DATEVALUE(D79),0)<DATE(2024,9,1),"ERA-1 • масовані/ракетно-комбіновані",IF(IFERROR(DATEVALUE(D79),0)<DATE(2025,7,1),"ERA-2 • drone-saturation transition",IF(IFERROR(DATEVALUE(D79),0)<DATE(2026,4,1),"ERA-3 • змішаний / зростання балістики","ERA-4 • поточний балістично-насичений")))) -> ERA-3 • змішаний / зростання балістики | AR79: =IF(D79="","",IF(IFERROR(DATEVALUE(D79),0)>='Розрахунок'!$B$2-365,"MODEL-365","HISTORICAL_ONLY")) -> MODEL-365
A80: 79 | B80: Київ | C80: Балістика / швидкісні ракети | D80: 2026-02-03 | E80: Вівторок | F80: 1 | G80: Початок | H80: 1 | I80: Київ + область | J80: Core ballistic | K80: Так | L80: A — пряма/локальна прив’язка | M80: Масована атака Києва та області з балістичною складовою | N80: https://www.pravda.com.ua/news/2026/02/03/7555137/ | O80: https://suspilne.media/kyiv/1278185-ataka-na-kiiv-ta-oblast-e-zagibli-ta-poraneni/ | P80: Пряме підтвердження балістики по столиці. | AB80: Київ | AC80: Включено — 03.02: пряме підтвердження атаки Києва балістичними ракетами | AD80: KYI-20260203-087 | AE80: Так | AO80: балістика | AP80: Профіль підтверджено за джерелами аудованого реєстру | AQ80: =IF(D80="","",IF(IFERROR(DATEVALUE(D80),0)<DATE(2024,9,1),"ERA-1 • масовані/ракетно-комбіновані",IF(IFERROR(DATEVALUE(D80),0)<DATE(2025,7,1),"ERA-2 • drone-saturation transition",IF(IFERROR(DATEVALUE(D80),0)<DATE(2026,4,1),"ERA-3 • змішаний / зростання балістики","ERA-4 • поточний балістично-насичений")))) -> ERA-3 • змішаний / зростання балістики | AR80: =IF(D80="","",IF(IFERROR(DATEVALUE(D80),0)>='Розрахунок'!$B$2-365,"MODEL-365","HISTORICAL_ONLY")) -> MODEL-365
A81: 80 | B81: Одеса | C81: Балістика / швидкісні ракети | D81: 2026-02-04 | E81: Середа | F81: 1 | G81: Початок | H81: 1 | I81: Одеса + Одеська область | J81: Іскандер-М | K81: Так | L81: A — пряма/локальна прив’язка | M81: Увечері Білгород-Дністровський район атаковано Іскандер-М; також застосовано Х-31П. | N81: https://rada.crimea.ua/rosijski-ataki-na-ukrainski-porti-chornogo-morja-v-sichni-ljutomu-2026-roku-baza-danih/ | O81: https://rada.crimea.ua/rosijski-ataki-na-ukrainski-porti-chornogo-morja-v-sichni-berezni-2026-roku-baza-danih/ | P81: Одеська область входить у модель Одеса. | S81: 1 | T81: Підтверджено | V81: Підтверджено | AB81: Одеса + Одеська область | AC81: Включено — підтверджений балістичний епізод по моделі Одеса + Одеська область | AD81: ODS-20260204-086 | AE81: Так | AF81: Так | AL81: Так | AO81: балістика + інші ракети | AP81: Профіль підтверджено за джерелами аудованого реєстру | AQ81: =IF(D81="","",IF(IFERROR(DATEVALUE(D81),0)<DATE(2024,9,1),"ERA-1 • масовані/ракетно-комбіновані",IF(IFERROR(DATEVALUE(D81),0)<DATE(2025,7,1),"ERA-2 • drone-saturation transition",IF(IFERROR(DATEVALUE(D81),0)<DATE(2026,4,1),"ERA-3 • змішаний / зростання балістики","ERA-4 • поточний балістично-насичений")))) -> ERA-3 • змішаний / зростання балістики | AR81: =IF(D81="","",IF(IFERROR(DATEVALUE(D81),0)>='Розрахунок'!$B$2-365,"MODEL-365","HISTORICAL_ONLY")) -> MODEL-365
A82: 81 | B82: Кривий Ріг | C82: Балістика / швидкісні ракети | D82: 2026-02-04 | E82: Середа | F82: 1 | G82: Початок | H82: 1 | I82: Кривий Ріг | J82: Балістична ракета — тип не уточнений | K82: Ні | L82: A — пряма локальна прив’язка | M82: 4 лютого Кривий Ріг атаковано балістикою; удар припав по інфраструктурному об’єкту. | N82: https://rudana.com.ua/calendar/2026/02/04 | O82: https://suspilne.media/dnipro/1230979-zertvi-obstriliv-pogoda-golovni-novini-dnipra-ta-oblasti-4-lutogo/ | P82: Локальна влада прямо повідомила про балістичний удар; subtype не встановлюємо. | T82: Кількість локально не уточнена | V82: Балістика підтверджена | W82: Кривий Ріг | AB82: Кривий Ріг | AC82: Включено — пряме локальне підтвердження балістики | AD82: KRR-20260204-165 | AE82: Так | AO82: балістика | AP82: Профіль підтверджено | AQ82: =IF(D82="","",IF(IFERROR(DATEVALUE(D82),0)<DATE(2024,9,1),"ERA-1 • масовані/ракетно-комбіновані",IF(IFERROR(DATEVALUE(D82),0)<DATE(2025,7,1),"ERA-2 • drone-saturation transition",IF(IFERROR(DATEVALUE(D82),0)<DATE(2026,4,1),"ERA-3 • змішаний / зростання балістики","ERA-4 • поточний балістично-насичений")))) -> ERA-3 • змішаний / зростання балістики | AR82: =IF(D82="","",IF(IFERROR(DATEVALUE(D82),0)>='Розрахунок'!$B$2-365,"MODEL-365","HISTORICAL_ONLY")) -> MODEL-365
A83: 82 | B83: Київ | C83: Балістика / швидкісні ракети | D83: 2026-02-07 | E83: Субота | F83: 1 | G83: Початок | H83: 1 | I83: Київ + область | J83: Core ballistic | K83: Так | L83: A — пряма/локальна прив’язка | M83: Масована комбінована атака Києва та області з балістичною складовою | N83: https://www.pravda.com.ua/news/2026/02/07/7555809/ | O83: https://suspilne.media/kyiv/1282265-ataka-na-kiiv-ta-oblast-e-zagibli-ta-poraneni/ | P83: Пряме підтвердження балістики по столиці. | AB83: Поза city-only / архів аудиту | AC83: Виключено — 07.02: була тривога через загрозу балістики, але прямого підтвердження балістичного удару по Києву не встановлено | AD83: KYI-20260207-085 | AE83: Ні | AP83: Профіль не включено до чистої моделі; збережено для аудиту | AQ83: =IF(D83="","",IF(IFERROR(DATEVALUE(D83),0)<DATE(2024,9,1),"ERA-1 • масовані/ракетно-комбіновані",IF(IFERROR(DATEVALUE(D83),0)<DATE(2025,7,1),"ERA-2 • drone-saturation transition",IF(IFERROR(DATEVALUE(D83),0)<DATE(2026,4,1),"ERA-3 • змішаний / зростання балістики","ERA-4 • поточний балістично-насичений")))) -> ERA-3 • змішаний / зростання балістики | AR83: =IF(D83="","",IF(IFERROR(DATEVALUE(D83),0)>='Розрахунок'!$B$2-365,"MODEL-365","HISTORICAL_ONLY")) -> MODEL-365
A84: 83 | B84: Київ | C84: Балістика / швидкісні ракети | D84: 2026-02-12 | E84: Четвер | F84: 2 | G84: Середина | H84: 1 | I84: Київ | J84: Іскандер-М/С-300 | K84: Так | L84: A — пряма локальна прив’язка до Києва | M84: У ніч на 12 лютого Київ атаковано балістичними ракетами; у столиці є постраждалі та пошкодження. | N84: https://suspilne.media/kyiv/1237990-rosia-vnoci-atakuvala-kiiv-balisticnimi-raketami-e-postrazdali/ | O84: https://www.pravda.com.ua/news/2026/02/12/8020610/ | P84: Пряме підтвердження балістичного удару по столиці; загальноукраїнську кількість ракет не переносимо на Київ. | T84: Локальну кількість не встановлюємо | V84: Балістика підтверджена | W84: Київ | Z84: https://suspilne.media/kyiv/1237990-rosia-vnoci-atakuvala-kiiv-balisticnimi-raketami-e-postrazdali/ | AA84: Новий епізод, пропущений у старому реєстрі. | AB84: Київ | AC84: Включено — аудит 365: пряме локальне/агломераційне підтвердження | AD84: KYI-20260212-084 | AE84: Так | AP84: Профіль включено після повторного аудиту 365 | AQ84: =IF(D84="","",IF(IFERROR(DATEVALUE(D84),0)<DATE(2024,9,1),"ERA-1 • масовані/ракетно-комбіновані",IF(IFERROR(DATEVALUE(D84),0)<DATE(2025,7,1),"ERA-2 • drone-saturation transition",IF(IFERROR(DATEVALUE(D84),0)<DATE(2026,4,1),"ERA-3 • змішаний / зростання балістики","ERA-4 • поточний балістично-насичений")))) -> ERA-3 • змішаний / зростання балістики | AR84: =IF(D84="","",IF(IFERROR(DATEVALUE(D84),0)>='Розрахунок'!$B$2-365,"MODEL-365","HISTORICAL_ONLY")) -> MODEL-365
A85: 84 | B85: Київ | C85: Балістика / швидкісні ракети | D85: 2026-02-14 | E85: Субота | F85: 2 | G85: Початок | H85: 1 | I85: Київ + область | J85: Core ballistic | K85: Так | L85: A — пряма/локальна прив’язка | M85: Нічна атака Києва та Київщини з балістичною складовою | N85: https://www.pravda.com.ua/news/2026/02/14/7556971/ | O85: https://suspilne.media/kyiv/1289395-ataka-na-kiiv-ta-oblast-e-zagibli-ta-poraneni/ | P85: Пряме підтвердження балістики по столиці. | AB85: Поза city-only / архів аудиту | AC85: Виключено — 14.02: перевірені локальні повідомлення фіксують удар БпЛА по Вишгородському району; балістичний удар по Києву не підтверджено | AD85: KYI-20260214-083 | AE85: Ні | AP85: Профіль не включено до чистої моделі; збережено для аудиту | AQ85: =IF(D85="","",IF(IFERROR(DATEVALUE(D85),0)<DATE(2024,9,1),"ERA-1 • масовані/ракетно-комбіновані",IF(IFERROR(DATEVALUE(D85),0)<DATE(2025,7,1),"ERA-2 • drone-saturation transition",IF(IFERROR(DATEVALUE(D85),0)<DATE(2026,4,1),"ERA-3 • змішаний / зростання балістики","ERA-4 • поточний балістично-насичений")))) -> ERA-3 • змішаний / зростання балістики | AR85: =IF(D85="","",IF(IFERROR(DATEVALUE(D85),0)>='Розрахунок'!$B$2-365,"MODEL-365","HISTORICAL_ONLY")) -> MODEL-365
A86: 85 | B86: Кривий Ріг | C86: Балістика / швидкісні ракети | D86: 2026-02-16 | E86: Понеділок | F86: 3 | G86: Середина | H86: 1 | I86: Кривий Ріг | J86: Балістична ракета — тип не уточнений | K86: Ні | L86: A — пряма локальна прив’язка | M86: 16 лютого близько 20:00 Кривий Ріг зазнав балістичного удару по транспортній інфраструктурі. | N86: https://rudana.com.ua/calendar/2026/02/16 | O86: https://fakty.com.ua/ua/proisshestvija/20260216-vybuhy-u-kryvomu-rozi-shho-stalosya-sogodni-16-lyutogo-2026-roku/amp/ | P86: Тип і точну кількість ракет не вигадуємо. | T86: Кількість локально не уточнена | V86: Балістика підтверджена | W86: Кривий Ріг | AB86: Кривий Ріг | AC86: Включено — підтверджений балістичний удар по транспортній інфраструктурі | AD86: KRR-20260216-166 | AE86: Так | AO86: балістика | AP86: Профіль підтверджено | AQ86: =IF(D86="","",IF(IFERROR(DATEVALUE(D86),0)<DATE(2024,9,1),"ERA-1 • масовані/ракетно-комбіновані",IF(IFERROR(DATEVALUE(D86),0)<DATE(2025,7,1),"ERA-2 • drone-saturation transition",IF(IFERROR(DATEVALUE(D86),0)<DATE(2026,4,1),"ERA-3 • змішаний / зростання балістики","ERA-4 • поточний балістично-насичений")))) -> ERA-3 • змішаний / зростання балістики | AR86: =IF(D86="","",IF(IFERROR(DATEVALUE(D86),0)>='Розрахунок'!$B$2-365,"MODEL-365","HISTORICAL_ONLY")) -> MODEL-365
A87: 86 | B87: Кривий Ріг | C87: Балістика / швидкісні ракети | D87: 2026-02-17 | E87: Вівторок | F87: 3 | G87: Середина | H87: 1 | I87: Кривий Ріг | J87: Балістична ракета — тип не уточнений | K87: Ні | L87: A — пряма локальна прив’язка | M87: 17 лютого Кривий Ріг повторно атаковано балістикою; ціллю була транспортна інфраструктура. | N87: https://fakty.com.ua/ua/proisshestvija/20260217-vybuhy-u-kryvomu-rozi-shho-stalosya-sogodni-17-lyutogo-2026-roku/ | O87: https://1kr.ua/ua/news-109800.html | P87: Окремий епізод від удару 16.02; не об’єднувати в одну атаку. | T87: Кількість локально не уточнена | V87: Балістика підтверджена | W87: Кривий Ріг | AB87: Кривий Ріг | AC87: Включено — окремий підтверджений балістичний епізод | AD87: KRR-20260217-167 | AE87: Так | AO87: балістика | AP87: Профіль підтверджено | AQ87: =IF(D87="","",IF(IFERROR(DATEVALUE(D87),0)<DATE(2024,9,1),"ERA-1 • масовані/ракетно-комбіновані",IF(IFERROR(DATEVALUE(D87),0)<DATE(2025,7,1),"ERA-2 • drone-saturation transition",IF(IFERROR(DATEVALUE(D87),0)<DATE(2026,4,1),"ERA-3 • змішаний / зростання балістики","ERA-4 • поточний балістично-насичений")))) -> ERA-3 • змішаний / зростання балістики | AR87: =IF(D87="","",IF(IFERROR(DATEVALUE(D87),0)>='Розрахунок'!$B$2-365,"MODEL-365","HISTORICAL_ONLY")) -> MODEL-365
A88: 87 | B88: Харків | C88: Балістика / швидкісні ракети | D88: 2026-02-20 | E88: П’ятниця | F88: 3 | G88: Середина | H88: 1 | I88: Харків | J88: Іскандер-М, попередня форензика | K88: Ні | L88: A — пряма локальна прив’язка | M88: 20 лютого ракета, попередньо Іскандер-М, вдарила по Слобідському району Харкова. | N88: https://suspilne.media/kharkiv/1245052-rf-zavdala-raketnogo-udaru-po-slobidskomu-rajonu-harkova-poskodzeno-budivlu-avto-ta-bagatopoverhivki/ | O88: https://infocity.kharkiv.ua/proisshestvija/armiia-rf-zavdala-udariv-po-kharkovu-ta-oblasti-ie-postrazhdali/ | P88: Subtype попередній; city ballistic attack-day підтверджено. | Q88: 2026-02-20 | R88: ~05:10 | S88: 1 | T88: Підтверджено: 1; subtype попередній | V88: Балістика підтверджена | W88: Харків | Z88: https://suspilne.media/kharkiv/1245052-rf-zavdala-raketnogo-udaru-po-slobidskomu-rajonu-harkova-poskodzeno-budivlu-avto-ta-bagatopoverhivki/ | AA88: Пошкодження у Слобідському районі. | AB88: Харків | AC88: Включено — прямий балістичний удар по Харкову | AD88: KHR-20260220-187 | AE88: Так | AN88: 1 | AO88: балістика Іскандер-М (попередньо) | AP88: Профіль підтверджено за двома джерелами | AQ88: =IF(D88="","",IF(IFERROR(DATEVALUE(D88),0)<DATE(2024,9,1),"ERA-1 • масовані/ракетно-комбіновані",IF(IFERROR(DATEVALUE(D88),0)<DATE(2025,7,1),"ERA-2 • drone-saturation transition",IF(IFERROR(DATEVALUE(D88),0)<DATE(2026,4,1),"ERA-3 • змішаний / зростання балістики","ERA-4 • поточний балістично-насичений")))) -> ERA-3 • змішаний / зростання балістики | AR88: =IF(D88="","",IF(IFERROR(DATEVALUE(D88),0)>='Розрахунок'!$B$2-365,"MODEL-365","HISTORICAL_ONLY")) -> MODEL-365
A89: 88 | B89: Київ | C89: Балістика / швидкісні ракети | D89: 2026-02-21 | E89: Субота | F89: 3 | G89: Середина | H89: 1 | I89: Київ + область | J89: Core ballistic | K89: Так | L89: A — пряма/локальна прив’язка | M89: Масована атака Києва та області балістикою та БпЛА | N89: https://www.pravda.com.ua/news/2026/02/21/7558133/ | O89: https://suspilne.media/kyiv/1296525-rf-atakuvala-kiiv-balistikou-ta-dronami/ | P89: Пряме підтвердження балістичної складової. | AB89: Поза city-only / архів аудиту | AC89: Виключено — 21.02: у ніч на 21.02 Повітряні сили фіксували атаку БпЛА; прямого балістичного удару по Києву не підтверджено | AD89: KYI-20260221-082 | AE89: Ні | AH89: Так | AO89: БпЛА | AP89: Профіль не включено до чистої моделі; збережено для аудиту | AQ89: =IF(D89="","",IF(IFERROR(DATEVALUE(D89),0)<DATE(2024,9,1),"ERA-1 • масовані/ракетно-комбіновані",IF(IFERROR(DATEVALUE(D89),0)<DATE(2025,7,1),"ERA-2 • drone-saturation transition",IF(IFERROR(DATEVALUE(D89),0)<DATE(2026,4,1),"ERA-3 • змішаний / зростання балістики","ERA-4 • поточний балістично-насичений")))) -> ERA-3 • змішаний / зростання балістики | AR89: =IF(D89="","",IF(IFERROR(DATEVALUE(D89),0)>='Розрахунок'!$B$2-365,"MODEL-365","HISTORICAL_ONLY")) -> MODEL-365
A90: 89 | B90: Одеса | C90: Балістика / швидкісні ракети | D90: 2026-02-23 | E90: Понеділок | F90: 4 | G90: Кінець | H90: 1 | I90: Одеса + Одеська область | J90: Іскандер-М | K90: Так | L90: A — пряма/локальна прив’язка | M90: Одещину атаковано балістичною ракетою Іскандер-М із ТОТ Криму. | N90: https://ivms.mil.gov.ua/wp-content/uploads/2026/03/dovidka-22.02-28.02.2026.pdf | O90: https://rada.crimea.ua/rosijski-ataki-na-ukrainski-porti-chornogo-morja-v-sichni-berezni-2026-roku-baza-danih/ | P90: ПК Південь. | S90: 1 | T90: Підтверджено | V90: Підтверджено | AB90: Одеса + Одеська область | AC90: Включено — підтверджений балістичний епізод по моделі Одеса + Одеська область | AD90: ODS-20260223-081 | AE90: Так | AO90: балістика | AP90: Профіль підтверджено за джерелами аудованого реєстру | AQ90: =IF(D90="","",IF(IFERROR(DATEVALUE(D90),0)<DATE(2024,9,1),"ERA-1 • масовані/ракетно-комбіновані",IF(IFERROR(DATEVALUE(D90),0)<DATE(2025,7,1),"ERA-2 • drone-saturation transition",IF(IFERROR(DATEVALUE(D90),0)<DATE(2026,4,1),"ERA-3 • змішаний / зростання балістики","ERA-4 • поточний балістично-насичений")))) -> ERA-3 • змішаний / зростання балістики | AR90: =IF(D90="","",IF(IFERROR(DATEVALUE(D90),0)>='Розрахунок'!$B$2-365,"MODEL-365","HISTORICAL_ONLY")) -> MODEL-365
A91: 90 | B91: Одеса | C91: Балістика / швидкісні ракети | D91: 2026-02-25 | E91: Середа | F91: 4 | G91: Кінець | H91: 1 | I91: Одеса + Одеська область | J91: Іскандер-М | K91: Так | L91: A — пряма/локальна прив’язка | M91: Одещину атаковано балістичною ракетою Іскандер-М із ТОТ Криму. | N91: https://ivms.mil.gov.ua/wp-content/uploads/2026/03/dovidka-22.02-28.02.2026.pdf | O91: https://rada.crimea.ua/rosijski-ataki-na-ukrainski-porti-chornogo-morja-v-sichni-berezni-2026-roku-baza-danih/ | P91: ПК Південь. | S91: 1 | T91: Підтверджено | V91: Підтверджено | AB91: Одеса + Одеська область | AC91: Включено — 25.02: ПК Південь підтвердило Іскандер-М по Одещині | AD91: ODS-20260225-080 | AE91: Так | AO91: балістика | AP91: Профіль підтверджено за джерелами аудованого реєстру | AQ91: =IF(D91="","",IF(IFERROR(DATEVALUE(D91),0)<DATE(2024,9,1),"ERA-1 • масовані/ракетно-комбіновані",IF(IFERROR(DATEVALUE(D91),0)<DATE(2025,7,1),"ERA-2 • drone-saturation transition",IF(IFERROR(DATEVALUE(D91),0)<DATE(2026,4,1),"ERA-3 • змішаний / зростання балістики","ERA-4 • поточний балістично-насичений")))) -> ERA-3 • змішаний / зростання балістики | AR91: =IF(D91="","",IF(IFERROR(DATEVALUE(D91),0)>='Розрахунок'!$B$2-365,"MODEL-365","HISTORICAL_ONLY")) -> MODEL-365
A92: 91 | B92: Харків | C92: Балістика / швидкісні ракети | D92: 2026-02-26 | E92: Четвер | F92: 4 | G92: Кінець | H92: 1 | I92: Харків + ближня агломерація | J92: Іскандер-М, 2 ракети | K92: Так | L92: A — пряма локальна прив’язка | M92: У ніч на 26 лютого Харків і ближнє передмістя зазнали комбінованої атаки; прокуратура підтвердила дві балістичні ракети Іскандер-М та ударні БпЛА. | N92: https://kharkivoda.gov.ua/news/134760 | O92: https://infocity.kharkiv.ua/proisshestvija/kombinovanyj-udar-po-kharkovu-ta-peredmistiu-26-liutoho-naslidky/ | P92: Включено за city+agglomeration scope; кількість 2 підтверджена. | Q92: 2026-02-26 | R92: ~03:40–05:40 | S92: 2 | T92: Підтверджено: 2 Іскандер-М | V92: Балістика підтверджена | W92: Харків + ближня агломерація | Z92: https://kharkivoda.gov.ua/news/134760 | AA92: Комбінована атака; наслідки не приписувати лише балістиці. | AB92: Харків + ближня агломерація | AC92: Включено — два Іскандер-М по Харкову/ближній агломерації | AD92: KHR-20260226-188 | AE92: Так | AH92: Так | AM92: 17 | AN92: 2 | AO92: балістика + БпЛА | AP92: Профіль підтверджено за двома джерелами | AQ92: =IF(D92="","",IF(IFERROR(DATEVALUE(D92),0)<DATE(2024,9,1),"ERA-1 • масовані/ракетно-комбіновані",IF(IFERROR(DATEVALUE(D92),0)<DATE(2025,7,1),"ERA-2 • drone-saturation transition",IF(IFERROR(DATEVALUE(D92),0)<DATE(2026,4,1),"ERA-3 • змішаний / зростання балістики","ERA-4 • поточний балістично-насичений")))) -> ERA-3 • змішаний / зростання балістики | AR92: =IF(D92="","",IF(IFERROR(DATEVALUE(D92),0)>='Розрахунок'!$B$2-365,"MODEL-365","HISTORICAL_ONLY")) -> MODEL-365
A93: 92 | B93: Одеса | C93: Балістика / швидкісні ракети | D93: 2026-03-04 | E93: Середа | F93: 1 | G93: Початок | H93: 1 | I93: Одеса + Одеська область | J93: Іскандер-М | K93: Так | L93: A — пряма/локальна прив’язка | M93: Одещину атаковано однією балістичною ракетою Іскандер-М. | N93: https://ivms.mil.gov.ua/wp-content/uploads/2026/03/dovidka-01.03-07.03.2026.pdf | O93: https://www.blackseanews.net/read/243655 | P93: Окремо від ракети по Миколаївщині. | S93: 1 | T93: Підтверджено | V93: Підтверджено | AB93: Одеса + Одеська область | AC93: Включено — підтверджений балістичний епізод по моделі Одеса + Одеська область | AD93: ODS-20260304-079 | AE93: Так | AO93: балістика | AP93: Профіль підтверджено за джерелами аудованого реєстру | AQ93: =IF(D93="","",IF(IFERROR(DATEVALUE(D93),0)<DATE(2024,9,1),"ERA-1 • масовані/ракетно-комбіновані",IF(IFERROR(DATEVALUE(D93),0)<DATE(2025,7,1),"ERA-2 • drone-saturation transition",IF(IFERROR(DATEVALUE(D93),0)<DATE(2026,4,1),"ERA-3 • змішаний / зростання балістики","ERA-4 • поточний балістично-насичений")))) -> ERA-3 • змішаний / зростання балістики | AR93: =IF(D93="","",IF(IFERROR(DATEVALUE(D93),0)>='Розрахунок'!$B$2-365,"MODEL-365","HISTORICAL_ONLY")) -> MODEL-365
A94: 93 | B94: Київ | C94: Балістика / швидкісні ракети | D94: 2026-03-07 | E94: Субота | F94: 1 | G94: Початок | H94: 1 | I94: Київ + область | J94: Core ballistic | K94: Так | L94: A — пряма/локальна прив’язка | M94: Масована комбінована атака Києва та області з балістичною складовою | N94: https://www.pravda.com.ua/news/2026/03/07/7560457/ | O94: https://suspilne.media/kyiv/1310785-ataka-na-kiiv-ta-oblast-e-zagibli-ta-poraneni/ | P94: Пряме підтвердження балістики по столиці. | AB94: Київ | AC94: Включено — 07.03: пряме підтвердження наслідків балістичної атаки по Києву | AD94: KYI-20260307-078 | AE94: Так | AO94: балістика | AP94: Профіль підтверджено за джерелами аудованого реєстру | AQ94: =IF(D94="","",IF(IFERROR(DATEVALUE(D94),0)<DATE(2024,9,1),"ERA-1 • масовані/ракетно-комбіновані",IF(IFERROR(DATEVALUE(D94),0)<DATE(2025,7,1),"ERA-2 • drone-saturation transition",IF(IFERROR(DATEVALUE(D94),0)<DATE(2026,4,1),"ERA-3 • змішаний / зростання балістики","ERA-4 • поточний балістично-насичений")))) -> ERA-3 • змішаний / зростання балістики | AR94: =IF(D94="","",IF(IFERROR(DATEVALUE(D94),0)>='Розрахунок'!$B$2-365,"MODEL-365","HISTORICAL_ONLY")) -> MODEL-365
